Workbook
Name SegmentaciónDeDatos_AÑO: #N/A
Name SegmentaciónDeDatos_AÑO1: #N/A
Name SegmentaciónDeDatos_MES: #N/A
Name SegmentaciónDeDatos_MES1: #N/A

Sheet Ene
A2: DETALLE DE VENTAS 2026
E3: COSTO SIT UNITARIO | H3: COSTO SIT CANTIDAD
A4: GRUPO | B4: REF. | C4: DESCRIPCION | D4: CANT | E4: CUMAT | F4: CUMO | G4: CUNago | H4: CTMAT | I4: CTMO | J4: CTSIT | K4: %PART | L4: CIFU | M4: MOU | N4: CTU | O4: CT | P4: PUV | Q4: PRECIOTOT | R4: %CTO | S4: %Part.
A5: =VLOOKUP(B5,Grupos!$A$2:$B$619,2,FALSE) -> ACCESORIOS | B5: BN-08 | C5: BANDEJA PARA INTERIOR *I-8P* | D5: 1 | E5: 1216.9 | F5: 76.52 | G5: =E5+F5 -> 1293.42 | H5: =E5*D5 -> 1216.9 | I5: =F5*D5 -> 76.52 | J5: =G5*D5 -> 1293.42 | K5: =J5/$J$293 -> 9.7176893e-07 | L5: =$K$364*K5/D5 -> 251.39558 | M5: =F5*$M$363 -> 410.93762 | N5: =G5+L5+M5 -> 1955.7532 | O5: =N5*D5 -> 1955.7532 | P5: =Q5/D5 -> 12075 | Q5: 12075 | R5: =O5/Q5 -> 0.16196714
A6: =VLOOKUP(B6,Grupos!$A$2:$B$619,2,FALSE) -> ACCESORIOS | B6: BN-12 | C6: BANDEJA PARA INTERIOR *I-12P,I-212,I-312 | D6: 4 | E6: 1547.34 | F6: 77.82 | G6: =E6+F6 -> 1625.16 | H6: =E6*D6 -> 6189.36 | I6: =F6*D6 -> 311.28 | J6: =G6*D6 -> 6500.64 | K6: =J6/$J$293 -> 4.8840438e-06 | L6: =$K$364*K6/D6 -> 315.87422 | M6: =F6*$M$363 -> 417.91904 | N6: =G6+L6+M6 -> 2358.9533 | O6: =N6*D6 -> 9435.8131 | P6: =Q6/D6 -> 9492 | Q6: 37968 | R6: =O6/Q6 -> 0.24852015
A7: =VLOOKUP(B7,Grupos!$A$2:$B$619,2,FALSE) -> ACCESORIOS | B7: BN-24 | C7: BANDEJA PARA INTERIOR *I-224,I-324* | D7: 1 | E7: 2376.63 | F7: 89.86 | G7: =E7+F7 -> 2466.49 | H7: =E7*D7 -> 2376.63 | I7: =F7*D7 -> 89.86 | J7: =G7*D7 -> 2466.49 | K7: =J7/$J$293 -> 1.8531168e-06 | L7: =$K$364*K7/D7 -> 479.39932 | M7: =F7*$M$363 -> 482.57781 | N7: =G7+L7+M7 -> 3428.4671 | O7: =N7*D7 -> 3428.4671 | P7: =Q7/D7 -> 15664 | Q7: 15664 | R7: =O7/Q7 -> 0.21887558
A8: =VLOOKUP(B8,Grupos!$A$2:$B$619,2,FALSE) -> ACCESORIOS | B8: CHAPA-1 | C8: CHAPA GAVETA (TRPs) | D8: 3 | E8: 3200 | F8: 0 | G8: =E8+F8 -> 3200 | H8: =E8*D8 -> 9600 | I8: =F8*D8 -> 0 | J8: =G8*D8 -> 9600 | K8: =J8/$J$293 -> 7.2126469e-06 | L8: =$K$364*K8/D8 -> 621.96799 | M8: =F8*$M$363 -> 0 | N8: =G8+L8+M8 -> 3821.968 | O8: =N8*D8 -> 11465.904 | P8: =Q8/D8 -> 13987.5 | Q8: 41962.5 | R8: =O8/Q8 -> 0.27324168
A9: =VLOOKUP(B9,Grupos!$A$2:$B$619,2,FALSE) -> ACCESORIOS | B9: FLETES | C9: VALOR FLETES MERCANCIA | D9: 3 | E9: 0 | F9: 0 | G9: =E9+F9 -> 0 | H9: =E9*D9 -> 0 | I9: =F9*D9 -> 0 | J9: =G9*D9 -> 0 | K9: =J9/$J$293 -> 0 | L9: =$K$364*K9/D9 -> 0 | M9: =F9*$M$363 -> 0 | N9: =G9+L9+M9 -> 0 | O9: =N9*D9 -> 0 | P9: =Q9/D9 -> 147333.33 | Q9: 442000 | R9: =O9/Q9 -> 0
A10: =VLOOKUP(B10,Grupos!$A$2:$B$619,2,FALSE) -> ACCESORIOS | B10: GRAPAM12-D | C10: GRAPA METALICA 1/2" DOBLE | D10: 39600 | E10: 59.89 | F10: 34.71 | G10: =E10+F10 -> 94.6 | H10: =E10*D10 -> 2371644 | I10: =F10*D10 -> 1374516 | J10: =G10*D10 -> 3746160 | K10: =J10/$J$293 -> 0.0028145551 | L10: =$K$364*K10/D10 -> 18.386929 | M10: =F10*$M$363 -> 186.40414 | N10: =G10+L10+M10 -> 299.39107 | O10: =N10*D10 -> 11855886 | P10: =Q10/D10 -> 126.09091 | Q10: 4993200.2 | R10: =O10/Q10 -> 2.3744064
A11: =VLOOKUP(B11,Grupos!$A$2:$B$619,2,FALSE) -> ACCESORIOS | B11: GRAPAM12-S | C11: GRAPA METALICA 1/2" SENCILLA | D11: 2400 | E11: 43.39 | F11: 43.22 | G11: =E11+F11 -> 86.61 | H11: =E11*D11 -> 104136 | I11: =F11*D11 -> 103728 | J11: =G11*D11 -> 207864 | K11: =J11/$J$293 -> 0.00015617184 | L11: =$K$364*K11/D11 -> 16.833952 | M11: =F11*$M$363 -> 232.10564 | N11: =G11+L11+M11 -> 335.54959 | O11: =N11*D11 -> 805319.03 | P11: =Q11/D11 -> 102.50001 | Q11: 246000.02 | R11: =O11/Q11 -> 3.2736543
A12: =VLOOKUP(B12,Grupos!$A$2:$B$619,2,FALSE) -> ACCESORIOS | B12: NEUTRO12 | C12: NEUTRO DE 12 CIRCUITOS | D12: 15 | E12: 2166.94 | F12: 0 | G12: =E12+F12 -> 2166.94 | H12: =E12*D12 -> 32504.1 | I12: =F12*D12 -> 0 | J12: =G12*D12 -> 32504.1 | K12: =J12/$J$293 -> 2.4420895e-05 | L12: =$K$364*K12/D12 -> 421.17729 | M12: =F12*$M$363 -> 0 | N12: =G12+L12+M12 -> 2588.1173 | O12: =N12*D12 -> 38821.759 | P12: =Q12/D12 -> 16952 | Q12: 254280 | R12: =O12/Q12 -> 0.15267327
A13: =VLOOKUP(B13,Grupos!$A$2:$B$619,2,FALSE) -> ACCESORIOS | B13: NEUTRO18 | C13: NEUTRO DE 18 CIRCUITOS | D13: 5 | E13: 3042.06 | F13: 0 | G13: =E13+F13 -> 3042.06 | H13: =E13*D13 -> 15210.3 | I13: =F13*D13 -> 0 | J13: =G13*D13 -> 15210.3 | K13: =J13/$J$293 -> 1.1427763e-05 | L13: =$K$364*K13/D13 -> 591.26998 | M13: =F13*$M$363 -> 0 | N13: =G13+L13+M13 -> 3633.33 | O13: =N13*D13 -> 18166.65 | P13: =Q13/D13 -> 19250 | Q13: 96250 | R13: =O13/Q13 -> 0.18874441
A14: =VLOOKUP(B14,Grupos!$A$2:$B$619,2,FALSE) -> ACCESORIOS | B14: NEUTRO24R | C14: NEUTRO DE 24 CIRCUITOS REFORZADO | D14: 13 | E14: 9036.65 | F14: 0 | G14: =E14+F14 -> 9036.65 | H14: =E14*D14 -> 117476.45 | I14: =F14*D14 -> 0 | J14: =G14*D14 -> 117476.45 | K14: =J14/$J$293 -> 8.8262099e-05 | L14: =$K$364*K14/D14 -> 1756.4085 | M14: =F14*$M$363 -> 0 | N14: =G14+L14+M14 -> 10793.058 | O14: =N14*D14 -> 140309.76 | P14: =Q14/D14 -> 38300.577 | Q14: 497907.5 | R14: =O14/Q14 -> 0.28179885
A15: =VLOOKUP(B15,Grupos!$A$2:$B$619,2,FALSE) -> ACCESORIOS | B15: NEUTRO42R | C15: NEUTRO DE 42 CIRCUITOS REFORZADO | D15: 2 | E15: 14590.87 | F15: 0 | G15: =E15+F15 -> 14590.87 | H15: =E15*D15 -> 29181.74 | I15: =F15*D15 -> 0 | J15: =G15*D15 -> 29181.74 | K15: =J15/$J$293 -> 2.1924748e-05 | L15: =$K$364*K15/D15 -> 2835.9544 | M15: =F15*$M$363 -> 0 | N15: =G15+L15+M15 -> 17426.824 | O15: =N15*D15 -> 34853.649 | P15: =Q15/D15 -> 85125 | Q15: 170250 | R15: =O15/Q15 -> 0.2047204
A16: =VLOOKUP(B16,Grupos!$A$2:$B$619,2,FALSE) -> ACCESORIOS | B16: NEUTRO6 | C16: NEUTRO DE 6 CIRCUITOS | D16: 10 | E16: 1229.39 | F16: 0 | G16: =E16+F16 -> 1229.39 | H16: =E16*D16 -> 12293.9 | I16: =F16*D16 -> 0 | J16: =G16*D16 -> 12293.9 | K16: =J16/$J$293 -> 9.2366208e-06 | L16: =$K$364*K16/D16 -> 238.95038 | M16: =F16*$M$363 -> 0 | N16: =G16+L16+M16 -> 1468.3404 | O16: =N16*D16 -> 14683.404 | P16: =Q16/D16 -> 6776 | Q16: 67760 | R16: =O16/Q16 -> 0.21669722
... A33: =VLOOKUP(B33,Grupos!$A$2:$B$619,2,FALSE) -> ACCESORIOS | B33: TIERRA8ALET | C33: TIERRA 8 CIRCUITOS ALET | D33: 150 | E33: 1201 | F33: 0 | G33: =E33+F33 -> 1201 | H33: =E33*D33 -> 180150 | I33: =F33*D33 -> 0 | J33: =G33*D33 -> 180150 | K33: =J33/$J$293 -> 0.00013534983 | L33: =$K$364*K33/D33 -> 233.43236 | M33: =F33*$M$363 -> 0 | N33: =G33+L33+M33 -> 1434.4324 | O33: =N33*D33 -> 215164.85 | P33: =Q33/D33 -> 9240.0004 | Q33: 1386000.1 | R33: =O33/Q33 -> 0.15524159
A34: Total ACCESORIOS | D34: =SUBTOTAL(9,D5:D33) -> 43103 | H34: =SUBTOTAL(9,H5:H33) -> 3330960.9 | I34: =SUBTOTAL(9,I5:I33) -> 1479744.8 | J34: =SUBTOTAL(9,J5:J33) -> 4810705.7 | O34: =SUBTOTAL(9,O5:O33) -> 13692456 | Q34: =SUBTOTAL(9,Q5:Q33) -> 10984624 | R34: =O34/Q34 -> 1.2465111 | S34: =Q34/$Q$293 -> 0.0033463018
A35: =VLOOKUP(B35,Grupos!$A$2:$B$619,2,FALSE) -> ADAPTADORES | B35: ACAMPANA12 | C35: ADAPTADOR CAMPANA 1/2" | D35: 11200 | E35: 14.92 | F35: 4.79 | G35: =E35+F35 -> 19.71 | H35: =E35*D35 -> 167104 | I35: =F35*D35 -> 53648 | J35: =G35*D35 -> 220752 | K35: =J35/$J$293 -> 0.00016585481 | L35: =$K$364*K35/D35 -> 3.8309341 | M35: =F35*$M$363 -> 25.723878 | N35: =G35+L35+M35 -> 49.264813 | O35: =N35*D35 -> 551765.9 | P35: =Q35/D35 -> 87.857146 | Q35: 984000.04 | R35: =O35/Q35 -> 0.56073768
A36: =VLOOKUP(B36,Grupos!$A$2:$B$619,2,FALSE) -> ADAPTADORES | B36: ACAMPANA34 | C36: ADAPTADOR CAMPANA 3/4" | D36: 3000 | E36: 19.99 | F36: 5.28 | G36: =E36+F36 -> 25.27 | H36: =E36*D36 -> 59970 | I36: =F36*D36 -> 15840 | J36: =G36*D36 -> 75810 | K36: =J36/$J$293 -> 5.6957371e-05 | L36: =$K$364*K36/D36 -> 4.9116035 | M36: =F36*$M$363 -> 28.35534 | N36: =G36+L36+M36 -> 58.536943 | O36: =N36*D36 -> 175610.83 | P36: =Q36/D36 -> 114 | Q36: 341999.99 | R36: =O36/Q36 -> 0.51348198
A37: =VLOOKUP(B37,Grupos!$A$2:$B$619,2,FALSE) -> ADAPTADORES | B37: ADAPTER12 | C37: ADAPTADOR TERMINAL 1/2" | D37: 552000 | E37: 25.93 | F37: 11.01 | G37: =E37+F37 -> 36.94 | H37: =E37*D37 -> 14313360 | I37: =F37*D37 -> 6077520 | J37: =G37*D37 -> 20390880 | K37: =J37/$J$293 -> 0.015320023 | L37: =$K$364*K37/D37 -> 7.179843 | M37: =F37*$M$363 -> 59.127328 | N37: =G37+L37+M37 -> 103.24717 | O37: =N37*D37 -> 56992439 | P37: =Q37/D37 -> 106.51957 | Q37: 58798802 | R37: =O37/Q37 -> 0.96927891
A38: =VLOOKUP(B38,Grupos!$A$2:$B$619,2,FALSE) -> ADAPTADORES | B38: ADAPTER34 | C38: ADAPTADOR TERMINAL 3/4" | D38: 192800 | E38: 39.89 | F38: 11.25 | G38: =E38+F38 -> 51.14 | H38: =E38*D38 -> 7690792 | I38: =F38*D38 -> 2169000 | J38: =G38*D38 -> 9859792 | K38: =J38/$J$293 -> 0.0074078331 | L38: =$K$364*K38/D38 -> 9.939826 | M38: =F38*$M$363 -> 60.416207 | N38: =G38+L38+M38 -> 121.49603 | O38: =N38*D38 -> 23424435 | P38: =Q38/D38 -> 142.29046 | Q38: 27433601 | R38: =O38/Q38 -> 0.85385929
A39: Total ADAPTADORES | D39: =SUBTOTAL(9,D35:D38) -> 759000 | H39: =SUBTOTAL(9,H35:H38) -> 22231226 | I39: =SUBTOTAL(9,I35:I38) -> 8316008 | J39: =SUBTOTAL(9,J35:J38) -> 30547234 | O39: =SUBTOTAL(9,O35:O38) -> 81144250 | Q39: =SUBTOTAL(9,Q35:Q38) -> 87558403 | R39: =O39/Q39 -> 0.92674429 | S39: =Q39/$Q$293 -> 0.02667336
A40: =VLOOKUP(B40,Grupos!$A$2:$B$619,2,FALSE) -> CAJAS ARRANCADORAS | B40: CA-30 | C40: CAJA ARRANCADOR Y CONTROL INDUSTRIAL 30X20X16 | D40: 3 | E40: 30739.86 | F40: 5164.81 | G40: =E40+F40 -> 35904.67 | H40: =E40*D40 -> 92219.58 | I40: =F40*D40 -> 15494.43 | J40: =G40*D40 -> 107714.01 | K40: =J40/$J$293 -> 8.0927408e-05 | L40: =$K$364*K40/D40 -> 6978.6111 | M40: =F40*$M$363 -> 27736.732 | N40: =G40+L40+M40 -> 70620.013 | O40: =N40*D40 -> 211860.04 | P40: =Q40/D40 -> 102543 | Q40: 307629 | R40: =O40/Q40 -> 0.68868682
A41: =VLOOKUP(B41,Grupos!$A$2:$B$619,2,FALSE) -> CAJAS ARRANCADORAS | B41: CA-70 | C41: CAJA ARRANCADOR Y CONTROL INDUSTRIAL 70X50X25 | D41: 7 | E41: 80513.68 | F41: 8176.17 | G41: =E41+F41 -> 88689.85 | H41: =E41*D41 -> 563595.76 | I41: =F41*D41 -> 57233.19 | J41: =G41*D41 -> 620828.95 | K41: =J41/$J$293 -> 0.00046643958 | L41: =$K$364*K41/D41 -> 17238.202 | M41: =F41*$M$363 -> 43908.727 | N41: =G41+L41+M41 -> 149836.78 | O41: =N41*D41 -> 1048857.5 | P41: =Q41/D41 -> 325214.87 | Q41: 2276504.1 | R41: =O41/Q41 -> 0.46073164
A42: =VLOOKUP(B42,Grupos!$A$2:$B$619,2,FALSE) -> CAJAS ARRANCADORAS | B42: CA-80 | C42: CAJA ARRANCADOR Y CONTROL INDUSTRIAL 80X50X25 | D42: 5 | E42: 86707.31 | F42: 10954.65 | G42: =E42+F42 -> 97661.96 | H42: =E42*D42 -> 433536.55 | I42: =F42*D42 -> 54773.25 | J42: =G42*D42 -> 488309.8 | K42: =J42/$J$293 -> 0.00036687564 | L42: =$K$364*K42/D42 -> 18982.067 | M42: =F42*$M$363 -> 58830.08 | N42: =G42+L42+M42 -> 175474.11 | O42: =N42*D42 -> 877370.54 | P42: =Q42/D42 -> 322411 | Q42: 1612055 | R42: =O42/Q42 -> 0.54425596
A43: =VLOOKUP(B43,Grupos!$A$2:$B$619,2,FALSE) -> CAJAS ARRANCADORAS | B43: CA-90 | C43: CAJA ARRANCADOR Y CONTROL INDUSTRIAL 90X50X25 | D43: 2 | E43: 97632.57 | F43: 6348.31 | G43: =E43+F43 -> 103980.88 | H43: =E43*D43 -> 195265.14 | I43: =F43*D43 -> 12696.62 | J43: =G43*D43 -> 207961.76 | K43: =J43/$J$293 -> 0.00015624528 | L43: =$K$364*K43/D43 -> 20210.244 | M43: =F43*$M$363 -> 34092.517 | N43: =G43+L43+M43 -> 158283.64 | O43: =N43*D43 -> 316567.28 | P43: =Q43/D43 -> 359078.77 | Q43: 718157.53 | R43: =O43/Q43 -> 0.44080479
A44: Total CAJAS ARRANCADORAS | D44: =SUBTOTAL(9,D40:D43) -> 17 | H44: =SUBTOTAL(9,H40:H43) -> 1284617 | I44: =SUBTOTAL(9,I40:I43) -> 140197.49 | J44: =SUBTOTAL(9,J40:J43) -> 1424814.5 | O44: =SUBTOTAL(9,O40:O43) -> 2454655.3 | Q44: =SUBTOTAL(9,Q40:Q43) -> 4914345.6 | R44: =O44/Q44 -> 0.49948773 | S44: =Q44/$Q$293 -> 0.001497082
A45: =VLOOKUP(B45,Grupos!$A$2:$B$619,2,FALSE) -> CAJAS EMPALME | B45: CE13-13-8B | C45: CAJA DE EMPALME 13X13X8 BLANCA | D45: 72 | E45: 3093.28 | F45: 1065.47 | G45: =E45+F45 -> 4158.75 | H45: =E45*D45 -> 222716.16 | I45: =F45*D45 -> 76713.84 | J45: =G45*D45 -> 299430 | K45: =J45/$J$293 -> 0.00022496696 | L45: =$K$364*K45/D45 -> 808.31543 | M45: =F45*$M$363 -> 5721.925 | N45: =G45+L45+M45 -> 10688.99 | O45: =N45*D45 -> 769607.31 | P45: =Q45/D45 -> 12158.25 | Q45: 875394.01 | R45: =O45/Q45 -> 0.87915533
A46: =VLOOKUP(B46,Grupos!$A$2:$B$619,2,FALSE) -> CAJAS EMPALME | B46: CE15-15-10B | C46: CAJA DE EMPALME 15X15X10 BLANCA | D46: 1260 | E46: 4183.02 | F46: 784.88 | G46: =E46+F46 -> 4967.9 | H46: =E46*D46 -> 5270605.2 | I46: =F46*D46 -> 988948.8 | J46: =G46*D46 -> 6259554 | K46: =J46/$J$293 -> 0.0047029117 | L46: =$K$364*K46/D46 -> 965.58587 | M46: =F46*$M$363 -> 4215.0642 | N46: =G46+L46+M46 -> 10148.55 | O46: =N46*D46 -> 12787173 | P46: =Q46/D46 -> 13611.714 | Q46: 17150760 | R46: =O46/Q46 -> 0.74557473
A47: =VLOOKUP(B47,Grupos!$A$2:$B$619,2,FALSE) -> CAJAS EMPALME | B47: CE20-15-10B | C47: CAJA DE EMPALME 20X15X10 BLANCA | D47: 44 | E47: 5073.7 | F47: 592.66 | G47: =E47+F47 -> 5666.36 | H47: =E47*D47 -> 223242.8 | I47: =F47*D47 -> 26077.04 | J47: =G47*D47 -> 249319.84 | K47: =J47/$J$293 -> 0.00018731833 | L47: =$K$364*K47/D47 -> 1101.342 | M47: =F47*$M$363 -> 3182.7795 | N47: =G47+L47+M47 -> 9950.4816 | O47: =N47*D47 -> 437821.19 | P47: =Q47/D47 -> 16372.75 | Q47: 720401.02 | R47: =O47/Q47 -> 0.60774649
A48: =VLOOKUP(B48,Grupos!$A$2:$B$619,2,FALSE) -> CAJAS EMPALME | B48: CE20-20-10B | C48: CAJA DE EMPALME 20X20X10 BLANCA | D48: 1740 | E48: 6127.68 | F48: 823.65 | G48: =E48+F48 -> 6951.33 | H48: =E48*D48 -> 10662163 | I48: =F48*D48 -> 1433151 | J48: =G48*D48 -> 12095314 | K48: =J48/$J$293 -> 0.0090874198 | L48: =$K$364*K48/D48 -> 1351.0952 | M48: =F48*$M$363 -> 4423.2719 | N48: =G48+L48+M48 -> 12725.697 | O48: =N48*D48 -> 22142713 | P48: =Q48/D48 -> 18357.333 | Q48: 31941760 | R48: =O48/Q48 -> 0.69322145
A49: =VLOOKUP(B49,Grupos!$A$2:$B$619,2,FALSE) -> CAJAS EMPALME | B49: CE20-20-15B | C49: CAJA DE EMPALME 20X20X15 BLANCA | D49: 1221 | E49: 7494.34 | F49: 780.46 | G49: =E49+F49 -> 8274.8 | H49: =E49*D49 -> 9150589.1 | I49: =F49*D49 -> 952941.66 | J49: =G49*D49 -> 10103531 | K49: =J49/$J$293 -> 0.0075909583 | L49: =$K$364*K49/D49 -> 1608.3315 | M49: =F49*$M$363 -> 4191.3274 | N49: =G49+L49+M49 -> 14074.459 | O49: =N49*D49 -> 17184914 | P49: =Q49/D49 -> 23593.192 | Q49: 28807288 | R49: =O49/Q49 -> 0.59654746
A50: =VLOOKUP(B50,Grupos!$A$2:$B$619,2,FALSE) -> CAJAS EMPALME | B50: CE25-20-10B | C50: CAJA DE EMPALME 25X20X10 BLANCA | D50: 18 | E50: 7089.89 | F50: 482.92 | G50: =E50+F50 -> 7572.81 | H50: =E50*D50 -> 127618.02 | I50: =F50*D50 -> 8692.56 | J50: =G50*D50 -> 136310.58 | K50: =J50/$J$293 -> 0.00010241251 | L50: =$K$364*K50/D50 -> 1471.8892 | M50: =F50*$M$363 -> 2593.4395 | N50: =G50+L50+M50 -> 11638.139 | O50: =N50*D50 -> 209486.5 | P50: =Q50/D50 -> 25256.002 | Q50: 454608.03 | R50: =O50/Q50 -> 0.46080686
A51: =VLOOKUP(B51,Grupos!$A$2:$B$619,2,FALSE) -> CAJAS EMPALME | B51: CE25-25-10B | C51: CAJA DE EMPALME 25X25X10 BLANCA | D51: 795 | E51: 8428.08 | F51: 647.97 | G51: =E51+F51 -> 9076.05 | H51: =E51*D51 -> 6700323.6 | I51: =F51*D51 -> 515136.15 | J51: =G51*D51 -> 7215459.7 | K51: =J51/$J$293 -> 0.0054211003 | L51: =$K$364*K51/D51 -> 1764.0664 | M51: =F51*$M$363 -> 3479.8124 | N51: =G51+L51+M51 -> 14319.929 | O51: =N51*D51 -> 11384343 | P51: =Q51/D51 -> 27317.187 | Q51: 21717164 | R51: =O51/Q51 -> 0.5242095
A52: =VLOOKUP(B52,Grupos!$A$2:$B$619,2,FALSE) -> CAJAS EMPALME | B52: CE25-25-15B | C52: CAJA DE EMPALME 25X25X15 BLANCA | D52: 528 | E52: 10016.57 | F52: 648.25 | G52: =E52+F52 -> 10664.82 | H52: =E52*D52 -> 5288749 | I52: =F52*D52 -> 342276 | J52: =G52*D52 -> 5631025 | K52: =J52/$J$293 -> 0.0042306869 | L52: =$K$364*K52/D52 -> 2072.8677 | M52: =F52*$M$363 -> 3481.3161 | N52: =G52+L52+M52 -> 16219.004 | O52: =N52*D52 -> 8563634 | P52: =Q52/D52 -> 31732.852 | Q52: 16754946 | R52: =O52/Q52 -> 0.51111081
A53: =VLOOKUP(B53,Grupos!$A$2:$B$619,2,FALSE) -> CAJAS EMPALME | B53: CE30-30-10B | C53: CAJA DE EMPALME 30X30X10 BLANCA | D53: 1230 | E53: 11060.96 | F53: 596.56 | G53: =E53+F53 -> 11657.52 | H53: =E53*D53 -> 13604981 | I53: =F53*D53 -> 733768.8 | J53: =G53*D53 -> 14338750 | K53: =J53/$J$293 -> 0.010772952 | L53: =$K$364*K53/D53 -> 2265.8138 | M53: =F53*$M$363 -> 3203.7238 | N53: =G53+L53+M53 -> 17127.058 | O53: =N53*D53 -> 21066281 | P53: =Q53/D53 -> 33475.573 | Q53: 41174955 | R53: =O53/Q53 -> 0.51162851
A54: =VLOOKUP(B54,Grupos!$A$2:$B$619,2,FALSE) -> CAJAS EMPALME | B54: CE30-30-15B | C54: CAJA DE EMPALME 30X30X15 BLANCA | D54: 1764 | E54: 12773.82 | F54: 721.56 | G54: =E54+F54 -> 13495.38 | H54: =E54*D54 -> 22533018 | I54: =F54*D54 -> 1272831.8 | J54: =G54*D54 -> 23805850 | K54: =J54/$J$293 -> 0.017885749 | L54: =$K$364*K54/D54 -> 2623.0295 | M54: =F54*$M$363 -> 3875.015 | N54: =G54+L54+M54 -> 19993.424 | O54: =N54*D54 -> 35268401 | P54: =Q54/D54 -> 39262.814 | Q54: 69259603 | R54: =O54/Q54 -> 0.50922037
A55: =VLOOKUP(B55,Grupos!$A$2:$B$619,2,FALSE) -> CAJAS EMPALME | B55: CE30-30-20B | C55: CAJA DE EMPALME 30X30X20 BLANCA | D55: 90 | E55: 16238.13 | F55: 1508.32 | G55: =E55+F55 -> 17746.45 | H55: =E55*D55 -> 1461431.7 | I55: =F55*D55 -> 135748.8 | J55: =G55*D55 -> 1597180.5 | K55: =J55/$J$293 -> 0.0011999895 | L55: =$K$364*K55/D55 -> 3449.2887 | M55: =F55*$M$363 -> 8100.1754 | N55: =G55+L55+M55 -> 29295.914 | O55: =N55*D55 -> 2636632.3 | P55: =Q55/D55 -> 47879.999 | Q55: 4309199.9 | R55: =O55/Q55 -> 0.61186121
A56: =VLOOKUP(B56,Grupos!$A$2:$B$619,2,FALSE) -> CAJAS EMPALME | B56: CE40-40-15B | C56: CAJA DE EMPALME 40X40X15 BLANCA | D56: 761 | E56: 20258.69 | F56: 1240.45 | G56: =E56+F56 -> 21499.14 | H56: =E56*D56 -> 15416863 | I56: =F56*D56 -> 943982.45 | J56: =G56*D56 -> 16360846 | K56: =J56/$J$293 -> 0.012292188 | L56: =$K$364*K56/D56 -> 4178.6803 | M56: =F56*$M$363 -> 6661.6253 | N56: =G56+L56+M56 -> 32339.446 | O56: =N56*D56 -> 24610318 | P56: =Q56/D56 -> 59300.715 | Q56: 45127844 | R56: =O56/Q56 -> 0.54534664
... A62: =VLOOKUP(B62,Grupos!$A$2:$B$619,2,FALSE) -> CAJAS EMPALME | B62: CI-BU | C62: CAJA INDUSTRIAL BREAKER UNIVERSAL 100 AMP | D62: 70 | E62: 9059.16 | F62: 636.21 | G62: =E62+F62 -> 9695.37 | H62: =E62*D62 -> 634141.2 | I62: =F62*D62 -> 44534.7 | J62: =G62*D62 -> 678675.9 | K62: =J62/$J$293 -> 0.000509901 | L62: =$K$364*K62/D62 -> 1884.4406 | M62: =F62*$M$363 -> 3416.6574 | N62: =G62+L62+M62 -> 14996.468 | O62: =N62*D62 -> 1049752.8 | P62: =Q62/D62 -> 36925.713 | Q62: 2584799.9 | R62: =O62/Q62 -> 0.40612534
A63: Total CAJAS EMPALME | D63: =SUBTOTAL(9,D45:D62) -> 10268 | H63: =SUBTOTAL(9,H45:H62) -> 1.1033453e+08 | I63: =SUBTOTAL(9,I45:I62) -> 8546983.8 | J63: =SUBTOTAL(9,J45:J62) -> 1.1888151e+08 | O63: =SUBTOTAL(9,O45:O62) -> 1.8788804e+08 | Q63: =SUBTOTAL(9,Q45:Q62) -> 3.3667613e+08 | R63: =O63/Q63 -> 0.55806759 | S63: =Q63/$Q$293 -> 0.10256336
A64: =VLOOKUP(B64,Grupos!$A$2:$B$619,2,FALSE) -> CAJAS PLASTICAS CC | B64: CP2X4-CC | C64: CAJA PLASTICA 2X4 BLANCA | D64: 295920 | E64: 168.87 | F64: 7.9 | G64: =E64+F64 -> 176.77 | H64: =E64*D64 -> 49972010 | I64: =F64*D64 -> 2337768 | J64: =G64*D64 -> 52309778 | K64: =J64/$J$293 -> 0.039301246 | L64: =$K$364*K64/D64 -> 34.357901 | M64: =F64*$M$363 -> 42.425603 | N64: =G64+L64+M64 -> 253.5535 | O64: =N64*D64 -> 75031553 | P64: =Q64/D64 -> 313.72848 | Q64: 92838531 | R64: =O64/Q64 -> 0.8081941
A65: =VLOOKUP(B65,Grupos!$A$2:$B$619,2,FALSE) -> CAJAS PLASTICAS CC | B65: CP4X4-CC | C65: CAJA PLASTICA 4X4 BLANCA | D65: 225450 | E65: 262.69 | F65: 10.81 | G65: =E65+F65 -> 273.5 | H65: =E65*D65 -> 59223460 | I65: =F65*D65 -> 2437114.5 | J65: =G65*D65 -> 61660575 | K65: =J65/$J$293 -> 0.046326662 | L65: =$K$364*K65/D65 -> 53.158827 | M65: =F65*$M$363 -> 58.053262 | N65: =G65+L65+M65 -> 384.71209 | O65: =N65*D65 -> 86733341 | P65: =Q65/D65 -> 472.53416 | Q65: 1.0653283e+08 | R65: =O65/Q65 -> 0.81414663
A66: =VLOOKUP(B66,Grupos!$A$2:$B$619,2,FALSE) -> CAJAS PLASTICAS CC | B66: CPOCTOGONAL-CC | C66: CAJA PLASTICA OCTOGONAL BLANCA | D66: 126900 | E66: 212.15 | F66: 9.15 | G66: =E66+F66 -> 221.3 | H66: =E66*D66 -> 26921835 | I66: =F66*D66 -> 1161135 | J66: =G66*D66 -> 28082970 | K66: =J66/$J$293 -> 0.021099223 | L66: =$K$364*K66/D66 -> 43.012974 | M66: =F66*$M$363 -> 49.138515 | N66: =G66+L66+M66 -> 313.45149 | O66: =N66*D66 -> 39776994 | P66: =Q66/D66 -> 466.52023 | Q66: 59201417 | R66: =O66/Q66 -> 0.6718926
A67: Total CAJAS PLASTICAS CC | D67: =SUBTOTAL(9,D64:D66) -> 648270 | H67: =SUBTOTAL(9,H64:H66) -> 1.3611731e+08 | I67: =SUBTOTAL(9,I64:I66) -> 5936017.5 | J67: =SUBTOTAL(9,J64:J66) -> 1.4205332e+08 | O67: =SUBTOTAL(9,O64:O66) -> 2.0154189e+08 | Q67: =SUBTOTAL(9,Q64:Q66) -> 2.5857277e+08 | R67: =O67/Q67 -> 0.77943971 | S67: =Q67/$Q$293 -> 0.078770335
A68: =VLOOKUP(B68,Grupos!$A$2:$B$619,2,FALSE) -> CAJAS PLASTICAS LH | B68: CP2X4-LH | C68: CAJA PLASTICA 2X4 LIBRE DE HALOGENOS | D68: 21600 | E68: 182 | F68: 8.6 | G68: =E68+F68 -> 190.6 | H68: =E68*D68 -> 3931200 | I68: =F68*D68 -> 185760 | J68: =G68*D68 -> 4116960 | K68: =J68/$J$293 -> 0.0030931436 | L68: =$K$364*K68/D68 -> 37.045969 | M68: =F68*$M$363 -> 46.184834 | N68: =G68+L68+M68 -> 273.8308 | O68: =N68*D68 -> 5914745.3 | P68: =Q68/D68 -> 336.57001 | Q68: 7269912.2 | R68: =O68/Q68 -> 0.8135924
A69: =VLOOKUP(B69,Grupos!$A$2:$B$619,2,FALSE) -> CAJAS PLASTICAS LH | B69: CP4X4-LH | C69: CAJA PLASTICA 4X4 LIBRE DE HALOGENOS | D69: 34560 | E69: 260 | F69: 11.62 | G69: =E69+F69 -> 271.62 | H69: =E69*D69 -> 8985600 | I69: =F69*D69 -> 401587.2 | J69: =G69*D69 -> 9387187.2 | K69: =J69/$J$293 -> 0.0070527569 | L69: =$K$364*K69/D69 -> 52.793421 | M69: =F69*$M$363 -> 62.403229 | N69: =G69+L69+M69 -> 386.81665 | O69: =N69*D69 -> 13368383 | P69: =Q69/D69 -> 485.45314 | Q69: 16777260 | R69: =O69/Q69 -> 0.79681563
A70: =VLOOKUP(B70,Grupos!$A$2:$B$619,2,FALSE) -> CAJAS PLASTICAS LH | B70: CPOCT-LH | C70: CAJA PLASTICA OCTOGONAL LIBRE DE HALOGENOS | D70: 17010 | E70: 217.92 | F70: 8.55 | G70: =E70+F70 -> 226.47 | H70: =E70*D70 -> 3706819.2 | I70: =F70*D70 -> 145435.5 | J70: =G70*D70 -> 3852254.7 | K70: =J70/$J$293 -> 0.0028942659 | L70: =$K$364*K70/D70 -> 44.017841 | M70: =F70*$M$363 -> 45.916318 | N70: =G70+L70+M70 -> 316.40416 | O70: =N70*D70 -> 5382034.7 | P70: =Q70/D70 -> 495.11112 | Q70: 8421840.2 | R70: =O70/Q70 -> 0.63905686
A71: Total CAJAS PLASTICAS LH | D71: =SUBTOTAL(9,D68:D70) -> 73170 | H71: =SUBTOTAL(9,H68:H70) -> 16623619 | I71: =SUBTOTAL(9,I68:I70) -> 732782.7 | J71: =SUBTOTAL(9,J68:J70) -> 17356402 | O71: =SUBTOTAL(9,O68:O70) -> 24665163 | Q71: =SUBTOTAL(9,Q68:Q70) -> 32469013 | R71: =O71/Q71 -> 0.7596524 | S71: =Q71/$Q$293 -> 0.0098912001
A72: =VLOOKUP(B72,Grupos!$A$2:$B$619,2,FALSE) -> CAJAS TELEFONICAS | B72: CT20-20-10 | C72: CAJA TELEFONICA 20X20X10 | D72: 20 | E72: 6348.57 | F72: 657.94 | G72: =E72+F72 -> 7006.51 | H72: =E72*D72 -> 126971.4 | I72: =F72*D72 -> 13158.8 | J72: =G72*D72 -> 140130.2 | K72: =J72/$J$293 -> 0.00010528225 | L72: =$K$364*K72/D72 -> 1361.8203 | M72: =F72*$M$363 -> 3533.3546 | N72: =G72+L72+M72 -> 11901.685 | O72: =N72*D72 -> 238033.7 | P72: =Q72/D72 -> 31520.999 | Q72: 630419.99 | R72: =O72/Q72 -> 0.37757955
A73: =VLOOKUP(B73,Grupos!$A$2:$B$619,2,FALSE) -> CAJAS TELEFONICAS | B73: CT20-20-15 | C73: CAJA TELEFONICA 20X20X15 | D73: 48 | E73: 7530.77 | F73: 688.78 | G73: =E73+F73 -> 8219.55 | H73: =E73*D73 -> 361476.96 | I73: =F73*D73 -> 33061.44 | J73: =G73*D73 -> 394538.4 | K73: =J73/$J$293 -> 0.00029642356 | L73: =$K$364*K73/D73 -> 1597.5928 | M73: =F73*$M$363 -> 3698.9756 | N73: =G73+L73+M73 -> 13516.118 | O73: =N73*D73 -> 648773.68 | P73: =Q73/D73 -> 37652.333 | Q73: 1807312 | R73: =O73/Q73 -> 0.3589716
A74: =VLOOKUP(B74,Grupos!$A$2:$B$619,2,FALSE) -> CAJAS TELEFONICAS | B74: CT30-30-10 | C74: CAJA TELEFONICA 30X30X10 | D74: 80 | E74: 12123.53 | F74: 640.79 | G74: =E74+F74 -> 12764.32 | H74: =E74*D74 -> 969882.4 | I74: =F74*D74 -> 51263.2 | J74: =G74*D74 -> 1021145.6 | K74: =J74/$J$293 -> 0.00076720444 | L74: =$K$364*K74/D74 -> 2480.937 | M74: =F74*$M$363 -> 3441.2535 | N74: =G74+L74+M74 -> 18686.51 | O74: =N74*D74 -> 1494920.8 | P74: =Q74/D74 -> 44529.502 | Q74: 3562360.1 | R74: =O74/Q74 -> 0.41964338
A75: =VLOOKUP(B75,Grupos!$A$2:$B$619,2,FALSE) -> CAJAS TELEFONICAS | B75: CT40-40-15 | C75: CAJA TELEFONICA 40X40X15 | D75: 62 | E75: 22164.95 | F75: 668.16 | G75: =E75+F75 -> 22833.11 | H75: =E75*D75 -> 1374226.9 | I75: =F75*D75 -> 41425.92 | J75: =G75*D75 -> 1415652.8 | K75: =J75/$J$293 -> 0.0010636046 | L75: =$K$364*K75/D75 -> 4437.9574 | M75: =F75*$M$363 -> 3588.2394 | N75: =G75+L75+M75 -> 30859.307 | O75: =N75*D75 -> 1913277 | P75: =Q75/D75 -> 71693.437 | Q75: 4444993.1 | R75: =O75/Q75 -> 0.43043419
A76: =VLOOKUP(B76,Grupos!$A$2:$B$619,2,FALSE) -> CAJAS TELEFONICAS | B76: CT40-40-20 | C76: CAJA TELEFONICA 40X40X20 | D76: 56 | E76: 24574.8 | F76: 789.33 | G76: =E76+F76 -> 25364.13 | H76: =E76*D76 -> 1376188.8 | I76: =F76*D76 -> 44202.48 | J76: =G76*D76 -> 1420391.3 | K76: =J76/$J$293 -> 0.0010671647 | L76: =$K$364*K76/D76 -> 4929.8991 | M76: =F76*$M$363 -> 4238.9622 | N76: =G76+L76+M76 -> 34532.991 | O76: =N76*D76 -> 1933847.5 | P76: =Q76/D76 -> 88955.718 | Q76: 4981520.2 | R76: =O76/Q76 -> 0.38820429
A77: Total CAJAS TELEFONICAS | D77: =SUBTOTAL(9,D72:D76) -> 266 | H77: =SUBTOTAL(9,H72:H76) -> 4208746.5 | I77: =SUBTOTAL(9,I72:I76) -> 183111.84 | J77: =SUBTOTAL(9,J72:J76) -> 4391858.3 | O77: =SUBTOTAL(9,O72:O76) -> 6228852.8 | Q77: =SUBTOTAL(9,Q72:Q76) -> 15426605 | R77: =O77/Q77 -> 0.40377339 | S77: =Q77/$Q$293 -> 0.004699485
A78: =VLOOKUP(B78,Grupos!$A$2:$B$619,2,FALSE) -> CE 125 | B78: CE125LE | C78: CAJA 12X12X5 TAPA LEVITON GRIS | D78: 9360 | E78: 2031.35 | F78: 435.36 | G78: =E78+F78 -> 2466.71 | H78: =E78*D78 -> 19013436 | I78: =F78*D78 -> 4074969.6 | J78: =G78*D78 -> 23088406 | K78: =J78/$J$293 -> 0.01734672 | L78: =$K$364*K78/D78 -> 479.44208 | M78: =F78*$M$363 -> 2338.0267 | N78: =G78+L78+M78 -> 5284.1788 | O78: =N78*D78 -> 49459913 | P78: =Q78/D78 -> 4814.8846 | Q78: 45067320 | R78: =O78/Q78 -> 1.0974674
A79: =VLOOKUP(B79,Grupos!$A$2:$B$619,2,FALSE) -> CE 125 | B79: CE125LEB | C79: CAJA 12X12X5 TAPA LEVITON BLANCA | D79: 1200 | E79: 2141.44 | F79: 402.72 | G79: =E79+F79 -> 2544.16 | H79: =E79*D79 -> 2569728 | I79: =F79*D79 -> 483264 | J79: =G79*D79 -> 3052992 | K79: =J79/$J$293 -> 0.002293766 | L79: =$K$364*K79/D79 -> 494.49565 | M79: =F79*$M$363 -> 2162.7391 | N79: =G79+L79+M79 -> 5201.3948 | O79: =N79*D79 -> 6241673.7 | P79: =Q79/D79 -> 5083.5 | Q79: 6100200.1 | R79: =O79/Q79 -> 1.0231916
A80: =VLOOKUP(B80,Grupos!$A$2:$B$619,2,FALSE) -> CE 125 | B80: CE125LEDB | C80: CAJA 12X12X5 TAPA LEVITON DOBLE BLANCA | D80: 540 | E80: 1988.04 | F80: 537.63 | G80: =E80+F80 -> 2525.67 | H80: =E80*D80 -> 1073541.6 | I80: =F80*D80 -> 290320.2 | J80: =G80*D80 -> 1363861.8 | K80: =J80/$J$293 -> 0.0010246931 | L80: =$K$364*K80/D80 -> 490.90184 | M80: =F80*$M$363 -> 2887.2503 | N80: =G80+L80+M80 -> 5903.8221 | O80: =N80*D80 -> 3188063.9 | P80: =Q80/D80 -> 5356 | Q80: 2892240 | R80: =O80/Q80 -> 1.1022819
A81: =VLOOKUP(B81,Grupos!$A$2:$B$619,2,FALSE) -> CE 125 | B81: CE125LI | C81: CAJA 12X12X5 TAPA LISA GRIS | D81: 9060 | E81: 2031.35 | F81: 432.81 | G81: =E81+F81 -> 2464.16 | H81: =E81*D81 -> 18404031 | I81: =F81*D81 -> 3921258.6 | J81: =G81*D81 -> 22325290 | K81: =J81/$J$293 -> 0.016773378 | L81: =$K$364*K81/D81 -> 478.94645 | M81: =F81*$M$363 -> 2324.3323 | N81: =G81+L81+M81 -> 5267.4388 | O81: =N81*D81 -> 47722995 | P81: =Q81/D81 -> 4850.6093 | Q81: 43946520 | R81: =O81/Q81 -> 1.0859334
A82: =VLOOKUP(B82,Grupos!$A$2:$B$619,2,FALSE) -> CE 125 | B82: CE125LIB | C82: CAJA 12X12X5 TAPA LISA BLANCA | D82: 3720 | E82: 2141.44 | F82: 424.82 | G82: =E82+F82 -> 2566.26 | H82: =E82*D82 -> 7966156.8 | I82: =F82*D82 -> 1580330.4 | J82: =G82*D82 -> 9546487.2 | K82: =J82/$J$293 -> 0.0071724418 | L82: =$K$364*K82/D82 -> 498.79112 | M82: =F82*$M$363 -> 2281.4234 | N82: =G82+L82+M82 -> 5346.4745 | O82: =N82*D82 -> 19888885 | P82: =Q82/D82 -> 5114.0322 | Q82: 19024200 | R82: =O82/Q82 -> 1.0454519
A83: =VLOOKUP(B83,Grupos!$A$2:$B$619,2,FALSE) -> CE 125 | B83: CE125LX | C83: CAJA 12X12X5 TAPA DATOS GRIS | D83: 7080 | E83: 2028.07 | F83: 415.36 | G83: =E83+F83 -> 2443.43 | H83: =E83*D83 -> 14358736 | I83: =F83*D83 -> 2940748.8 | J83: =G83*D83 -> 17299484 | K83: =J83/$J$293 -> 0.012997403 | L83: =$K$364*K83/D83 -> 474.91727 | M83: =F83*$M$363 -> 2230.6201 | N83: =G83+L83+M83 -> 5148.9673 | O83: =N83*D83 -> 36454689 | P83: =Q83/D83 -> 4890.4237 | Q83: 34624200 | R83: =O83/Q83 -> 1.0528673
A84: =VLOOKUP(B84,Grupos!$A$2:$B$619,2,FALSE) -> CE 125 | B84: CE125LXB | C84: CAJA 12X12X5 TAPA DATOS BLANCA | D84: 780 | E84: 2141.44 | F84: 426.01 | G84: =E84+F84 -> 2567.45 | H84: =E84*D84 -> 1670323.2 | I84: =F84*D84 -> 332287.8 | J84: =G84*D84 -> 2002611 | K84: =J84/$J$293 -> 0.0015045965 | L84: =$K$364*K84/D84 -> 499.02241 | M84: =F84*$M$363 -> 2287.8141 | N84: =G84+L84+M84 -> 5354.2865 | O84: =N84*D84 -> 4176343.5 | P84: =Q84/D84 -> 5226 | Q84: 4076280 | R84: =O84/Q84 -> 1.0245477
A85: Total CE 125 | D85: =SUBTOTAL(9,D78:D84) -> 31740 | H85: =SUBTOTAL(9,H78:H84) -> 65055952 | I85: =SUBTOTAL(9,I78:I84) -> 13623179 | J85: =SUBTOTAL(9,J78:J84) -> 78679132 | O85: =SUBTOTAL(9,O78:O84) -> 1.6713256e+08 | Q85: =SUBTOTAL(9,Q78:Q84) -> 1.5573096e+08 | R85: =O85/Q85 -> 1.0732135 | S85: =Q85/$Q$293 -> 0.047441112
A86: =VLOOKUP(B86,Grupos!$A$2:$B$619,2,FALSE) -> EXCEDENTES INDUSTRIALES | B86: EXARCHIVO | C86: EXCEDENTES INDUSTRIALES DE ARCHIVO | D86: 85 | E86: 0 | F86: 0 | G86: =E86+F86 -> 0 | H86: =E86*D86 -> 0 | I86: =F86*D86 -> 0 | J86: =G86*D86 -> 0 | K86: =J86/$J$293 -> 0 | L86: =$K$364*K86/D86 -> 0 | M86: =F86*$M$363 -> 0 | N86: =G86+L86+M86 -> 0 | O86: =N86*D86 -> 0 | P86: =Q86/D86 -> 739.41176 | Q86: 62850 | R86: =O86/Q86 -> 0
A87: =VLOOKUP(B87,Grupos!$A$2:$B$619,2,FALSE) -> EXCEDENTES INDUSTRIALES | B87: EXBOLSASP | C87: EXCEDENTES BOLSAS PLASTICAS | D87: 18.65 | E87: 0 | F87: 0 | G87: =E87+F87 -> 0 | H87: =E87*D87 -> 0 | I87: =F87*D87 -> 0 | J87: =G87*D87 -> 0 | K87: =J87/$J$293 -> 0 | L87: =$K$364*K87/D87 -> 0 | M87: =F87*$M$363 -> 0 | N87: =G87+L87+M87 -> 0 | O87: =N87*D87 -> 0 | P87: =Q87/D87 -> 500 | Q87: 9325 | R87: =O87/Q87 -> 0
A88: =VLOOKUP(B88,Grupos!$A$2:$B$619,2,FALSE) -> EXCEDENTES INDUSTRIALES | B88: EXCARTON | C88: EXCEDENTES INDUSTRIALES DE CATON | D88: 864 | E88: 0 | F88: 0 | G88: =E88+F88 -> 0 | H88: =E88*D88 -> 0 | I88: =F88*D88 -> 0 | J88: =G88*D88 -> 0 | K88: =J88/$J$293 -> 0 | L88: =$K$364*K88/D88 -> 0 | M88: =F88*$M$363 -> 0 | N88: =G88+L88+M88 -> 0 | O88: =N88*D88 -> 0 | P88: =Q88/D88 -> 300 | Q88: 259200 | R88: =O88/Q88 -> 0
A89: =VLOOKUP(B89,Grupos!$A$2:$B$619,2,FALSE) -> EXCEDENTES INDUSTRIALES | B89: EXCEBARREDU | C89: EXCEDENTES INDUSTRIALES - BARREDURA PP | D89: 548.05 | E89: 0 | F89: 0 | G89: =E89+F89 -> 0 | H89: =E89*D89 -> 0 | I89: =F89*D89 -> 0 | J89: =G89*D89 -> 0 | K89: =J89/$J$293 -> 0 | L89: =$K$364*K89/D89 -> 0 | M89: =F89*$M$363 -> 0 | N89: =G89+L89+M89 -> 0 | O89: =N89*D89 -> 0 | P89: =Q89/D89 -> 500 | Q89: 274025 | R89: =O89/Q89 -> 0
A90: =VLOOKUP(B90,Grupos!$A$2:$B$619,2,FALSE) -> EXCEDENTES INDUSTRIALES | B90: EXCEDENTES | C90: EXCEDENTES INDUSTRIALES MADEROS CORTOS | D90: 112 | E90: 0 | F90: 0 | G90: =E90+F90 -> 0 | H90: =E90*D90 -> 0 | I90: =F90*D90 -> 0 | J90: =G90*D90 -> 0 | K90: =J90/$J$293 -> 0 | L90: =$K$364*K90/D90 -> 0 | M90: =F90*$M$363 -> 0 | N90: =G90+L90+M90 -> 0 | O90: =N90*D90 -> 0 | P90: =Q90/D90 -> 500 | Q90: 56000 | R90: =O90/Q90 -> 0
A91: =VLOOKUP(B91,Grupos!$A$2:$B$619,2,FALSE) -> EXCEDENTES INDUSTRIALES | B91: EXCEDENTESIN | C91: EXCEDENTES INDUSTRIALES MADEROS LARGOS | D91: 67 | E91: 0 | F91: 0 | G91: =E91+F91 -> 0 | H91: =E91*D91 -> 0 | I91: =F91*D91 -> 0 | J91: =G91*D91 -> 0 | K91: =J91/$J$293 -> 0 | L91: =$K$364*K91/D91 -> 0 | M91: =F91*$M$363 -> 0 | N91: =G91+L91+M91 -> 0 | O91: =N91*D91 -> 0 | P91: =Q91/D91 -> 1000 | Q91: 67000 | R91: =O91/Q91 -> 0
A92: =VLOOKUP(B92,Grupos!$A$2:$B$619,2,FALSE) -> EXCEDENTES INDUSTRIALES | B92: EXCETORTAPOC | C92: EXCEDENTES INDUSTRIALES TORTA POLICARBONATO | D92: 292.5 | E92: 0 | F92: 0 | G92: =E92+F92 -> 0 | H92: =E92*D92 -> 0 | I92: =F92*D92 -> 0 | J92: =G92*D92 -> 0 | K92: =J92/$J$293 -> 0 | L92: =$K$364*K92/D92 -> 0 | M92: =F92*$M$363 -> 0 | N92: =G92+L92+M92 -> 0 | O92: =N92*D92 -> 0 | P92: =Q92/D92 -> 250 | Q92: 73125 | R92: =O92/Q92 -> 0
A93: =VLOOKUP(B93,Grupos!$A$2:$B$619,2,FALSE) -> EXCEDENTES INDUSTRIALES | B93: EXCETORTAPOLIP | C93: EXCEDENTES INDUSTRIALES TORTA POLIPROPILENO | D93: 252.6 | E93: 0 | F93: 0 | G93: =E93+F93 -> 0 | H93: =E93*D93 -> 0 | I93: =F93*D93 -> 0 | J93: =G93*D93 -> 0 | K93: =J93/$J$293 -> 0 | L93: =$K$364*K93/D93 -> 0 | M93: =F93*$M$363 -> 0 | N93: =G93+L93+M93 -> 0 | O93: =N93*D93 -> 0 | P93: =Q93/D93 -> 250 | Q93: 63150 | R93: =O93/Q93 -> 0
A94: =VLOOKUP(B94,Grupos!$A$2:$B$619,2,FALSE) -> EXCEDENTES INDUSTRIALES | B94: EXCINDUSTR | C94: EXCEDENTES INDUSTRIALES - REMOLIDO DE POLICARBONATO | D94: 156.85 | E94: 0 | F94: 0 | G94: =E94+F94 -> 0 | H94: =E94*D94 -> 0 | I94: =F94*D94 -> 0 | J94: =G94*D94 -> 0 | K94: =J94/$J$293 -> 0 | L94: =$K$364*K94/D94 -> 0 | M94: =F94*$M$363 -> 0 | N94: =G94+L94+M94 -> 0 | O94: =N94*D94 -> 0 | P94: =Q94/D94 -> 500 | Q94: 78425 | R94: =O94/Q94 -> 0
A95: =VLOOKUP(B95,Grupos!$A$2:$B$619,2,FALSE) -> EXCEDENTES INDUSTRIALES | B95: EXCOSTALES | C95: EXCEDENTE DE PLASTICO COSTALES | D95: 909 | E95: 0 | F95: 0 | G95: =E95+F95 -> 0 | H95: =E95*D95 -> 0 | I95: =F95*D95 -> 0 | J95: =G95*D95 -> 0 | K95: =J95/$J$293 -> 0 | L95: =$K$364*K95/D95 -> 0 | M95: =F95*$M$363 -> 0 | N95: =G95+L95+M95 -> 0 | O95: =N95*D95 -> 0 | P95: =Q95/D95 -> 220 | Q95: 199980 | R95: =O95/Q95 -> 0
A96: Total EXCEDENTES INDUSTRIALES | D96: =SUBTOTAL(9,D86:D95) -> 3305.65 | H96: =SUBTOTAL(9,H86:H95) -> 0 | I96: =SUBTOTAL(9,I86:I95) -> 0 | J96: =SUBTOTAL(9,J86:J95) -> 0 | O96: =SUBTOTAL(9,O86:O95) -> 0 | Q96: =SUBTOTAL(9,Q86:Q95) -> 1143080 | R96: =O96/Q96 -> 0 | S96: =Q96/$Q$293 -> 0.00034822226
A97: =VLOOKUP(B97,Grupos!$A$2:$B$619,2,FALSE) -> INTERIORES | B97: I12P | C97: INTERIOR 12 CTOS 2F 125 AMP | D97: 2 | E97: 15453.34 | F97: 935.42 | G97: =E97+F97 -> 16388.76 | H97: =E97*D97 -> 30906.68 | I97: =F97*D97 -> 1870.84 | J97: =G97*D97 -> 32777.52 | K97: =J97/$J$293 -> 2.462632e-05 | L97: =$K$364*K97/D97 -> 3185.4013 | M97: =F97*$M$363 -> 5023.5137 | N97: =G97+L97+M97 -> 24597.675 | O97: =N97*D97 -> 49195.35 | P97: =Q97/D97 -> 64828 | Q97: 129656 | R97: =O97/Q97 -> 0.3794298
A98: =VLOOKUP(B98,Grupos!$A$2:$B$619,2,FALSE) -> INTERIORES | B98: I18P | C98: INTERIOR 18 CTOS 2F 125 AMP | D98: 8 | E98: 21969.01 | F98: 1049.78 | G98: =E98+F98 -> 23018.79 | H98: =E98*D98 -> 175752.08 | I98: =F98*D98 -> 8398.24 | J98: =G98*D98 -> 184150.32 | K98: =J98/$J$293 -> 0.00013835534 | L98: =$K$364*K98/D98 -> 4474.0471 | M98: =F98*$M$363 -> 5637.6645 | N98: =G98+L98+M98 -> 33130.502 | O98: =N98*D98 -> 265044.01 | P98: =Q98/D98 -> 83220 | Q98: 665760 | R98: =O98/Q98 -> 0.39810745
A99: =VLOOKUP(B99,Grupos!$A$2:$B$619,2,FALSE) -> INTERIORES | B99: I224 | C99: INTERIOR 24 CTOS 2F 225 AMP | D99: 2 | E99: 39787.73 | F99: 2660.46 | G99: =E99+F99 -> 42448.19 | H99: =E99*D99 -> 79575.46 | I99: =F99*D99 -> 5320.92 | J99: =G99*D99 -> 84896.38 | K99: =J99/$J$293 -> 6.3784126e-05 | L99: =$K$364*K99/D99 -> 8250.4424 | M99: =F99*$M$363 -> 14287.547 | N99: =G99+L99+M99 -> 64986.179 | O99: =N99*D99 -> 129972.36 | P99: =Q99/D99 -> 143963 | Q99: 287926 | R99: =O99/Q99 -> 0.4514089
A100: =VLOOKUP(B100,Grupos!$A$2:$B$619,2,FALSE) -> INTERIORES | B100: I230 | C100: INTERIOR 30 CTOS 2F 225 AMP | D100: 3 | E100: 49797.97 | F100: 2108.2 | G100: =E100+F100 -> 51906.17 | H100: =E100*D100 -> 149393.91 | I100: =F100*D100 -> 6324.6 | J100: =G100*D100 -> 155718.51 | K100: =J100/$J$293 -> 0.00011699402 | L100: =$K$364*K100/D100 -> 10088.743 | M100: =F100*$M$363 -> 11321.729 | N100: =G100+L100+M100 -> 73316.641 | O100: =N100*D100 -> 219949.92 | P100: =Q100/D100 -> 184000 | Q100: 551999.99 | R100: =O100/Q100 -> 0.39846001
A101: =VLOOKUP(B101,Grupos!$A$2:$B$619,2,FALSE) -> INTERIORES | B101: I312 | C101: INTERIOR 12 CTOS 3F 225 AMP | D101: 34 | E101: 25206.92 | F101: 1511.1 | G101: =E101+F101 -> 26718.02 | H101: =E101*D101 -> 857035.28 | I101: =F101*D101 -> 51377.4 | J101: =G101*D101 -> 908412.68 | K101: =J101/$J$293 -> 0.00068250624 | L101: =$K$364*K101/D101 -> 5193.0479 | M101: =F101*$M$363 -> 8115.105 | N101: =G101+L101+M101 -> 40026.173 | O101: =N101*D101 -> 1360889.9 | P101: =Q101/D101 -> 98693.088 | Q101: 3355565 | R101: =O101/Q101 -> 0.40556207
A102: =VLOOKUP(B102,Grupos!$A$2:$B$619,2,FALSE) -> INTERIORES | B102: I318 | C102: INTERIOR 18 CTOS 3F 225 AMP | D102: 13 | E102: 37165.5 | F102: 2067.14 | G102: =E102+F102 -> 39232.64 | H102: =E102*D102 -> 483151.5 | I102: =F102*D102 -> 26872.82 | J102: =G102*D102 -> 510024.32 | K102: =J102/$J$293 -> 0.00038319014 | L102: =$K$364*K102/D102 -> 7625.452 | M102: =F102*$M$363 -> 11101.223 | N102: =G102+L102+M102 -> 57959.315 | O102: =N102*D102 -> 753471.09 | P102: =Q102/D102 -> 119073 | Q102: 1547949 | R102: =O102/Q102 -> 0.48675448
A103: =VLOOKUP(B103,Grupos!$A$2:$B$619,2,FALSE) -> INTERIORES | B103: I318-125 | C103: INTERIOR 18 CTOS 3F 125 AMP | D103: 2 | E103: 30107.38 | F103: 1595.87 | G103: =E103+F103 -> 31703.25 | H103: =E103*D103 -> 60214.76 | I103: =F103*D103 -> 3191.74 | J103: =G103*D103 -> 63406.5 | K103: =J103/$J$293 -> 4.7638406e-05 | L103: =$K$364*K103/D103 -> 6162.0021 | M103: =F103*$M$363 -> 8570.3478 | N103: =G103+L103+M103 -> 46435.6 | O103: =N103*D103 -> 92871.2 | P103: =Q103/D103 -> 109472 | Q103: 218944 | R103: =O103/Q103 -> 0.42417787
A104: =VLOOKUP(B104,Grupos!$A$2:$B$619,2,FALSE) -> INTERIORES | B104: I318-BIMETALICO | C104: INTERIOR 18 CTOS 3 FASES TRP318 BIMETALICO | D104: 7 | E104: 12022 | F104: 2049.66 | G104: =E104+F104 -> 14071.66 | H104: =E104*D104 -> 84154 | I104: =F104*D104 -> 14347.62 | J104: =G104*D104 -> 98501.62 | K104: =J104/$J$293 -> 7.4005979e-05 | L104: =$K$364*K104/D104 -> 2735.0382 | M104: =F104*$M$363 -> 11007.35 | N104: =G104+L104+M104 -> 27814.048 | O104: =N104*D104 -> 194698.33 | P104: =Q104/D104 -> 102008.01 | Q104: 714056.05 | R104: =O104/Q104 -> 0.27266534
A105: =VLOOKUP(B105,Grupos!$A$2:$B$619,2,FALSE) -> INTERIORES | B105: I324 | C105: INTERIOR 24 CTOS 3F 225 AMP | D105: 1 | E105: 49135.39 | F105: 2558.08 | G105: =E105+F105 -> 51693.47 | H105: =E105*D105 -> 49135.39 | I105: =F105*D105 -> 2558.08 | J105: =G105*D105 -> 51693.47 | K105: =J105/$J$293 -> 3.8838203e-05 | L105: =$K$364*K105/D105 -> 10047.401 | M105: =F105*$M$363 -> 13737.733 | N105: =G105+L105+M105 -> 75478.604 | O105: =N105*D105 -> 75478.604 | P105: =Q105/D105 -> 178059.51 | Q105: 178059.51 | R105: =O105/Q105 -> 0.42389538
A106: =VLOOKUP(B106,Grupos!$A$2:$B$619,2,FALSE) -> INTERIORES | B106: I330 | C106: INTERIOR 30 CTOS 3F 225 AMP | D106: 2 | E106: 61058.56 | F106: 2754.57 | G106: =E106+F106 -> 63813.13 | H106: =E106*D106 -> 122117.12 | I106: =F106*D106 -> 5509.14 | J106: =G106*D106 -> 127626.26 | K106: =J106/$J$293 -> 9.5887827e-05 | L106: =$K$364*K106/D106 -> 12403.039 | M106: =F106*$M$363 -> 14792.949 | N106: =G106+L106+M106 -> 91009.117 | O106: =N106*D106 -> 182018.23 | P106: =Q106/D106 -> 182400 | Q106: 364800 | R106: =O106/Q106 -> 0.4989535
A107: =VLOOKUP(B107,Grupos!$A$2:$B$619,2,FALSE) -> INTERIORES | B107: I336 | C107: INTERIOR 36 CTOS 3F 225 AMP | D107: 6 | E107: 73332.86 | F107: 3209.09 | G107: =E107+F107 -> 76541.95 | H107: =E107*D107 -> 439997.16 | I107: =F107*D107 -> 19254.54 | J107: =G107*D107 -> 459251.7 | K107: =J107/$J$293 -> 0.00034504378 | L107: =$K$364*K107/D107 -> 14877.076 | M107: =F107*$M$363 -> 17233.871 | N107: =G107+L107+M107 -> 108652.9 | O107: =N107*D107 -> 651917.38 | P107: =Q107/D107 -> 200602 | Q107: 1203612 | R107: =O107/Q107 -> 0.54163417
A108: =VLOOKUP(B108,Grupos!$A$2:$B$619,2,FALSE) -> INTERIORES | B108: I342 | C108: INTERIOR 42 CTOS 3F 225 AMP | D108: 1 | E108: 85554.43 | F108: 4227.38 | G108: =E108+F108 -> 89781.81 | H108: =E108*D108 -> 85554.43 | I108: =F108*D108 -> 4227.38 | J108: =G108*D108 -> 89781.81 | K108: =J108/$J$293 -> 6.7454634e-05 | L108: =$K$364*K108/D108 -> 17450.441 | M108: =F108*$M$363 -> 22702.424 | N108: =G108+L108+M108 -> 129934.67 | O108: =N108*D108 -> 129934.67 | P108: =Q108/D108 -> 229577 | Q108: 229577 | R108: =O108/Q108 -> 0.56597427
A109: =VLOOKUP(B109,Grupos!$A$2:$B$619,2,FALSE) -> INTERIORES | B109: I8P | C109: INTERIOR 08 CTOS 2F 125 AMP | D109: 2 | E109: 11612.16 | F109: 891.76 | G109: =E109+F109 -> 12503.92 | H109: =E109*D109 -> 23224.32 | I109: =F109*D109 -> 1783.52 | J109: =G109*D109 -> 25007.84 | K109: =J109/$J$293 -> 1.8788825e-05 | L109: =$K$364*K109/D109 -> 2430.3244 | M109: =F109*$M$363 -> 4789.0451 | N109: =G109+L109+M109 -> 19723.289 | O109: =N109*D109 -> 39446.579 | P109: =Q109/D109 -> 51642 | Q109: 103284 | R109: =O109/Q109 -> 0.38192342
A110: Total INTERIORES | D110: =SUBTOTAL(9,D97:D109) -> 83 | H110: =SUBTOTAL(9,H97:H109) -> 2640212.1 | I110: =SUBTOTAL(9,I97:I109) -> 151036.84 | J110: =SUBTOTAL(9,J97:J109) -> 2791248.9 | O110: =SUBTOTAL(9,O97:O109) -> 4144887.6 | Q110: =SUBTOTAL(9,Q97:Q109) -> 9551188.5 | R110: =O110/Q110 -> 0.43396564 | S110: =Q110/$Q$293 -> 0.002909627
A111: =VLOOKUP(B111,Grupos!$A$2:$B$619,2,FALSE) -> REGLETAS | B111: R4M-BIMETALICO | C111: REGLETA DE 4 CTOS 1 FASE BIMETALICA (R4TPEM) | D111: 12 | E111: 4496.18 | F111: 453.42 | G111: =E111+F111 -> 4949.6 | H111: =E111*D111 -> 53954.16 | I111: =F111*D111 -> 5441.04 | J111: =G111*D111 -> 59395.2 | K111: =J111/$J$293 -> 4.4624646e-05 | L111: =$K$364*K111/D111 -> 962.02899 | M111: =F111*$M$363 -> 2435.0148 | N111: =G111+L111+M111 -> 8346.6438 | O111: =N111*D111 -> 100159.73 | P111: =Q111/D111 -> 30075 | Q111: 360900 | R111: =O111/Q111 -> 0.27752764
A112: =VLOOKUP(B112,Grupos!$A$2:$B$619,2,FALSE) -> REGLETAS | B112: R6M | C112: REGLETA DE 6 CIRCUITOS MONO (R6TPEM) | D112: 3 | E112: 6859.6 | F112: 718.26 | G112: =E112+F112 -> 7577.86 | H112: =E112*D112 -> 20578.8 | I112: =F112*D112 -> 2154.78 | J112: =G112*D112 -> 22733.58 | K112: =J112/$J$293 -> 1.7080134e-05 | L112: =$K$364*K112/D112 -> 1472.8707 | M112: =F112*$M$363 -> 3857.2929 | N112: =G112+L112+M112 -> 12908.024 | O112: =N112*D112 -> 38724.071 | P112: =Q112/D112 -> 22983 | Q112: 68949 | R112: =O112/Q112 -> 0.56163354
A113: =VLOOKUP(B113,Grupos!$A$2:$B$619,2,FALSE) -> REGLETAS | B113: R6M-BIMETALICO | C113: REGLETA DE 6 CTOS 1 FASE BIMETALICA (R6TPEM) | D113: 12 | E113: 1640.13 | F113: 467.65 | G113: =E113+F113 -> 2107.78 | H113: =E113*D113 -> 19681.56 | I113: =F113*D113 -> 5611.8 | J113: =G113*D113 -> 25293.36 | K113: =J113/$J$293 -> 1.9003341e-05 | L113: =$K$364*K113/D113 -> 409.67865 | M113: =F113*$M$363 -> 2511.4346 | N113: =G113+L113+M113 -> 5028.8933 | O113: =N113*D113 -> 60346.719 | P113: =Q113/D113 -> 36675 | Q113: 440100 | R113: =O113/Q113 -> 0.13712047
A114: Total REGLETAS | D114: =SUBTOTAL(9,D111:D113) -> 27 | H114: =SUBTOTAL(9,H111:H113) -> 94214.52 | I114: =SUBTOTAL(9,I111:I113) -> 13207.62 | J114: =SUBTOTAL(9,J111:J113) -> 107422.14 | O114: =SUBTOTAL(9,O111:O113) -> 199230.52 | Q114: =SUBTOTAL(9,Q111:Q113) -> 869949 | R114: =O114/Q114 -> 0.22901402 | S114: =Q114/$Q$293 -> 0.00026501698
A115: =VLOOKUP(B115,Grupos!$A$2:$B$619,2,FALSE) -> RITEL | B115: GCOMP45-45-15G | C115: GABINETE COMPLEMENTARIO 45X45X15 GAL | D115: 1 | E115: 21236.87 | F115: 1292.35 | G115: =E115+F115 -> 22529.22 | H115: =E115*D115 -> 21236.87 | I115: =F115*D115 -> 1292.35 | J115: =G115*D115 -> 22529.22 | K115: =J115/$J$293 -> 1.6926595e-05 | L115: =$K$364*K115/D115 -> 4378.8918 | M115: =F115*$M$363 -> 6940.3454 | N115: =G115+L115+M115 -> 33848.457 | O115: =N115*D115 -> 33848.457 | P115: =Q115/D115 -> 80000 | Q115: 80000 | R115: =O115/Q115 -> 0.42310571
A116: =VLOOKUP(B116,Grupos!$A$2:$B$619,2,FALSE) -> RITEL | B116: GPISO ESPECIAL | C116: GABINETE DE PISO MEDIDAS ESPECIALES | D116: 1 | E116: 75399.64 | F116: 4733.26 | G116: =E116+F116 -> 80132.9 | H116: =E116*D116 -> 75399.64 | I116: =F116*D116 -> 4733.26 | J116: =G116*D116 -> 80132.9 | K116: =J116/$J$293 -> 6.0205241e-05 | L116: =$K$364*K116/D116 -> 15575.031 | M116: =F116*$M$363 -> 25419.166 | N116: =G116+L116+M116 -> 121127.1 | O116: =N116*D116 -> 121127.1 | P116: =Q116/D116 -> 390000 | Q116: 390000 | R116: =O116/Q116 -> 0.3105823
A117: =VLOOKUP(B117,Grupos!$A$2:$B$619,2,FALSE) -> RITEL | B117: GPISO100G | C117: GABINETE DE PISO 100X55X20 GAL | D117: 153 | E117: 105004.52 | F117: 5522.6 | G117: =E117+F117 -> 110527.12 | H117: =E117*D117 -> 16065692 | I117: =F117*D117 -> 844957.8 | J117: =G117*D117 -> 16910649 | K117: =J117/$J$293 -> 0.012705265 | L117: =$K$364*K117/D117 -> 21482.603 | M117: =F117*$M$363 -> 29658.182 | N117: =G117+L117+M117 -> 161667.91 | O117: =N117*D117 -> 24735190 | P117: =Q117/D117 -> 353722.22 | Q117: 54119500 | R117: =O117/Q117 -> 0.45704764
A118: =VLOOKUP(B118,Grupos!$A$2:$B$619,2,FALSE) -> RITEL | B118: GPISO7030G | C118: GABINETE DE PISO DE 70X50X30 GAL | D118: 33 | E118: 75457.34 | F118: 5072.71 | G118: =E118+F118 -> 80530.05 | H118: =E118*D118 -> 2490092.2 | I118: =F118*D118 -> 167399.43 | J118: =G118*D118 -> 2657491.6 | K118: =J118/$J$293 -> 0.0019966197 | L118: =$K$364*K118/D118 -> 15652.223 | M118: =F118*$M$363 -> 27242.124 | N118: =G118+L118+M118 -> 123424.4 | O118: =N118*D118 -> 4073005.1 | P118: =Q118/D118 -> 271712.12 | Q118: 8966500 | R118: =O118/Q118 -> 0.45424693
A119: =VLOOKUP(B119,Grupos!$A$2:$B$619,2,FALSE) -> RITEL | B119: GPISO70G | C119: GABINETE DE PISO 70X50X20 GAL | D119: 237 | E119: 75399.64 | F119: 4733.26 | G119: =E119+F119 -> 80132.9 | H119: =E119*D119 -> 17869715 | I119: =F119*D119 -> 1121782.6 | J119: =G119*D119 -> 18991497 | K119: =J119/$J$293 -> 0.014268642 | L119: =$K$364*K119/D119 -> 15575.031 | M119: =F119*$M$363 -> 25419.166 | N119: =G119+L119+M119 -> 121127.1 | O119: =N119*D119 -> 28707122 | P119: =Q119/D119 -> 234278.48 | Q119: 55524000 | R119: =O119/Q119 -> 0.51702186
A120: =VLOOKUP(B120,Grupos!$A$2:$B$619,2,FALSE) -> RITEL | B120: PAU506G | C120: CAJA PAU 30X50X6 PLUS GAL | D120: 521 | E120: 19073.87 | F120: 688.5 | G120: =E120+F120 -> 19762.37 | H120: =E120*D120 -> 9937486.3 | I120: =F120*D120 -> 358708.5 | J120: =G120*D120 -> 10296195 | K120: =J120/$J$293 -> 0.0077357101 | L120: =$K$364*K120/D120 -> 3841.113 | M120: =F120*$M$363 -> 3697.4719 | N120: =G120+L120+M120 -> 27300.955 | O120: =N120*D120 -> 14223797 | P120: =Q120/D120 -> 65758.157 | Q120: 34260000 | R120: =O120/Q120 -> 0.41517214
A121: =VLOOKUP(B121,Grupos!$A$2:$B$619,2,FALSE) -> RITEL | B121: PAU506G-E | C121: CAJA PAU 30X50X6 ESTANDAR GAL | D121: 3991 | E121: 15292.76 | F121: 594.59 | G121: =E121+F121 -> 15887.35 | H121: =E121*D121 -> 61033405 | I121: =F121*D121 -> 2373008.7 | J121: =G121*D121 -> 63406414 | K121: =J121/$J$293 -> 0.047638341 | L121: =$K$364*K121/D121 -> 3087.9447 | M121: =F121*$M$363 -> 3193.1442 | N121: =G121+L121+M121 -> 22168.439 | O121: =N121*D121 -> 88474240 | P121: =Q121/D121 -> 37887.181 | Q121: 151207740 | R121: =O121/Q121 -> 0.58511714
A122: =VLOOKUP(B122,Grupos!$A$2:$B$619,2,FALSE) -> RITEL | B122: PAU506G-EH | C122: CAJA PAU 30X50X6 TAPA ESTANDAR CAJA PLUS SIN DF | D122: 318 | E122: 13775.09 | F122: 428.88 | G122: =E122+F122 -> 14203.97 | H122: =E122*D122 -> 4380478.6 | I122: =F122*D122 -> 136383.84 | J122: =G122*D122 -> 4516862.5 | K122: =J122/$J$293 -> 0.0033935973 | L122: =$K$364*K122/D122 -> 2760.7546 | M122: =F122*$M$363 -> 2303.2269 | N122: =G122+L122+M122 -> 19267.952 | O122: =N122*D122 -> 6127208.6 | P122: =Q122/D122 -> 39298.742 | Q122: 12497000 | R122: =O122/Q122 -> 0.49029436
...

Sheet Ene PUV lista
A2: DETALLE DE VENTAS 2026
E3: COSTO SIT UNITARIO | H3: COSTO SIT CANTIDAD
A4: GRUPO | B4: REF. | C4: DESCRIPCION | D4: CANT | E4: CUMAT | F4: CUMO | G4: CUNago | H4: CTMAT | I4: CTMO | J4: CTSIT | K4: %PART | L4: CIFU | M4: MOU | N4: CTU | O4: CT | P4: PUV | Q4: PU-LISTA | R4: DCTO PIE FACT | S4: % DCTO | T4: PRECIOTOT | U4: %CTO | V4: %Part.
A5: =VLOOKUP(B5,Grupos!$A$2:$B$619,2,FALSE) -> ACCESORIOS | B5: BN-08 | C5: BANDEJA PARA INTERIOR *I-8P* | D5: 1 | E5: 1216.9 | F5: 76.52 | G5: =E5+F5 -> 1293.42 | H5: =E5*D5 -> 1216.9 | I5: =F5*D5 -> 76.52 | J5: =G5*D5 -> 1293.42 | K5: =J5/$J$264 -> 9.7176893e-07 | L5: 251.39558 | M5: 410.93762 | N5: =G5+L5+M5 -> 1955.7532 | O5: =N5*D5 -> 1955.7532 | P5: =T5/D5 -> 12075 | Q5: 16100 | R5: =Q5-P5 -> 4025 | S5: =R5/Q5 -> 0.25 | T5: 12075 | U5: =O5/T5 -> 0.16196714
A6: =VLOOKUP(B6,Grupos!$A$2:$B$619,2,FALSE) -> ACCESORIOS | B6: BN-12 | C6: BANDEJA PARA INTERIOR *I-12P,I-212,I-312 | D6: 4 | E6: 1547.34 | F6: 77.82 | G6: =E6+F6 -> 1625.16 | H6: =E6*D6 -> 6189.36 | I6: =F6*D6 -> 311.28 | J6: =G6*D6 -> 6500.64 | K6: =J6/$J$264 -> 4.8840438e-06 | L6: 315.87422 | M6: 417.91904 | N6: =G6+L6+M6 -> 2358.9533 | O6: =N6*D6 -> 9435.8131 | P6: =T6/D6 -> 9492 | Q6: 22600 | R6: =Q6-P6 -> 13108 | S6: =R6/Q6 -> 0.58 | T6: 37968 | U6: =O6/T6 -> 0.24852015
A7: =VLOOKUP(B7,Grupos!$A$2:$B$619,2,FALSE) -> ACCESORIOS | B7: BN-24 | C7: BANDEJA PARA INTERIOR *I-224,I-324* | D7: 1 | E7: 2376.63 | F7: 89.86 | G7: =E7+F7 -> 2466.49 | H7: =E7*D7 -> 2376.63 | I7: =F7*D7 -> 89.86 | J7: =G7*D7 -> 2466.49 | K7: =J7/$J$264 -> 1.8531168e-06 | L7: 479.39932 | M7: 482.57781 | N7: =G7+L7+M7 -> 3428.4671 | O7: =N7*D7 -> 3428.4671 | P7: =T7/D7 -> 15664 | Q7: 33600 | R7: =Q7-P7 -> 17936 | S7: =R7/Q7 -> 0.53380952 | T7: 15664 | U7: =O7/T7 -> 0.21887558
A8: =VLOOKUP(B8,Grupos!$A$2:$B$619,2,FALSE) -> ACCESORIOS | B8: CHAPA-1 | C8: CHAPA GAVETA (TRPs) | D8: 3 | E8: 3200 | F8: 0 | G8: =E8+F8 -> 3200 | H8: =E8*D8 -> 9600 | I8: =F8*D8 -> 0 | J8: =G8*D8 -> 9600 | K8: =J8/$J$264 -> 7.2126469e-06 | L8: 621.96799 | M8: 0 | N8: =G8+L8+M8 -> 3821.968 | O8: =N8*D8 -> 11465.904 | P8: =T8/D8 -> 13987.5 | Q8: 18650 | R8: =Q8-P8 -> 4662.5 | S8: =R8/Q8 -> 0.25 | T8: 41962.5 | U8: =O8/T8 -> 0.27324168
A9: =VLOOKUP(B9,Grupos!$A$2:$B$619,2,FALSE) -> ACCESORIOS | B9: FLETES | C9: VALOR FLETES MERCANCIA | D9: 3 | E9: 0 | F9: 0 | G9: =E9+F9 -> 0 | H9: =E9*D9 -> 0 | I9: =F9*D9 -> 0 | J9: =G9*D9 -> 0 | K9: =J9/$J$264 -> 0 | L9: 0 | M9: 0 | N9: =G9+L9+M9 -> 0 | O9: =N9*D9 -> 0 | P9: =T9/D9 -> 147333.33 | Q9: 0 | S9: 0 | T9: 442000 | U9: =O9/T9 -> 0
A10: =VLOOKUP(B10,Grupos!$A$2:$B$619,2,FALSE) -> ACCESORIOS | B10: GRAPAM12-D | C10: GRAPA METALICA 1/2" DOBLE | D10: 39600 | E10: 59.89 | F10: 34.71 | G10: =E10+F10 -> 94.6 | H10: =E10*D10 -> 2371644 | I10: =F10*D10 -> 1374516 | J10: =G10*D10 -> 3746160 | K10: =J10/$J$264 -> 0.0028145551 | L10: 18.386929 | M10: 186.40414 | N10: =G10+L10+M10 -> 299.39107 | O10: =N10*D10 -> 11855886 | P10: =T10/D10 -> 126.09091 | Q10: 300 | R10: =Q10-P10 -> 173.90909 | S10: =R10/Q10 -> 0.57969695 | T10: 4993200.2 | U10: =O10/T10 -> 2.3744064
A11: =VLOOKUP(B11,Grupos!$A$2:$B$619,2,FALSE) -> ACCESORIOS | B11: GRAPAM12-S | C11: GRAPA METALICA 1/2" SENCILLA | D11: 2400 | E11: 43.39 | F11: 43.22 | G11: =E11+F11 -> 86.61 | H11: =E11*D11 -> 104136 | I11: =F11*D11 -> 103728 | J11: =G11*D11 -> 207864 | K11: =J11/$J$264 -> 0.00015617184 | L11: 16.833952 | M11: 232.10564 | N11: =G11+L11+M11 -> 335.54959 | O11: =N11*D11 -> 805319.03 | P11: =T11/D11 -> 102.50001 | Q11: 250 | R11: =Q11-P11 -> 147.49999 | S11: =R11/Q11 -> 0.58999997 | T11: 246000.02 | U11: =O11/T11 -> 3.2736543
A12: =VLOOKUP(B12,Grupos!$A$2:$B$619,2,FALSE) -> ACCESORIOS | B12: NEUTRO12 | C12: NEUTRO DE 12 CIRCUITOS | D12: 15 | E12: 2166.94 | F12: 0 | G12: =E12+F12 -> 2166.94 | H12: =E12*D12 -> 32504.1 | I12: =F12*D12 -> 0 | J12: =G12*D12 -> 32504.1 | K12: =J12/$J$264 -> 2.4420895e-05 | L12: 421.17729 | M12: 0 | N12: =G12+L12+M12 -> 2588.1173 | O12: =N12*D12 -> 38821.759 | P12: =T12/D12 -> 16952 | Q12: 31200 | R12: =Q12-P12 -> 14248 | S12: =R12/Q12 -> 0.45666667 | T12: 254280 | U12: =O12/T12 -> 0.15267327
A13: =VLOOKUP(B13,Grupos!$A$2:$B$619,2,FALSE) -> ACCESORIOS | B13: NEUTRO18 | C13: NEUTRO DE 18 CIRCUITOS | D13: 5 | E13: 3042.06 | F13: 0 | G13: =E13+F13 -> 3042.06 | H13: =E13*D13 -> 15210.3 | I13: =F13*D13 -> 0 | J13: =G13*D13 -> 15210.3 | K13: =J13/$J$264 -> 1.1427763e-05 | L13: 591.26998 | M13: 0 | N13: =G13+L13+M13 -> 3633.33 | O13: =N13*D13 -> 18166.65 | P13: =T13/D13 -> 19250 | Q13: 43750 | R13: =Q13-P13 -> 24500 | S13: =R13/Q13 -> 0.56 | T13: 96250 | U13: =O13/T13 -> 0.18874441
A14: =VLOOKUP(B14,Grupos!$A$2:$B$619,2,FALSE) -> ACCESORIOS | B14: NEUTRO24R | C14: NEUTRO DE 24 CIRCUITOS REFORZADO | D14: 13 | E14: 9036.65 | F14: 0 | G14: =E14+F14 -> 9036.65 | H14: =E14*D14 -> 117476.45 | I14: =F14*D14 -> 0 | J14: =G14*D14 -> 117476.45 | K14: =J14/$J$264 -> 8.8262099e-05 | L14: 1756.4085 | M14: 0 | N14: =G14+L14+M14 -> 10793.058 | O14: =N14*D14 -> 140309.76 | P14: =T14/D14 -> 38300.577 | Q14: 69250 | R14: =Q14-P14 -> 30949.423 | S14: =R14/Q14 -> 0.44692308 | T14: 497907.5 | U14: =O14/T14 -> 0.28179885
A15: =VLOOKUP(B15,Grupos!$A$2:$B$619,2,FALSE) -> ACCESORIOS | B15: NEUTRO42R | C15: NEUTRO DE 42 CIRCUITOS REFORZADO | D15: 2 | E15: 14590.87 | F15: 0 | G15: =E15+F15 -> 14590.87 | H15: =E15*D15 -> 29181.74 | I15: =F15*D15 -> 0 | J15: =G15*D15 -> 29181.74 | K15: =J15/$J$264 -> 2.1924748e-05 | L15: 2835.9544 | M15: 0 | N15: =G15+L15+M15 -> 17426.824 | O15: =N15*D15 -> 34853.649 | P15: =T15/D15 -> 85125 | Q15: 113500 | R15: =Q15-P15 -> 28375 | S15: =R15/Q15 -> 0.25 | T15: 170250 | U15: =O15/T15 -> 0.2047204
A16: =VLOOKUP(B16,Grupos!$A$2:$B$619,2,FALSE) -> ACCESORIOS | B16: NEUTRO6 | C16: NEUTRO DE 6 CIRCUITOS | D16: 10 | E16: 1229.39 | F16: 0 | G16: =E16+F16 -> 1229.39 | H16: =E16*D16 -> 12293.9 | I16: =F16*D16 -> 0 | J16: =G16*D16 -> 12293.9 | K16: =J16/$J$264 -> 9.2366208e-06 | L16: 238.95038 | M16: 0 | N16: =G16+L16+M16 -> 1468.3404 | O16: =N16*D16 -> 14683.404 | P16: =T16/D16 -> 6776 | Q16: 15400 | R16: =Q16-P16 -> 8624 | S16: =R16/Q16 -> 0.56 | T16: 67760 | U16: =O16/T16 -> 0.21669722
A17: =VLOOKUP(B17,Grupos!$A$2:$B$619,2,FALSE) -> ACCESORIOS | B17: NEUTRO8 | C17: NEUTRO DE 8 CIRCUITOS | D17: 10 | E17: 1583.66 | F17: 0 | G17: =E17+F17 -> 1583.66 | H17: =E17*D17 -> 15836.6 | I17: =F17*D17 -> 0 | J17: =G17*D17 -> 15836.6 | K17: =J17/$J$264 -> 1.1898313e-05 | L17: 307.80807 | M17: 0 | N17: =G17+L17+M17 -> 1891.4681 | O17: =N17*D17 -> 18914.681 | P17: =T17/D17 -> 9680 | Q17: 22000 | R17: =Q17-P17 -> 12320 | S17: =R17/Q17 -> 0.56 | T17: 96800 | U17: =O17/T17 -> 0.19539959
A18: =VLOOKUP(B18,Grupos!$A$2:$B$619,2,FALSE) -> ACCESORIOS | B18: NEUTRO8ALET | C18: NEUTRO 8 CIRCUITOS ALET | D18: 150 | E18: 1185 | F18: 0 | G18: =E18+F18 -> 1185 | H18: =E18*D18 -> 177750 | I18: =F18*D18 -> 0 | J18: =G18*D18 -> 177750 | K18: =J18/$J$264 -> 0.00013354666 | L18: 230.32252 | M18: 0 | N18: =G18+L18+M18 -> 1415.3225 | O18: =N18*D18 -> 212298.38 | P18: =T18/D18 -> 9240.0004 | Q18: 22000 | R18: =Q18-P18 -> 12760 | S18: =R18/Q18 -> 0.57999998 | T18: 1386000.1 | U18: =O18/T18 -> 0.15317343
A19: =VLOOKUP(B19,Grupos!$A$2:$B$619,2,FALSE) -> ACCESORIOS | B19: PUERTA VISOR8 | C19: PUERTA VISOR PLASTICO TABLERO 8 DE 95 AMP | D19: 20 | E19: 1003 | F19: 0 | G19: =E19+F19 -> 1003 | H19: =E19*D19 -> 20060 | I19: =F19*D19 -> 0 | J19: =G19*D19 -> 20060 | K19: =J19/$J$264 -> 1.5071427e-05 | L19: 194.94809 | M19: 0 | N19: =G19+L19+M19 -> 1197.9481 | O19: =N19*D19 -> 23958.962 | P19: =T19/D19 -> 3006 | Q19: 8350 | R19: =Q19-P19 -> 5344 | S19: =R19/Q19 -> 0.64 | T19: 60120 | U19: =O19/T19 -> 0.39851899
A20: =VLOOKUP(B20,Grupos!$A$2:$B$619,2,FALSE) -> ACCESORIOS | B20: T1012P | C20: TORNILLO LAMINA 10 x1/2 | D20: 24 | E20: 60 | F20: 0 | G20: =E20+F20 -> 60 | H20: =E20*D20 -> 1440 | I20: =F20*D20 -> 0 | J20: =G20*D20 -> 1440 | K20: =J20/$J$264 -> 1.081897e-06 | L20: 11.6619 | M20: 0 | N20: =G20+L20+M20 -> 71.6619 | O20: =N20*D20 -> 1719.8856 | P20: =T20/D20 -> 220 | Q20: 220 | R20: =Q20-P20 -> 0 | S20: =R20/Q20 -> 0 | T20: 5280 | U20: =O20/T20 -> 0.32573591
A21: =VLOOKUP(B21,Grupos!$A$2:$B$619,2,FALSE) -> ACCESORIOS | B21: T10P | C21: TORNILLO LAMINA 10 x 1. 1/4 PUNTA GUIA | D21: 584 | E21: 84.21 | F21: 0 | G21: =E21+F21 -> 84.21 | H21: =E21*D21 -> 49178.64 | I21: =F21*D21 -> 0 | J21: =G21*D21 -> 49178.64 | K21: =J21/$J$264 -> 3.6948767e-05 | L21: 16.367476 | M21: 0 | N21: =G21+L21+M21 -> 100.57748 | O21: =N21*D21 -> 58737.246 | P21: =T21/D21 -> 300 | Q21: 300 | R21: =Q21-P21 -> 0 | S21: =R21/Q21 -> 0 | T21: 175200 | U21: =O21/T21 -> 0.33525825
... A77: =VLOOKUP(B77,Grupos!$A$2:$B$619,2,FALSE) -> CE 125 | B77: CE125LXB | C77: CAJA 12X12X5 TAPA DATOS BLANCA | D77: 780 | E77: 2141.44 | F77: 426.01 | G77: =E77+F77 -> 2567.45 | H77: =E77*D77 -> 1670323.2 | I77: =F77*D77 -> 332287.8 | J77: =G77*D77 -> 2002611 | K77: =J77/$J$264 -> 0.0015045965 | L77: 499.02241 | M77: 2287.8141 | N77: =G77+L77+M77 -> 5354.2865 | O77: =N77*D77 -> 4176343.5 | P77: =T77/D77 -> 5226 | Q77: 15400 | R77: =Q77-P77 -> 10174 | S77: =R77/Q77 -> 0.66064935 | T77: 4076280 | U77: =O77/T77 -> 1.0245477
A78: =VLOOKUP(B78,Grupos!$A$2:$B$619,2,FALSE) -> EXCEDENTES INDUSTRIALES | B78: EXARCHIVO | C78: EXCEDENTES INDUSTRIALES DE ARCHIVO | D78: 85 | E78: 0 | F78: 0 | G78: =E78+F78 -> 0 | H78: =E78*D78 -> 0 | I78: =F78*D78 -> 0 | J78: =G78*D78 -> 0 | K78: =J78/$J$264 -> 0 | L78: 0 | M78: 0 | N78: =G78+L78+M78 -> 0 | O78: =N78*D78 -> 0 | P78: =T78/D78 -> 739.41176 | Q78: 0 | S78: 0 | T78: 62850 | U78: =O78/T78 -> 0
A79: =VLOOKUP(B79,Grupos!$A$2:$B$619,2,FALSE) -> EXCEDENTES INDUSTRIALES | B79: EXBOLSASP | C79: EXCEDENTES BOLSAS PLASTICAS | D79: 18.65 | E79: 0 | F79: 0 | G79: =E79+F79 -> 0 | H79: =E79*D79 -> 0 | I79: =F79*D79 -> 0 | J79: =G79*D79 -> 0 | K79: =J79/$J$264 -> 0 | L79: 0 | M79: 0 | N79: =G79+L79+M79 -> 0 | O79: =N79*D79 -> 0 | P79: =T79/D79 -> 500 | Q79: 0 | S79: 0 | T79: 9325 | U79: =O79/T79 -> 0
A80: =VLOOKUP(B80,Grupos!$A$2:$B$619,2,FALSE) -> EXCEDENTES INDUSTRIALES | B80: EXCARTON | C80: EXCEDENTES INDUSTRIALES DE CATON | D80: 864 | E80: 0 | F80: 0 | G80: =E80+F80 -> 0 | H80: =E80*D80 -> 0 | I80: =F80*D80 -> 0 | J80: =G80*D80 -> 0 | K80: =J80/$J$264 -> 0 | L80: 0 | M80: 0 | N80: =G80+L80+M80 -> 0 | O80: =N80*D80 -> 0 | P80: =T80/D80 -> 300 | Q80: 0 | S80: 0 | T80: 259200 | U80: =O80/T80 -> 0
A81: =VLOOKUP(B81,Grupos!$A$2:$B$619,2,FALSE) -> EXCEDENTES INDUSTRIALES | B81: EXCEBARREDU | C81: EXCEDENTES INDUSTRIALES - BARREDURA PP | D81: 548.05 | E81: 0 | F81: 0 | G81: =E81+F81 -> 0 | H81: =E81*D81 -> 0 | I81: =F81*D81 -> 0 | J81: =G81*D81 -> 0 | K81: =J81/$J$264 -> 0 | L81: 0 | M81: 0 | N81: =G81+L81+M81 -> 0 | O81: =N81*D81 -> 0 | P81: =T81/D81 -> 500 | Q81: 0 | S81: 0 | T81: 274025 | U81: =O81/T81 -> 0
A82: =VLOOKUP(B82,Grupos!$A$2:$B$619,2,FALSE) -> EXCEDENTES INDUSTRIALES | B82: EXCEDENTES | C82: EXCEDENTES INDUSTRIALES MADEROS CORTOS | D82: 112 | E82: 0 | F82: 0 | G82: =E82+F82 -> 0 | H82: =E82*D82 -> 0 | I82: =F82*D82 -> 0 | J82: =G82*D82 -> 0 | K82: =J82/$J$264 -> 0 | L82: 0 | M82: 0 | N82: =G82+L82+M82 -> 0 | O82: =N82*D82 -> 0 | P82: =T82/D82 -> 500 | Q82: 0 | S82: 0 | T82: 56000 | U82: =O82/T82 -> 0
A83: =VLOOKUP(B83,Grupos!$A$2:$B$619,2,FALSE) -> EXCEDENTES INDUSTRIALES | B83: EXCEDENTESIN | C83: EXCEDENTES INDUSTRIALES MADEROS LARGOS | D83: 67 | E83: 0 | F83: 0 | G83: =E83+F83 -> 0 | H83: =E83*D83 -> 0 | I83: =F83*D83 -> 0 | J83: =G83*D83 -> 0 | K83: =J83/$J$264 -> 0 | L83: 0 | M83: 0 | N83: =G83+L83+M83 -> 0 | O83: =N83*D83 -> 0 | P83: =T83/D83 -> 1000 | Q83: 0 | S83: 0 | T83: 67000 | U83: =O83/T83 -> 0
A84: =VLOOKUP(B84,Grupos!$A$2:$B$619,2,FALSE) -> EXCEDENTES INDUSTRIALES | B84: EXCETORTAPOC | C84: EXCEDENTES INDUSTRIALES TORTA POLICARBONATO | D84: 292.5 | E84: 0 | F84: 0 | G84: =E84+F84 -> 0 | H84: =E84*D84 -> 0 | I84: =F84*D84 -> 0 | J84: =G84*D84 -> 0 | K84: =J84/$J$264 -> 0 | L84: 0 | M84: 0 | N84: =G84+L84+M84 -> 0 | O84: =N84*D84 -> 0 | P84: =T84/D84 -> 250 | Q84: 0 | S84: 0 | T84: 73125 | U84: =O84/T84 -> 0
A85: =VLOOKUP(B85,Grupos!$A$2:$B$619,2,FALSE) -> EXCEDENTES INDUSTRIALES | B85: EXCETORTAPOLIP | C85: EXCEDENTES INDUSTRIALES TORTA POLIPROPILENO | D85: 252.6 | E85: 0 | F85: 0 | G85: =E85+F85 -> 0 | H85: =E85*D85 -> 0 | I85: =F85*D85 -> 0 | J85: =G85*D85 -> 0 | K85: =J85/$J$264 -> 0 | L85: 0 | M85: 0 | N85: =G85+L85+M85 -> 0 | O85: =N85*D85 -> 0 | P85: =T85/D85 -> 250 | Q85: 0 | S85: 0 | T85: 63150 | U85: =O85/T85 -> 0
A86: =VLOOKUP(B86,Grupos!$A$2:$B$619,2,FALSE) -> EXCEDENTES INDUSTRIALES | B86: EXCINDUSTR | C86: EXCEDENTES INDUSTRIALES - REMOLIDO DE POLICARBONATO | D86: 156.85 | E86: 0 | F86: 0 | G86: =E86+F86 -> 0 | H86: =E86*D86 -> 0 | I86: =F86*D86 -> 0 | J86: =G86*D86 -> 0 | K86: =J86/$J$264 -> 0 | L86: 0 | M86: 0 | N86: =G86+L86+M86 -> 0 | O86: =N86*D86 -> 0 | P86: =T86/D86 -> 500 | Q86: 0 | S86: 0 | T86: 78425 | U86: =O86/T86 -> 0
A87: =VLOOKUP(B87,Grupos!$A$2:$B$619,2,FALSE) -> EXCEDENTES INDUSTRIALES | B87: EXCOSTALES | C87: EXCEDENTE DE PLASTICO COSTALES | D87: 909 | E87: 0 | F87: 0 | G87: =E87+F87 -> 0 | H87: =E87*D87 -> 0 | I87: =F87*D87 -> 0 | J87: =G87*D87 -> 0 | K87: =J87/$J$264 -> 0 | L87: 0 | M87: 0 | N87: =G87+L87+M87 -> 0 | O87: =N87*D87 -> 0 | P87: =T87/D87 -> 220 | Q87: 0 | S87: 0 | T87: 199980 | U87: =O87/T87 -> 0
A88: =VLOOKUP(B88,Grupos!$A$2:$B$619,2,FALSE) -> INTERIORES | B88: I12P | C88: INTERIOR 12 CTOS 2F 125 AMP | D88: 2 | E88: 15453.34 | F88: 935.42 | G88: =E88+F88 -> 16388.76 | H88: =E88*D88 -> 30906.68 | I88: =F88*D88 -> 1870.84 | J88: =G88*D88 -> 32777.52 | K88: =J88/$J$264 -> 2.462632e-05 | L88: 3185.4013 | M88: 5023.5137 | N88: =G88+L88+M88 -> 24597.675 | O88: =N88*D88 -> 49195.35 | P88: =T88/D88 -> 64828 | Q88: 170600 | R88: =Q88-P88 -> 105772 | S88: =R88/Q88 -> 0.62 | T88: 129656 | U88: =O88/T88 -> 0.3794298
A89: =VLOOKUP(B89,Grupos!$A$2:$B$619,2,FALSE) -> INTERIORES | B89: I18P | C89: INTERIOR 18 CTOS 2F 125 AMP | D89: 8 | E89: 21969.01 | F89: 1049.78 | G89: =E89+F89 -> 23018.79 | H89: =E89*D89 -> 175752.08 | I89: =F89*D89 -> 8398.24 | J89: =G89*D89 -> 184150.32 | K89: =J89/$J$264 -> 0.00013835534 | L89: 4474.0471 | M89: 5637.6645 | N89: =G89+L89+M89 -> 33130.502 | O89: =N89*D89 -> 265044.01 | P89: =T89/D89 -> 83220 | Q89: 219000 | R89: =Q89-P89 -> 135780 | S89: =R89/Q89 -> 0.62 | T89: 665760 | U89: =O89/T89 -> 0.39810745
A90: =VLOOKUP(B90,Grupos!$A$2:$B$619,2,FALSE) -> INTERIORES | B90: I224 | C90: INTERIOR 24 CTOS 2F 225 AMP | D90: 2 | E90: 39787.73 | F90: 2660.46 | G90: =E90+F90 -> 42448.19 | H90: =E90*D90 -> 79575.46 | I90: =F90*D90 -> 5320.92 | J90: =G90*D90 -> 84896.38 | K90: =J90/$J$264 -> 6.3784126e-05 | L90: 8250.4424 | M90: 14287.547 | N90: =G90+L90+M90 -> 64986.179 | O90: =N90*D90 -> 129972.36 | P90: =T90/D90 -> 143963 | Q90: 378850 | R90: =Q90-P90 -> 234887 | S90: =R90/Q90 -> 0.62 | T90: 287926 | U90: =O90/T90 -> 0.4514089
A91: =VLOOKUP(B91,Grupos!$A$2:$B$619,2,FALSE) -> INTERIORES | B91: I230 | C91: INTERIOR 30 CTOS 2F 225 AMP | D91: 3 | E91: 49797.97 | F91: 2108.2 | G91: =E91+F91 -> 51906.17 | H91: =E91*D91 -> 149393.91 | I91: =F91*D91 -> 6324.6 | J91: =G91*D91 -> 155718.51 | K91: =J91/$J$264 -> 0.00011699402 | L91: 10088.743 | M91: 11321.729 | N91: =G91+L91+M91 -> 73316.641 | O91: =N91*D91 -> 219949.92 | P91: =T91/D91 -> 184000 | Q91: 480000 | R91: =Q91-P91 -> 296000 | S91: =R91/Q91 -> 0.61666667 | T91: 551999.99 | U91: =O91/T91 -> 0.39846001
A92: =VLOOKUP(B92,Grupos!$A$2:$B$619,2,FALSE) -> INTERIORES | B92: I312 | C92: INTERIOR 12 CTOS 3F 225 AMP | D92: 34 | E92: 25206.92 | F92: 1511.1 | G92: =E92+F92 -> 26718.02 | H92: =E92*D92 -> 857035.28 | I92: =F92*D92 -> 51377.4 | J92: =G92*D92 -> 908412.68 | K92: =J92/$J$264 -> 0.00068250624 | L92: 5193.0479 | M92: 8115.105 | N92: =G92+L92+M92 -> 40026.173 | O92: =N92*D92 -> 1360889.9 | P92: =T92/D92 -> 98693.088 | Q92: 256150 | R92: =Q92-P92 -> 157456.91 | S92: =R92/Q92 -> 0.61470588 | T92: 3355565 | U92: =O92/T92 -> 0.40556207
A93: =VLOOKUP(B93,Grupos!$A$2:$B$619,2,FALSE) -> INTERIORES | B93: I318 | C93: INTERIOR 18 CTOS 3F 225 AMP | D93: 13 | E93: 37165.5 | F93: 2067.14 | G93: =E93+F93 -> 39232.64 | H93: =E93*D93 -> 483151.5 | I93: =F93*D93 -> 26872.82 | J93: =G93*D93 -> 510024.32 | K93: =J93/$J$264 -> 0.00038319014 | L93: 7625.452 | M93: 11101.223 | N93: =G93+L93+M93 -> 57959.315 | O93: =N93*D93 -> 753471.09 | P93: =T93/D93 -> 119073 | Q93: 313350 | R93: =Q93-P93 -> 194277 | S93: =R93/Q93 -> 0.62 | T93: 1547949 | U93: =O93/T93 -> 0.48675448
A94: =VLOOKUP(B94,Grupos!$A$2:$B$619,2,FALSE) -> INTERIORES | B94: I318-125 | C94: INTERIOR 18 CTOS 3F 125 AMP | D94: 2 | E94: 30107.38 | F94: 1595.87 | G94: =E94+F94 -> 31703.25 | H94: =E94*D94 -> 60214.76 | I94: =F94*D94 -> 3191.74 | J94: =G94*D94 -> 63406.5 | K94: =J94/$J$264 -> 4.7638406e-05 | L94: 6162.0021 | M94: 8570.3478 | N94: =G94+L94+M94 -> 46435.6 | O94: =N94*D94 -> 92871.2 | P94: =T94/D94 -> 109472 | Q94: 248800 | R94: =Q94-P94 -> 139328 | S94: =R94/Q94 -> 0.56 | T94: 218944 | U94: =O94/T94 -> 0.42417787
A95: =VLOOKUP(B95,Grupos!$A$2:$B$619,2,FALSE) -> INTERIORES | B95: I318-BIMETALICO | C95: INTERIOR 18 CTOS 3 FASES TRP318 BIMETALICO | D95: 7 | E95: 12022 | F95: 2049.66 | G95: =E95+F95 -> 14071.66 | H95: =E95*D95 -> 84154 | I95: =F95*D95 -> 14347.62 | J95: =G95*D95 -> 98501.62 | K95: =J95/$J$264 -> 7.4005979e-05 | L95: 2735.0382 | M95: 11007.35 | N95: =G95+L95+M95 -> 27814.048 | O95: =N95*D95 -> 194698.33 | P95: =T95/D95 -> 102008.01 | Q95: 248800 | R95: =Q95-P95 -> 146791.99 | S95: =R95/Q95 -> 0.58999997 | T95: 714056.05 | U95: =O95/T95 -> 0.27266534
A96: =VLOOKUP(B96,Grupos!$A$2:$B$619,2,FALSE) -> INTERIORES | B96: I324 | C96: INTERIOR 24 CTOS 3F 225 AMP | D96: 1 | E96: 49135.39 | F96: 2558.08 | G96: =E96+F96 -> 51693.47 | H96: =E96*D96 -> 49135.39 | I96: =F96*D96 -> 2558.08 | J96: =G96*D96 -> 51693.47 | K96: =J96/$J$264 -> 3.8838203e-05 | L96: 10047.401 | M96: 13737.733 | N96: =G96+L96+M96 -> 75478.604 | O96: =N96*D96 -> 75478.604 | P96: =T96/D96 -> 178059.51 | Q96: 378850 | R96: =Q96-P96 -> 200790.49 | S96: =R96/Q96 -> 0.52999997 | T96: 178059.51 | U96: =O96/T96 -> 0.42389538
A97: =VLOOKUP(B97,Grupos!$A$2:$B$619,2,FALSE) -> INTERIORES | B97: I330 | C97: INTERIOR 30 CTOS 3F 225 AMP | D97: 2 | E97: 61058.56 | F97: 2754.57 | G97: =E97+F97 -> 63813.13 | H97: =E97*D97 -> 122117.12 | I97: =F97*D97 -> 5509.14 | J97: =G97*D97 -> 127626.26 | K97: =J97/$J$264 -> 9.5887827e-05 | L97: 12403.039 | M97: 14792.949 | N97: =G97+L97+M97 -> 91009.117 | O97: =N97*D97 -> 182018.23 | P97: =T97/D97 -> 182400 | Q97: 480000 | R97: =Q97-P97 -> 297600 | S97: =R97/Q97 -> 0.62 | T97: 364800 | U97: =O97/T97 -> 0.4989535
A98: =VLOOKUP(B98,Grupos!$A$2:$B$619,2,FALSE) -> INTERIORES | B98: I336 | C98: INTERIOR 36 CTOS 3F 225 AMP | D98: 6 | E98: 73332.86 | F98: 3209.09 | G98: =E98+F98 -> 76541.95 | H98: =E98*D98 -> 439997.16 | I98: =F98*D98 -> 19254.54 | J98: =G98*D98 -> 459251.7 | K98: =J98/$J$264 -> 0.00034504378 | L98: 14877.076 | M98: 17233.871 | N98: =G98+L98+M98 -> 108652.9 | O98: =N98*D98 -> 651917.38 | P98: =T98/D98 -> 200602 | Q98: 527900 | R98: =Q98-P98 -> 327298 | S98: =R98/Q98 -> 0.62000001 | T98: 1203612 | U98: =O98/T98 -> 0.54163417
A99: =VLOOKUP(B99,Grupos!$A$2:$B$619,2,FALSE) -> INTERIORES | B99: I342 | C99: INTERIOR 42 CTOS 3F 225 AMP | D99: 1 | E99: 85554.43 | F99: 4227.38 | G99: =E99+F99 -> 89781.81 | H99: =E99*D99 -> 85554.43 | I99: =F99*D99 -> 4227.38 | J99: =G99*D99 -> 89781.81 | K99: =J99/$J$264 -> 6.7454634e-05 | L99: 17450.441 | M99: 22702.424 | N99: =G99+L99+M99 -> 129934.67 | O99: =N99*D99 -> 129934.67 | P99: =T99/D99 -> 229577 | Q99: 604150 | R99: =Q99-P99 -> 374573 | S99: =R99/Q99 -> 0.62 | T99: 229577 | U99: =O99/T99 -> 0.56597427
... A263: =VLOOKUP(B263,Grupos!$A$2:$B$619,2,FALSE) -> TAPAS PLASTICAS | B263: TPL4X4-LH | C263: TAPA PLASTICA LISA 4X4 LIBRE DE HALOGENOS | D263: 17670 | E263: 96.03 | F263: 23.29 | G263: =E263+F263 -> 119.32 | H263: =E263*D263 -> 1696850.1 | I263: =F263*D263 -> 411534.3 | J263: =G263*D263 -> 2108384.4 | K263: =J263/$J$264 -> 0.0015840658 | L263: 23.191632 | M263: 125.07497 | N263: =G263+L263+M263 -> 267.58661 | O263: =N263*D263 -> 4728255.3 | P263: =T263/D263 -> 281.80646 | Q263: 800 | R263: =Q263-P263 -> 518.19354 | S263: =R263/Q263 -> 0.64774192 | T263: 4979520.2 | U263: =O263/T263 -> 0.94954034
A264: TOTAL FABRICADO | D264: 1836133.7 | G264: =E264+F264 -> 0 | H264: 1.2267847e+09 | I264: 1.0421076e+08 | J264: 1.3309954e+09 | M264: 0 | O264: 2.1493405e+09 | T264: 3.2826161e+09 | U264: =O264/T264 -> 0.65476449 | V264: =T264/T329 -> 0.86916147
A265: =VLOOKUP(B265,Grupos!$A$2:$B$619,2,FALSE) -> BREAKERS | B265: ITM115 | C265: INTERRUPTOR TERMOMAGNETICO 1P 15 AMP BLANCO | D265: 2124 | E265: 5808.8316 | G265: =E265+F265 -> 5808.8316 | H265: =E265*D265 -> 12337958 | I265: =F265*D265 -> 0 | J265: =G265*D265 -> 12337958 | L265: 0 | M265: 0 | N265: =G265+L265+M265 -> 5808.8316 | O265: =N265*D265 -> 12337958 | P265: =T265/D265 -> 6953.1073 | Q265: 21250 | R265: =Q265-P265 -> 14296.893 | S265: =R265/Q265 -> 0.67279495 | T265: 14768400 | U265: =O265/T265 -> 0.83542959
A266: =VLOOKUP(B266,Grupos!$A$2:$B$619,2,FALSE) -> BREAKERS | B266: ITM115NG | C266: INTERRUPTOR TERMOMAGNETICO 1P 15 AMP NEGRO | D266: 324 | E266: 5815.0243 | G266: =E266+F266 -> 5815.0243 | H266: =E266*D266 -> 1884067.9 | I266: =F266*D266 -> 0 | J266: =G266*D266 -> 1884067.9 | L266: 0 | M266: 0 | N266: =G266+L266+M266 -> 5815.0243 | O266: =N266*D266 -> 1884067.9 | P266: =T266/D266 -> 7029.6296 | Q266: 21250 | R266: =Q266-P266 -> 14220.37 | S266: =R266/Q266 -> 0.6691939 | T266: 2277600 | U266: =O266/T266 -> 0.82721632
A267: =VLOOKUP(B267,Grupos!$A$2:$B$619,2,FALSE) -> BREAKERS | B267: ITM120 | C267: INTERRUPTOR TERMOMAGNETICO 1P 20 AMP BLANCO | D267: 9420 | E267: 5212.9902 | G267: =E267+F267 -> 5212.9902 | H267: =E267*D267 -> 49106367 | I267: =F267*D267 -> 0 | J267: =G267*D267 -> 49106367 | L267: 0 | M267: 0 | N267: =G267+L267+M267 -> 5212.9902 | O267: =N267*D267 -> 49106367 | P267: =T267/D267 -> 6961.4331 | Q267: 21250 | R267: =Q267-P267 -> 14288.567 | S267: =R267/Q267 -> 0.67240315 | T267: 65576700 | U267: =O267/T267 -> 0.74883865
A268: =VLOOKUP(B268,Grupos!$A$2:$B$619,2,FALSE) -> BREAKERS | B268: ITM120NG | C268: INTERRUPTOR TERMOMAGNETICO 1P 20 AMP NEGRO | D268: 6677 | E268: 5212.9902 | G268: =E268+F268 -> 5212.9902 | H268: =E268*D268 -> 34807135 | I268: =F268*D268 -> 0 | J268: =G268*D268 -> 34807135 | L268: 0 | M268: 0 | N268: =G268+L268+M268 -> 5212.9902 | O268: =N268*D268 -> 34807135 | P268: =T268/D268 -> 6949.9476 | Q268: 21250 | R268: =Q268-P268 -> 14300.052 | S268: =R268/Q268 -> 0.67294364 | T268: 46404800 | U268: =O268/T268 -> 0.75007618
A269: =VLOOKUP(B269,Grupos!$A$2:$B$619,2,FALSE) -> BREAKERS | B269: ITM130 | C269: INTERRUPTOR TERMOMAGNETICO 1P 30 AMP BLANCO | D269: 2772 | E269: 5212.9902 | G269: =E269+F269 -> 5212.9902 | H269: =E269*D269 -> 14450409 | I269: =F269*D269 -> 0 | J269: =G269*D269 -> 14450409 | L269: 0 | M269: 0 | N269: =G269+L269+M269 -> 5212.9902 | O269: =N269*D269 -> 14450409 | P269: =T269/D269 -> 6935.2814 | Q269: 21250 | R269: =Q269-P269 -> 14314.719 | S269: =R269/Q269 -> 0.67363382 | T269: 19224600 | U269: =O269/T269 -> 0.75166239
A270: =VLOOKUP(B270,Grupos!$A$2:$B$619,2,FALSE) -> BREAKERS | B270: ITM130NG | C270: INTERRUPTOR TERMOMAGNETICO 1P 30 AMP NEGRO | D270: 2184 | E270: 5212.9902 | G270: =E270+F270 -> 5212.9902 | H270: =E270*D270 -> 11385171 | I270: =F270*D270 -> 0 | J270: =G270*D270 -> 11385171 | L270: 0 | M270: 0 | N270: =G270+L270+M270 -> 5212.9902 | O270: =N270*D270 -> 11385171 | P270: =T270/D270 -> 7028.8462 | Q270: 21250 | R270: =Q270-P270 -> 14221.154 | S270: =R270/Q270 -> 0.66923077 | T270: 15351000 | U270: =O270/T270 -> 0.7416566
A271: =VLOOKUP(B271,Grupos!$A$2:$B$619,2,FALSE) -> BREAKERS | B271: ITM140 | C271: INTERRUPTOR TERMOMAGNETICO 1P 40 AMP BLANCO | D271: 1356 | E271: 5541.3675 | G271: =E271+F271 -> 5541.3675 | H271: =E271*D271 -> 7514094.3 | I271: =F271*D271 -> 0 | J271: =G271*D271 -> 7514094.3 | L271: 0 | M271: 0 | N271: =G271+L271+M271 -> 5541.3675 | O271: =N271*D271 -> 7514094.3 | P271: =T271/D271 -> 6989.1593 | Q271: 21250 | R271: =Q271-P271 -> 14260.841 | S271: =R271/Q271 -> 0.67109839 | T271: 9477300 | U271: =O271/T271 -> 0.7928518
A272: =VLOOKUP(B272,Grupos!$A$2:$B$619,2,FALSE) -> BREAKERS | B272: ITM140NG | C272: INTERRUPTOR TERMOMAGNETICO 1P 40 AMP NEGRO | D272: 1992 | E272: 5541.3675 | G272: =E272+F272 -> 5541.3675 | H272: =E272*D272 -> 11038404 | I272: =F272*D272 -> 0 | J272: =G272*D272 -> 11038404 | L272: 0 | M272: 0 | N272: =G272+L272+M272 -> 5541.3675 | O272: =N272*D272 -> 11038404 | P272: =T272/D272 -> 6974.3976 | Q272: 21250 | R272: =Q272-P272 -> 14275.602 | S272: =R272/Q272 -> 0.67179305 | T272: 13893000 | U272: =O272/T272 -> 0.79452991
A273: =VLOOKUP(B273,Grupos!$A$2:$B$619,2,FALSE) -> BREAKERS | B273: ITM150 | C273: INTERRUPTOR TERMOMAGNETICO 1P 50 AMP BLANCO | D273: 252 | E273: 6052.9657 | G273: =E273+F273 -> 6052.9657 | H273: =E273*D273 -> 1525347.4 | I273: =F273*D273 -> 0 | J273: =G273*D273 -> 1525347.4 | L273: 0 | M273: 0 | N273: =G273+L273+M273 -> 6052.9657 | O273: =N273*D273 -> 1525347.4 | P273: =T273/D273 -> 6961.9048 | Q273: 21250 | R273: =Q273-P273 -> 14288.095 | S273: =R273/Q273 -> 0.67238095 | T273: 1754400 | U273: =O273/T273 -> 0.86944104
A274: =VLOOKUP(B274,Grupos!$A$2:$B$619,2,FALSE) -> BREAKERS | B274: ITM150NG | C274: INTERRUPTOR TERMOMAGNETICO 1P 50 AMP NEGRO | D274: 600 | E274: 5541.3675 | G274: =E274+F274 -> 5541.3675 | H274: =E274*D274 -> 3324820.5 | I274: =F274*D274 -> 0 | J274: =G274*D274 -> 3324820.5 | L274: 0 | M274: 0 | N274: =G274+L274+M274 -> 5541.3675 | O274: =N274*D274 -> 3324820.5 | P274: =T274/D274 -> 6948 | Q274: 21250 | R274: =Q274-P274 -> 14302 | S274: =R274/Q274 -> 0.67303529 | T274: 4168800 | U274: =O274/T274 -> 0.79754857
A275: =VLOOKUP(B275,Grupos!$A$2:$B$619,2,FALSE) -> BREAKERS | B275: ITM160 | C275: INTERRUPTOR TERMOMAGNETICO 1P 60 AMP BLANCO | D275: 252 | E275: 6066.47 | G275: =E275+F275 -> 6066.47 | H275: =E275*D275 -> 1528750.4 | I275: =F275*D275 -> 0 | J275: =G275*D275 -> 1528750.4 | L275: 0 | M275: 0 | N275: =G275+L275+M275 -> 6066.47 | O275: =N275*D275 -> 1528750.4 | P275: =T275/D275 -> 6978.5714 | Q275: 21250 | R275: =Q275-P275 -> 14271.429 | S275: =R275/Q275 -> 0.67159664 | T275: 1758600 | U275: =O275/T275 -> 0.86929969
A276: =VLOOKUP(B276,Grupos!$A$2:$B$619,2,FALSE) -> BREAKERS | B276: ITM160NG | C276: INTERRUPTOR TERMOMAGNETICO 1P 60 AMP NEGRO | D276: 72 | E276: 6093.0433 | G276: =E276+F276 -> 6093.0433 | H276: =E276*D276 -> 438699.12 | I276: =F276*D276 -> 0 | J276: =G276*D276 -> 438699.12 | L276: 0 | M276: 0 | N276: =G276+L276+M276 -> 6093.0433 | O276: =N276*D276 -> 438699.12 | P276: =T276/D276 -> 7050 | Q276: 21250 | R276: =Q276-P276 -> 14200 | S276: =R276/Q276 -> 0.66823529 | T276: 507600 | U276: =O276/T276 -> 0.86426147
... A315: =VLOOKUP(B315,Grupos!$A$2:$B$619,2,FALSE) -> BREAKERS | B315: ITM-R363 | C315: INTERRUPTOR TERMOMAGNÉTICO 3P 63 AMP TIPO RIEL | D315: 4 | E315: 16739.136 | G315: =E315+F315 -> 16739.136 | H315: =E315*D315 -> 66956.543 | I315: =F315*D315 -> 0 | J315: =G315*D315 -> 66956.543 | L315: 0 | M315: 0 | N315: =G315+L315+M315 -> 16739.136 | O315: =N315*D315 -> 66956.543 | P315: =T315/D315 -> 19500 | Q315: 20150 | R315: =Q315-P315 -> 650 | S315: =R315/Q315 -> 0.032258065 | T315: 78000 | U315: =O315/T315 -> 0.85841721
A316: TOTAL BREAKERS | D316: =SUM(D265:D315) -> 36909 | G316: =E316+F316 -> 0 | H316: =SUM(H265:H315) -> 2.4690815e+08 | I316: =SUM(I265:I315) -> 0 | J316: =SUM(J265:J315) -> 2.4690815e+08 | O316: =SUM(O265:O315) -> 2.4690815e+08 | T316: =SUM(T265:T315) -> 3.2617492e+08 | U316: =O316/T316 -> 0.75698078 | V316: =T316/T329 -> 0.086363639
A317: =VLOOKUP(B317,Grupos!$A$2:$B$619,2,FALSE) -> VARILLAS | B317: VCU C-120 | C317: VARILLA COBRE 5/8 X 120 | D317: 58 | E317: 88350 | F317: 114.4 | G317: =E317+F317 -> 88464.4 | H317: =E317*D317 -> 5124300 | I317: =F317*D317 -> 6635.2 | J317: =G317*D317 -> 5130935.2 | M317: 614.3657 | N317: =G317+L317+M317 -> 89078.766 | O317: =N317*D317 -> 5166568.4 | P317: =T317/D317 -> 105512.07 | Q317: 0 | T317: 6119700 | U317: =O317/T317 -> 0.84425191
A318: =VLOOKUP(B318,Grupos!$A$2:$B$619,2,FALSE) -> VARILLAS | B318: VCU C-150 | C318: VARILLA COBRE 5/8 X 150 | D318: 28 | E318: 110206.62 | F318: 165.47 | G318: =E318+F318 -> 110372.09 | H318: =E318*D318 -> 3085785.3 | I318: =F318*D318 -> 4633.16 | J318: =G318*D318 -> 3090418.5 | M318: 888.62843 | N318: =G318+L318+M318 -> 111260.72 | O318: =N318*D318 -> 3115300.1 | P318: =T318/D318 -> 131425 | Q318: 0 | T318: 3679900 | U318: =O318/T318 -> 0.84657193
A319: =VLOOKUP(B319,Grupos!$A$2:$B$619,2,FALSE) -> VARILLAS | B319: VCU C-180 | C319: VARILLA COBRE 5/8 X 180 | D319: 34 | E319: 131328.5 | F319: 162.95 | G319: =E319+F319 -> 131491.45 | H319: =E319*D319 -> 4465169 | I319: =F319*D319 -> 5540.3 | J319: =G319*D319 -> 4470709.3 | M319: 875.0952 | N319: =G319+L319+M319 -> 132366.55 | O319: =N319*D319 -> 4500462.5 | P319: =T319/D319 -> 147705.88 | Q319: 0 | T319: 5022000 | U319: =O319/T319 -> 0.89614945
A320: =VLOOKUP(B320,Grupos!$A$2:$B$619,2,FALSE) -> VARILLAS | B320: VCU C-240 | C320: VARILLA COBRE 5/8 X 240 | D320: 517 | E320: 175109.5 | F320: 110.24 | G320: =E320+F320 -> 175219.74 | H320: =E320*D320 -> 90531612 | I320: =F320*D320 -> 56994.08 | J320: =G320*D320 -> 90588606 | M320: 592.02513 | N320: =G320+L320+M320 -> 175811.77 | O320: =N320*D320 -> 90894683 | P320: =T320/D320 -> 194561.49 | Q320: 0 | T320: 100588292 | U320: =O320/T320 -> 0.90363084
A321: =VLOOKUP(B321,Grupos!$A$2:$B$619,2,FALSE) -> VARILLAS | B321: VCU1/2-120 | C321: VARILLA COBRE 1/2 X 120 | D321: 200 | E321: 72600 | G321: =E321+F321 -> 72600 | H321: =E321*D321 -> 14520000 | I321: =F321*D321 -> 0 | J321: =G321*D321 -> 14520000 | M321: 0 | N321: =G321+L321+M321 -> 72600 | O321: =N321*D321 -> 14520000 | P321: =T321/D321 -> 86700 | Q321: 0 | T321: 17340000 | U321: =O321/T321 -> 0.83737024
A322: =VLOOKUP(B322,Grupos!$A$2:$B$619,2,FALSE) -> VARILLAS | B322: VCU1/2-150 | C322: VARILLA COBRE 1/2 X 150 | D322: 180 | E322: 91050 | G322: =E322+F322 -> 91050 | H322: =E322*D322 -> 16389000 | I322: =F322*D322 -> 0 | J322: =G322*D322 -> 16389000 | M322: 0 | N322: =G322+L322+M322 -> 91050 | O322: =N322*D322 -> 16389000 | P322: =T322/D322 -> 108330 | Q322: 0 | T322: 19499400 | U322: =O322/T322 -> 0.8404874
A323: =VLOOKUP(B323,Grupos!$A$2:$B$619,2,FALSE) -> VARILLAS | B323: VCU1/2-180 | C323: VARILLA COBRE 1/2 X 180 | D323: 37 | E323: 107710 | G323: =E323+F323 -> 107710 | H323: =E323*D323 -> 3985270 | I323: =F323*D323 -> 0 | J323: =G323*D323 -> 3985270 | M323: 0 | N323: =G323+L323+M323 -> 107710 | O323: =N323*D323 -> 3985270 | P323: =T323/D323 -> 101096.06 | Q323: 0 | T323: 3740554 | U323: =O323/T323 -> 1.0654224
A324: =VLOOKUP(B324,Grupos!$A$2:$B$619,2,FALSE) -> VARILLAS | B324: VCU1/2-240 | C324: VARILLA COBRE 1/2 X 240 | D324: 45 | E324: 144042.5 | G324: =E324+F324 -> 144042.5 | H324: =E324*D324 -> 6481912.5 | I324: =F324*D324 -> 0 | J324: =G324*D324 -> 6481912.5 | M324: 0 | N324: =G324+L324+M324 -> 144042.5 | O324: =N324*D324 -> 6481912.5 | P324: =T324/D324 -> 161271.56 | Q324: 0 | T324: 7257220 | U324: =O324/T324 -> 0.89316742
A325: =VLOOKUP(B325,Grupos!$A$2:$B$619,2,FALSE) -> VARILLAS | B325: VCU-E 120X1200 | C325: VARILLA ENCHAQUETADA 1/2 X 120 | D325: 210 | E325: 9215 | F325: 9.42 | G325: =E325+F325 -> 9224.42 | H325: =E325*D325 -> 1935150 | I325: =F325*D325 -> 1978.2 | J325: =G325*D325 -> 1937128.2 | M325: 50.588504 | N325: =G325+L325+M325 -> 9275.0085 | O325: =N325*D325 -> 1947751.8 | P325: =T325/D325 -> 11723.81 | Q325: 0 | T325: 2462000 | U325: =O325/T325 -> 0.79112583
A326: =VLOOKUP(B326,Grupos!$A$2:$B$619,2,FALSE) -> VARILLAS | B326: VCU-E 120X1500 | C326: VARILLA ENCHAQUETADA 1/2 X 150 | D326: 170 | E326: 12125 | F326: 69.94 | G326: =E326+F326 -> 12194.94 | H326: =E326*D326 -> 2061250 | I326: =F326*D326 -> 11889.8 | J326: =G326*D326 -> 2073139.8 | M326: 375.60085 | N326: =G326+L326+M326 -> 12570.541 | O326: =N326*D326 -> 2136991.9 | P326: =T326/D326 -> 12352.941 | Q326: 0 | T326: 2100000 | U326: =O326/T326 -> 1.0176152
A327: =VLOOKUP(B327,Grupos!$A$2:$B$619,2,FALSE) -> VARILLAS | B327: VCU-E 120X1800 | C327: VARILLA ENCHAQUETADA 1/2 X 180 | D327: 12 | E327: 10379 | F327: 160.54 | G327: =E327+F327 -> 10539.54 | H327: =E327*D327 -> 124548 | I327: =F327*D327 -> 1926.48 | J327: =G327*D327 -> 126474.48 | M327: 862.1527 | N327: =G327+L327+M327 -> 11401.693 | O327: =N327*D327 -> 136820.31 | P327: =T327/D327 -> 13500 | Q327: 0 | T327: 162000 | U327: =O327/T327 -> 0.84456983
A328: TOTAL VARILLAS | D328: =SUM(D317:D327) -> 1491 | H328: =SUM(H317:H327) -> 1.48704e+08 | I328: =SUM(I317:I327) -> 89597.22 | J328: =SUM(J317:J327) -> 1.4879359e+08 | O328: =SUM(O317:O327) -> 1.4927476e+08 | T328: =SUM(T317:T327) -> 1.6797107e+08 | U328: =O328/T328 -> 0.88869329 | V328: =T328/T329 -> 0.044474886
A329: TOTAL | D329: =SUM(D328,D316,D264) -> 1874533.7 | H329: =SUM(H328,H316,H264) -> 1.6223968e+09 | I329: =SUM(I328,I316,I264) -> 1.0430036e+08 | J329: =SUM(J328,J316,J264) -> 1.7266972e+09 | O329: =SUM(O328,O316,O264) -> 2.5455234e+09 | T329: =SUM(T328,T316,T264) -> 3.7767621e+09 | U329: =O329/T329 -> 0.67399622
A330: DESCUENTOS | O330: -22412766 | T330: -58895398
A331: TOTAL SIN DESCUENTOS | D331: =D329+D330 -> 1874533.7 | H331: =H329+H330 -> 1.6223968e+09 | I331: =I329+I330 -> 1.0430036e+08 | J331: =J329+J330 -> 1.7266972e+09 | O331: =O329+O330 -> 2.5231106e+09 | T331: =T329+T330 -> 3.7178667e+09 | U331: =O331/T331 -> 0.67864472
H333: COSTO MATERIA PRIMA | K333: =H329 -> 1.6223968e+09 | L333: =K333/$T$329 -> 0.42957347
H334: MANO DE OBRA DIRECTA E INDIRECTA | K334: 664427639 | L334: =K334/$T$329 -> 0.1759252 | M334: =K334/I329-1 -> 5.3703295

Sheet Feb
A2: DETALLE DE VENTAS 2026
E3: COSTO SIT UNITARIO | H3: COSTO SIT CANTIDAD
A4: GRUPO | B4: REF. | C4: DESCRIPCION | D4: CANT | E4: CUMAT | F4: CUMO | G4: CUNago | H4: CTMAT | I4: CTMO | J4: CTSIT | K4: %PART | L4: CIFU | M4: MOU | N4: CTU | O4: CT | P4: PUV | Q4: PRECIOTOT | R4: %CTO | S4: %Part. | T4: MO Nago | U4: Dif | W4: MP Nago | X4: Dif
A5: =VLOOKUP(B5,Grupos!$A$2:$B$619,2,FALSE) -> ACCESORIOS | B5: 997 | C5: MAYOR VALOR COBRADO | D5: -2 | E5: 0 | F5: 0 | G5: =E5+F5 -> 0 | H5: =E5*D5 -> 0 | I5: =F5*D5 -> 0 | J5: =G5*D5 -> 0 | K5: =J5/$J$308 -> 0 | L5: =$K$383*K5/D5 -> 0 | M5: =F5*$M$382 -> 0 | N5: =G5+L5+M5 -> 0 | O5: =N5*D5 -> 0 | P5: =Q5/D5 -> 737800 | Q5: =-1404327-71273 -> -1475600 | R5: =O5/Q5 -> 0 | T5: =IFERROR(VLOOKUP(B5,[1]Todos!$A$2:$C$3021,3,FALSE),0) -> 0 | U5: =T5-F5 -> 0 | W5: =IFERROR(VLOOKUP(B5,[1]Todos!$A$2:$B$3021,2,FALSE),0) -> 0 | X5: =W5-E5 -> 0
A6: =VLOOKUP(B6,Grupos!$A$2:$B$619,2,FALSE) -> ACCESORIOS | B6: BN-08 | C6: BANDEJA PARA INTERIOR *I-8P* | D6: 1 | E6: 1216.9 | F6: 73.14 | G6: =E6+F6 -> 1290.04 | H6: =E6*D6 -> 1216.9 | I6: =F6*D6 -> 73.14 | J6: =G6*D6 -> 1290.04 | K6: =J6/$J$308 -> 7.6982246e-07 | L6: =$K$383*K6/D6 -> 321.15813 | M6: =F6*$M$382 -> 430.37216 | N6: =G6+L6+M6 -> 2041.5703 | O6: =N6*D6 -> 2041.5703 | P6: =Q6/D6 -> 6762 | Q6: 6762 | R6: =O6/Q6 -> 0.30191811 | T6: =IFERROR(VLOOKUP(B6,[1]Todos!$A$2:$C$3021,3,FALSE),0) -> 0 | U6: =T6-F6 -> -73.14 | W6: =IFERROR(VLOOKUP(B6,[1]Todos!$A$2:$B$3021,2,FALSE),0) -> 0 | X6: =W6-E6 -> -1216.9
A7: =VLOOKUP(B7,Grupos!$A$2:$B$619,2,FALSE) -> ACCESORIOS | B7: BN-18 | C7: BANDEJA PARA INTERIOR *I-18P,I-218,I-318 | D7: 1 | E7: 2120.5 | F7: 123.35 | G7: =E7+F7 -> 2243.85 | H7: =E7*D7 -> 2120.5 | I7: =F7*D7 -> 123.35 | J7: =G7*D7 -> 2243.85 | K7: =J7/$J$308 -> 1.339002e-06 | L7: =$K$383*K7/D7 -> 558.61111 | M7: =F7*$M$382 -> 725.81906 | N7: =G7+L7+M7 -> 3528.2802 | O7: =N7*D7 -> 3528.2802 | P7: =Q7/D7 -> 11970 | Q7: 11970 | R7: =O7/Q7 -> 0.29476025 | T7: =IFERROR(VLOOKUP(B7,[1]Todos!$A$2:$C$3021,3,FALSE),0) -> 0 | U7: =T7-F7 -> -123.35 | W7: =IFERROR(VLOOKUP(B7,[1]Todos!$A$2:$B$3021,2,FALSE),0) -> 0 | X7: =W7-E7 -> -2120.5
A8: =VLOOKUP(B8,Grupos!$A$2:$B$619,2,FALSE) -> ACCESORIOS | B8: BN-24 | C8: BANDEJA PARA INTERIOR *I-224,I-324* | D8: 1 | E8: 2376.63 | F8: 87.07 | G8: =E8+F8 -> 2463.7 | H8: =E8*D8 -> 2376.63 | I8: =F8*D8 -> 87.07 | J8: =G8*D8 -> 2463.7 | K8: =J8/$J$308 -> 1.470196e-06 | L8: =$K$383*K8/D8 -> 613.34322 | M8: =F8*$M$382 -> 512.3394 | N8: =G8+L8+M8 -> 3589.3826 | O8: =N8*D8 -> 3589.3826 | P8: =Q8/D8 -> 26700 | Q8: 26700 | R8: =O8/Q8 -> 0.13443381 | T8: =IFERROR(VLOOKUP(B8,[1]Todos!$A$2:$C$3021,3,FALSE),0) -> 0 | U8: =T8-F8 -> -87.07 | W8: =IFERROR(VLOOKUP(B8,[1]Todos!$A$2:$B$3021,2,FALSE),0) -> 0 | X8: =W8-E8 -> -2376.63
A9: =VLOOKUP(B9,Grupos!$A$2:$B$619,2,FALSE) -> ACCESORIOS | B9: BN-36 | C9: BANDEJA PARA INTERIOR *I-236,I-336* | D9: 1 | E9: 3286.26 | F9: 157.35 | G9: =E9+F9 -> 3443.61 | H9: =E9*D9 -> 3286.26 | I9: =F9*D9 -> 157.35 | J9: =G9*D9 -> 3443.61 | K9: =J9/$J$308 -> 2.0549505e-06 | L9: =$K$383*K9/D9 -> 857.29384 | M9: =F9*$M$382 -> 925.88268 | N9: =G9+L9+M9 -> 5226.7865 | O9: =N9*D9 -> 5226.7865 | P9: =Q9/D9 -> 38587.5 | Q9: 38587.5 | R9: =O9/Q9 -> 0.13545284 | T9: =IFERROR(VLOOKUP(B9,[1]Todos!$A$2:$C$3021,3,FALSE),0) -> 0 | U9: =T9-F9 -> -157.35 | W9: =IFERROR(VLOOKUP(B9,[1]Todos!$A$2:$B$3021,2,FALSE),0) -> 0 | X9: =W9-E9 -> -3286.26
A10: =VLOOKUP(B10,Grupos!$A$2:$B$619,2,FALSE) -> ACCESORIOS | B10: BNTOTA | C10: BANDEJA PARA TOTALIZADOR | D10: 1 | E10: 2141.58 | F10: 66.96 | G10: =E10+F10 -> 2208.54 | H10: =E10*D10 -> 2141.58 | I10: =F10*D10 -> 66.96 | J10: =G10*D10 -> 2208.54 | K10: =J10/$J$308 -> 1.317931e-06 | L10: =$K$383*K10/D10 -> 549.82061 | M10: =F10*$M$382 -> 394.00766 | N10: =G10+L10+M10 -> 3152.3683 | O10: =N10*D10 -> 3152.3683 | P10: =Q10/D10 -> 33112.5 | Q10: 33112.5 | R10: =O10/Q10 -> 0.09520176 | T10: =IFERROR(VLOOKUP(B10,[1]Todos!$A$2:$C$3021,3,FALSE),0) -> 67 | U10: =T10-F10 -> 0.04 | W10: =IFERROR(VLOOKUP(B10,[1]Todos!$A$2:$B$3021,2,FALSE),0) -> 1927.16 | X10: =W10-E10 -> -214.42
A11: =VLOOKUP(B11,Grupos!$A$2:$B$619,2,FALSE) -> ACCESORIOS | B11: CHAPA-1 | C11: CHAPA GAVETA (TRPs) | D11: 20 | E11: 3200 | F11: 0 | G11: =E11+F11 -> 3200 | H11: =E11*D11 -> 64000 | I11: =F11*D11 -> 0 | J11: =G11*D11 -> 64000 | K11: =J11/$J$308 -> 3.8191558e-05 | L11: =$K$383*K11/D11 -> 796.64663 | M11: =F11*$M$382 -> 0 | N11: =G11+L11+M11 -> 3996.6466 | O11: =N11*D11 -> 79932.933 | P11: =Q11/D11 -> 7217.55 | Q11: 144351 | R11: =O11/Q11 -> 0.55374007 | T11: =IFERROR(VLOOKUP(B11,[1]Todos!$A$2:$C$3021,3,FALSE),0) -> 0 | U11: =T11-F11 -> 0 | W11: =IFERROR(VLOOKUP(B11,[1]Todos!$A$2:$B$3021,2,FALSE),0) -> 3200 | X11: =W11-E11 -> 0
A12: =VLOOKUP(B12,Grupos!$A$2:$B$619,2,FALSE) -> ACCESORIOS | B12: CIERRE | C12: CIERRE DE TRINQUETE | D12: 20 | E12: 68.22 | F12: 12.44 | G12: =E12+F12 -> 80.66 | H12: =E12*D12 -> 1364.4 | I12: =F12*D12 -> 248.8 | J12: =G12*D12 -> 1613.2 | K12: =J12/$J$308 -> 9.6266596e-07 | L12: =$K$383*K12/D12 -> 20.080474 | M12: =F12*$M$382 -> 73.19975 | N12: =G12+L12+M12 -> 173.94022 | O12: =N12*D12 -> 3478.8045 | P12: =Q12/D12 -> 1540 | Q12: 30800 | R12: =O12/Q12 -> 0.1129482 | T12: =IFERROR(VLOOKUP(B12,[1]Todos!$A$2:$C$3021,3,FALSE),0) -> 12.51 | U12: =T12-F12 -> 0.07 | W12: =IFERROR(VLOOKUP(B12,[1]Todos!$A$2:$B$3021,2,FALSE),0) -> 68.15 | X12: =W12-E12 -> -0.07
A13: =VLOOKUP(B13,Grupos!$A$2:$B$619,2,FALSE) -> ACCESORIOS | B13: FLETES | C13: VALOR FLETES MERCANCIA | D13: 2 | E13: 0 | F13: 0 | G13: =E13+F13 -> 0 | H13: =E13*D13 -> 0 | I13: =F13*D13 -> 0 | J13: =G13*D13 -> 0 | K13: =J13/$J$308 -> 0 | L13: =$K$383*K13/D13 -> 0 | M13: =F13*$M$382 -> 0 | N13: =G13+L13+M13 -> 0 | O13: =N13*D13 -> 0 | P13: =Q13/D13 -> 351000 | Q13: 702000 | R13: =O13/Q13 -> 0 | T13: =IFERROR(VLOOKUP(B13,[1]Todos!$A$2:$C$3021,3,FALSE),0) -> 0 | U13: =T13-F13 -> 0 | W13: =IFERROR(VLOOKUP(B13,[1]Todos!$A$2:$B$3021,2,FALSE),0) -> 0 | X13: =W13-E13 -> 0
A14: =VLOOKUP(B14,Grupos!$A$2:$B$619,2,FALSE) -> ACCESORIOS | B14: GRAPAM12-D | C14: GRAPA METALICA 1/2" DOBLE | D14: 13800 | E14: 59.89 | F14: 35.07 | G14: =E14+F14 -> 94.96 | H14: =E14*D14 -> 826482 | I14: =F14*D14 -> 483966 | J14: =G14*D14 -> 1310448 | K14: =J14/$J$308 -> 0.00078200079 | L14: =$K$383*K14/D14 -> 23.640489 | M14: =F14*$M$382 -> 206.35974 | N14: =G14+L14+M14 -> 324.96023 | O14: =N14*D14 -> 4484451.2 | P14: =Q14/D14 -> 120.3913 | Q14: 1661399.9 | R14: =O14/Q14 -> 2.6992003 | T14: =IFERROR(VLOOKUP(B14,[1]Todos!$A$2:$C$3021,3,FALSE),0) -> 29.35 | U14: =T14-F14 -> -5.72 | W14: =IFERROR(VLOOKUP(B14,[1]Todos!$A$2:$B$3021,2,FALSE),0) -> 55.77 | X14: =W14-E14 -> -4.12
A15: =VLOOKUP(B15,Grupos!$A$2:$B$619,2,FALSE) -> ACCESORIOS | B15: GRAPAM12-S | C15: GRAPA METALICA 1/2" SENCILLA | D15: -2400 | E15: 43.39 | F15: 43.22 | G15: =E15+F15 -> 86.61 | H15: =E15*D15 -> -104136 | I15: =F15*D15 -> -103728 | J15: =G15*D15 -> -207864 | K15: =J15/$J$308 -> -0.00012404141 | L15: =$K$383*K15/D15 -> 21.561739 | M15: =F15*$M$382 -> 254.31617 | N15: =G15+L15+M15 -> 362.48791 | O15: =N15*D15 -> -869970.99 | P15: =Q15/D15 -> 102.50001 | Q15: -246000.02 | R15: =O15/Q15 -> 3.5364671 | T15: =IFERROR(VLOOKUP(B15,[1]Todos!$A$2:$C$3021,3,FALSE),0) -> 44.51 | U15: =T15-F15 -> 1.29 | W15: =IFERROR(VLOOKUP(B15,[1]Todos!$A$2:$B$3021,2,FALSE),0) -> 40.38 | X15: =W15-E15 -> -3.01
A16: =VLOOKUP(B16,Grupos!$A$2:$B$619,2,FALSE) -> ACCESORIOS | B16: NEUTRO12 | C16: NEUTRO DE 12 CIRCUITOS | D16: 28 | E16: 2166.94 | F16: 0 | G16: =E16+F16 -> 2166.94 | H16: =E16*D16 -> 60674.32 | I16: =F16*D16 -> 0 | J16: =G16*D16 -> 60674.32 | K16: =J16/$J$308 -> 3.6206981e-05 | L16: =$K$383*K16/D16 -> 539.4642 | M16: =F16*$M$382 -> 0 | N16: =G16+L16+M16 -> 2706.4042 | O16: =N16*D16 -> 75779.318 | P16: =Q16/D16 -> 12970.286 | Q16: 363168 | R16: =O16/Q16 -> 0.20866188 | T16: =IFERROR(VLOOKUP(B16,[1]Todos!$A$2:$C$3021,3,FALSE),0) -> 0 | U16: =T16-F16 -> 0 | W16: =IFERROR(VLOOKUP(B16,[1]Todos!$A$2:$B$3021,2,FALSE),0) -> 2166.94 | X16: =W16-E16 -> 0
A17: =VLOOKUP(B17,Grupos!$A$2:$B$619,2,FALSE) -> ACCESORIOS | B17: NEUTRO18 | C17: NEUTRO DE 18 CIRCUITOS | D17: 1 | E17: 3042.06 | F17: 0 | G17: =E17+F17 -> 3042.06 | H17: =E17*D17 -> 3042.06 | I17: =F17*D17 -> 0 | J17: =G17*D17 -> 3042.06 | K17: =J17/$J$308 -> 1.8153283e-06 | L17: =$K$383*K17/D17 -> 757.32714 | M17: =F17*$M$382 -> 0 | N17: =G17+L17+M17 -> 3799.3871 | O17: =N17*D17 -> 3799.3871 | P17: =Q17/D17 -> 32812.5 | Q17: 32812.5 | R17: =O17/Q17 -> 0.11579085 | T17: =IFERROR(VLOOKUP(B17,[1]Todos!$A$2:$C$3021,3,FALSE),0) -> 0 | U17: =T17-F17 -> 0 | W17: =IFERROR(VLOOKUP(B17,[1]Todos!$A$2:$B$3021,2,FALSE),0) -> 3042.06 | X17: =W17-E17 -> 0
... A42: =VLOOKUP(B42,Grupos!$A$2:$B$619,2,FALSE) -> ACCESORIOS | B42: TIERRA8 | C42: TIERRA DE 8 CIRCUITOS | D42: 136 | E42: 1666.74 | F42: 0 | G42: =E42+F42 -> 1666.74 | H42: =E42*D42 -> 226676.64 | I42: =F42*D42 -> 0 | J42: =G42*D42 -> 226676.64 | K42: =J42/$J$308 -> 0.00013526772 | L42: =$K$383*K42/D42 -> 414.93838 | M42: =F42*$M$382 -> 0 | N42: =G42+L42+M42 -> 2081.6784 | O42: =N42*D42 -> 283108.26 | P42: =Q42/D42 -> 9227.0591 | Q42: 1254880 | R42: =O42/Q42 -> 0.22560583 | T42: =IFERROR(VLOOKUP(B42,[1]Todos!$A$2:$C$3021,3,FALSE),0) -> 0 | U42: =T42-F42 -> 0 | W42: =IFERROR(VLOOKUP(B42,[1]Todos!$A$2:$B$3021,2,FALSE),0) -> 1666.74 | X42: =W42-E42 -> 0
A43: Total ACCESORIOS | D43: =SUBTOTAL(9,D5:D42) -> 13349 | H43: =SUBTOTAL(9,H5:H42) -> 2145861.2 | I43: =SUBTOTAL(9,I5:I42) -> 418308.47 | J43: =SUBTOTAL(9,J5:J42) -> 2564169.7 | O43: =SUBTOTAL(9,O5:O42) -> 5663945.8 | Q43: =SUBTOTAL(9,Q5:Q42) -> 8687211.6 | R43: =O43/Q43 -> 0.65198663 | S43: =Q43/$Q$308 -> 0.0020062368 | T43: =IFERROR(VLOOKUP(B43,[1]Todos!$A$2:$C$3021,3,FALSE),0) -> 0 | U43: =T43-F43 -> 0 | W43: =IFERROR(VLOOKUP(B43,[1]Todos!$A$2:$B$3021,2,FALSE),0) -> 0 | X43: =W43-E43 -> 0
A44: =VLOOKUP(B44,Grupos!$A$2:$B$619,2,FALSE) -> ADAPTADORES | B44: ACAMPANA12 | C44: ADAPTADOR CAMPANA 1/2" | D44: 12794 | E44: 15.04 | F44: 4.89 | G44: =E44+F44 -> 19.93 | H44: =E44*D44 -> 192421.76 | I44: =F44*D44 -> 62562.66 | J44: =G44*D44 -> 254984.42 | K44: =J44/$J$308 -> 0.00015216019 | L44: =$K$383*K44/D44 -> 4.9616148 | M44: =F44*$M$382 -> 28.773857 | N44: =G44+L44+M44 -> 53.665471 | O44: =N44*D44 -> 686596.04 | P44: =Q44/D44 -> 87.187358 | Q44: 1115475.1 | R44: =O44/Q44 -> 0.61551895 | T44: =IFERROR(VLOOKUP(B44,[1]Todos!$A$2:$C$3021,3,FALSE),0) -> 4.85 | U44: =T44-F44 -> -0.04 | W44: =IFERROR(VLOOKUP(B44,[1]Todos!$A$2:$B$3021,2,FALSE),0) -> 15.04 | X44: =W44-E44 -> 0
A45: =VLOOKUP(B45,Grupos!$A$2:$B$619,2,FALSE) -> ADAPTADORES | B45: ACAMPANA34 | C45: ADAPTADOR CAMPANA 3/4" | D45: 3000 | E45: 20.18 | F45: 5.27 | G45: =E45+F45 -> 25.45 | H45: =E45*D45 -> 60540 | I45: =F45*D45 -> 15810 | J45: =G45*D45 -> 76350 | K45: =J45/$J$308 -> 4.5561335e-05 | L45: =$K$383*K45/D45 -> 6.3358302 | M45: =F45*$M$382 -> 31.009862 | N45: =G45+L45+M45 -> 62.795692 | O45: =N45*D45 -> 188387.08 | P45: =Q45/D45 -> 104 | Q45: 312000.01 | R45: =O45/Q45 -> 0.60380471 | T45: =IFERROR(VLOOKUP(B45,[1]Todos!$A$2:$C$3021,3,FALSE),0) -> 4.9 | U45: =T45-F45 -> -0.37 | W45: =IFERROR(VLOOKUP(B45,[1]Todos!$A$2:$B$3021,2,FALSE),0) -> 20.18 | X45: =W45-E45 -> 0
A46: =VLOOKUP(B46,Grupos!$A$2:$B$619,2,FALSE) -> ADAPTADORES | B46: ADAPTER12 | C46: ADAPTADOR TERMINAL 1/2" | D46: 648000 | E46: 26.11 | F46: 10.98 | G46: =E46+F46 -> 37.09 | H46: =E46*D46 -> 16919280 | I46: =F46*D46 -> 7115040 | J46: =G46*D46 -> 24034320 | K46: =J46/$J$308 -> 0.014342314 | L46: =$K$383*K46/D46 -> 9.2336323 | M46: =F46*$M$382 -> 64.608782 | N46: =G46+L46+M46 -> 110.93241 | O46: =N46*D46 -> 71884205 | P46: =Q46/D46 -> 107.1 | Q46: 69400803 | R46: =O46/Q46 -> 1.0357835 | T46: =IFERROR(VLOOKUP(B46,[1]Todos!$A$2:$C$3021,3,FALSE),0) -> 10.32 | U46: =T46-F46 -> -0.66 | W46: =IFERROR(VLOOKUP(B46,[1]Todos!$A$2:$B$3021,2,FALSE),0) -> 26.12 | X46: =W46-E46 -> 0.01
A47: =VLOOKUP(B47,Grupos!$A$2:$B$619,2,FALSE) -> ADAPTADORES | B47: ADAPTER12-AI | C47: ADAPTADOR TERMINAL 1/2" ALTO IMPACTO | D47: 19200 | E47: 55.65 | F47: 10.16 | G47: =E47+F47 -> 65.81 | H47: =E47*D47 -> 1068480 | I47: =F47*D47 -> 195072 | J47: =G47*D47 -> 1263552 | K47: =J47/$J$308 -> 0.00075401593 | L47: =$K$383*K47/D47 -> 16.383536 | M47: =F47*$M$382 -> 59.783718 | N47: =G47+L47+M47 -> 141.97725 | O47: =N47*D47 -> 2725963.3 | P47: =Q47/D47 -> 175.3125 | Q47: 3365999.9 | R47: =O47/Q47 -> 0.80985245 | T47: =IFERROR(VLOOKUP(B47,[1]Todos!$A$2:$C$3021,3,FALSE),0) -> 10.6 | U47: =T47-F47 -> 0.44 | W47: =IFERROR(VLOOKUP(B47,[1]Todos!$A$2:$B$3021,2,FALSE),0) -> 55.65 | X47: =W47-E47 -> 0
A48: =VLOOKUP(B48,Grupos!$A$2:$B$619,2,FALSE) -> ADAPTADORES | B48: ADAPTER12-PP-SE | C48: ADAPTADOR TERMINAL 1/2" EN POLIPROPILENO SIN ENSAMBLE | D48: 400500 | E48: 27.67 | F48: 6.42 | G48: =E48+F48 -> 34.09 | H48: =E48*D48 -> 11081835 | I48: =F48*D48 -> 2571210 | J48: =G48*D48 -> 13653045 | K48: =J48/$J$308 -> 0.0081473603 | L48: =$K$383*K48/D48 -> 8.4867761 | M48: =F48*$M$382 -> 37.77672 | N48: =G48+L48+M48 -> 80.353496 | O48: =N48*D48 -> 32181575 | P48: =Q48/D48 -> 105.45843 | Q48: 42236101 | R48: =O48/Q48 -> 0.76194473 | T48: =IFERROR(VLOOKUP(B48,[1]Todos!$A$2:$C$3021,3,FALSE),0) -> 5.37 | U48: =T48-F48 -> -1.05 | W48: =IFERROR(VLOOKUP(B48,[1]Todos!$A$2:$B$3021,2,FALSE),0) -> 27.67 | X48: =W48-E48 -> 0
A49: =VLOOKUP(B49,Grupos!$A$2:$B$619,2,FALSE) -> ADAPTADORES | B49: ADAPTER34 | C49: ADAPTADOR TERMINAL 3/4" | D49: 290400 | E49: 40.16 | F49: 11.35 | G49: =E49+F49 -> 51.51 | H49: =E49*D49 -> 11662464 | I49: =F49*D49 -> 3296040 | J49: =G49*D49 -> 14958504 | K49: =J49/$J$308 -> 0.0089263839 | L49: =$K$383*K49/D49 -> 12.823521 | M49: =F49*$M$382 -> 66.785945 | N49: =G49+L49+M49 -> 131.11947 | O49: =N49*D49 -> 38077093 | P49: =Q49/D49 -> 143.33885 | Q49: 41625601 | R49: =O49/Q49 -> 0.91475179 | T49: =IFERROR(VLOOKUP(B49,[1]Todos!$A$2:$C$3021,3,FALSE),0) -> 11.11 | U49: =T49-F49 -> -0.24 | W49: =IFERROR(VLOOKUP(B49,[1]Todos!$A$2:$B$3021,2,FALSE),0) -> 41.81 | X49: =W49-E49 -> 1.65
A50: Total ADAPTADORES | D50: =SUBTOTAL(9,D44:D49) -> 1373894 | H50: =SUBTOTAL(9,H44:H49) -> 40985021 | I50: =SUBTOTAL(9,I44:I49) -> 13255735 | J50: =SUBTOTAL(9,J44:J49) -> 54240755 | O50: =SUBTOTAL(9,O44:O49) -> 1.4574382e+08 | Q50: =SUBTOTAL(9,Q44:Q49) -> 1.5805598e+08 | R50: =O50/Q50 -> 0.92210253 | S50: =Q50/$Q$308 -> 0.036501669 | T50: =IFERROR(VLOOKUP(B50,[1]Todos!$A$2:$C$3021,3,FALSE),0) -> 0 | U50: =T50-F50 -> 0 | W50: =IFERROR(VLOOKUP(B50,[1]Todos!$A$2:$B$3021,2,FALSE),0) -> 0 | X50: =W50-E50 -> 0
A51: =VLOOKUP(B51,Grupos!$A$2:$B$619,2,FALSE) -> CAJAS ARRANCADORAS | B51: CA-30 | C51: CAJA ARRANCADOR Y CONTROL INDUSTRIAL 30X20X16 | D51: 141 | E51: 30398.83 | F51: 4472.47 | G51: =E51+F51 -> 34871.3 | H51: =E51*D51 -> 4286235 | I51: =F51*D51 -> 630618.27 | J51: =G51*D51 -> 4916853.3 | K51: =J51/$J$308 -> 0.0029340982 | L51: =$K$383*K51/D51 -> 8681.2824 | M51: =F51*$M$382 -> 26317.016 | N51: =G51+L51+M51 -> 69869.599 | O51: =N51*D51 -> 9851613.4 | P51: =Q51/D51 -> 107461.54 | Q51: 15152077 | R51: =O51/Q51 -> 0.65018236 | T51: =IFERROR(VLOOKUP(B51,[1]Todos!$A$2:$C$3021,3,FALSE),0) -> 4472.47 | U51: =T51-F51 -> 0 | W51: =IFERROR(VLOOKUP(B51,[1]Todos!$A$2:$B$3021,2,FALSE),0) -> 30398.83 | X51: =W51-E51 -> 0
A52: =VLOOKUP(B52,Grupos!$A$2:$B$619,2,FALSE) -> CAJAS ARRANCADORAS | B52: CA-40 | C52: CAJA ARRANCADOR Y CONTROL INDUSTRIAL 40X30X20 | D52: 121 | E52: 40781.56 | F52: 5353.18 | G52: =E52+F52 -> 46134.74 | H52: =E52*D52 -> 4934568.8 | I52: =F52*D52 -> 647734.78 | J52: =G52*D52 -> 5582303.5 | K52: =J52/$J$308 -> 0.0033312011 | L52: =$K$383*K52/D52 -> 11485.339 | M52: =F52*$M$382 -> 31499.312 | N52: =G52+L52+M52 -> 89119.391 | O52: =N52*D52 -> 10783446 | P52: =Q52/D52 -> 150275.77 | Q52: 18183368 | R52: =O52/Q52 -> 0.593039 | T52: =IFERROR(VLOOKUP(B52,[1]Todos!$A$2:$C$3021,3,FALSE),0) -> 5353.18 | U52: =T52-F52 -> 0 | W52: =IFERROR(VLOOKUP(B52,[1]Todos!$A$2:$B$3021,2,FALSE),0) -> 40781.56 | X52: =W52-E52 -> 0
A53: =VLOOKUP(B53,Grupos!$A$2:$B$619,2,FALSE) -> CAJAS ARRANCADORAS | B53: CA-60 | C53: CAJA ARRANCADOR Y CONTROL INDUSTRIAL 60X40X25 | D53: 48 | E53: 62538.51 | F53: 5265.73 | G53: =E53+F53 -> 67804.24 | H53: =E53*D53 -> 3001848.5 | I53: =F53*D53 -> 252755.04 | J53: =G53*D53 -> 3254603.5 | K53: =J53/$J$308 -> 0.0019421622 | L53: =$K$383*K53/D53 -> 16880.006 | M53: =F53*$M$382 -> 30984.736 | N53: =G53+L53+M53 -> 115668.98 | O53: =N53*D53 -> 5552111.1 | P53: =Q53/D53 -> 247574.08 | Q53: 11883556 | R53: =O53/Q53 -> 0.46720957 | T53: =IFERROR(VLOOKUP(B53,[1]Todos!$A$2:$C$3021,3,FALSE),0) -> 5265.73 | U53: =T53-F53 -> 0 | W53: =IFERROR(VLOOKUP(B53,[1]Todos!$A$2:$B$3021,2,FALSE),0) -> 62538.51 | X53: =W53-E53 -> 0
A54: =VLOOKUP(B54,Grupos!$A$2:$B$619,2,FALSE) -> CAJAS ARRANCADORAS | B54: CA-70 | C54: CAJA ARRANCADOR Y CONTROL INDUSTRIAL 70X50X25 | D54: 20 | E54: 78390.9 | F54: 7236.18 | G54: =E54+F54 -> 85627.08 | H54: =E54*D54 -> 1567818 | I54: =F54*D54 -> 144723.6 | J54: =G54*D54 -> 1712541.6 | K54: =J54/$J$308 -> 0.0010219474 | L54: =$K$383*K54/D54 -> 21317.039 | M54: =F54*$M$382 -> 42579.306 | N54: =G54+L54+M54 -> 149523.42 | O54: =N54*D54 -> 2990468.5 | P54: =Q54/D54 -> 302535.4 | Q54: 6050708 | R54: =O54/Q54 -> 0.49423447 | T54: =IFERROR(VLOOKUP(B54,[1]Todos!$A$2:$C$3021,3,FALSE),0) -> 7236.18 | U54: =T54-F54 -> 0 | W54: =IFERROR(VLOOKUP(B54,[1]Todos!$A$2:$B$3021,2,FALSE),0) -> 78390.9 | X54: =W54-E54 -> 0
A55: =VLOOKUP(B55,Grupos!$A$2:$B$619,2,FALSE) -> CAJAS ARRANCADORAS | B55: CA-80 | C55: CAJA ARRANCADOR Y CONTROL INDUSTRIAL 80X50X25 | D55: 6 | E55: 84343.91 | F55: 8005.49 | G55: =E55+F55 -> 92349.4 | H55: =E55*D55 -> 506063.46 | I55: =F55*D55 -> 48032.94 | J55: =G55*D55 -> 554096.4 | K55: =J55/$J$308 -> 0.0003306532 | L55: =$K$383*K55/D55 -> 22990.574 | M55: =F55*$M$382 -> 47106.098 | N55: =G55+L55+M55 -> 162446.07 | O55: =N55*D55 -> 974676.44 | P55: =Q55/D55 -> 322410.99 | Q55: 1934466 | R55: =O55/Q55 -> 0.50384781 | T55: =IFERROR(VLOOKUP(B55,[1]Todos!$A$2:$C$3021,3,FALSE),0) -> 8005.49 | U55: =T55-F55 -> 0 | W55: =IFERROR(VLOOKUP(B55,[1]Todos!$A$2:$B$3021,2,FALSE),0) -> 84343.91 | X55: =W55-E55 -> 0
A56: =VLOOKUP(B56,Grupos!$A$2:$B$619,2,FALSE) -> CAJAS ARRANCADORAS | B56: CA-90 | C56: CAJA ARRANCADOR Y CONTROL INDUSTRIAL 90X50X25 | D56: 2 | E56: 94916.92 | F56: 5465.68 | G56: =E56+F56 -> 100382.6 | H56: =E56*D56 -> 189833.84 | I56: =F56*D56 -> 10931.36 | J56: =G56*D56 -> 200765.2 | K56: =J56/$J$308 -> 0.00011980525 | L56: =$K$383*K56/D56 -> 24990.456 | M56: =F56*$M$382 -> 32161.287 | N56: =G56+L56+M56 -> 157534.34 | O56: =N56*D56 -> 315068.69 | P56: =Q56/D56 -> 320142.51 | Q56: 640285.01 | R56: =O56/Q56 -> 0.49207569 | T56: =IFERROR(VLOOKUP(B56,[1]Todos!$A$2:$C$3021,3,FALSE),0) -> 5465.68 | U56: =T56-F56 -> 0 | W56: =IFERROR(VLOOKUP(B56,[1]Todos!$A$2:$B$3021,2,FALSE),0) -> 94916.92 | X56: =W56-E56 -> 0
A57: Total CAJAS ARRANCADORAS | D57: =SUBTOTAL(9,D51:D56) -> 338 | H57: =SUBTOTAL(9,H51:H56) -> 14486368 | I57: =SUBTOTAL(9,I51:I56) -> 1734796 | J57: =SUBTOTAL(9,J51:J56) -> 16221164 | O57: =SUBTOTAL(9,O51:O56) -> 30467384 | Q57: =SUBTOTAL(9,Q51:Q56) -> 53844460 | R57: =O57/Q57 -> 0.56584065 | S57: =Q57/$Q$308 -> 0.012434915 | T57: =IFERROR(VLOOKUP(B57,[1]Todos!$A$2:$C$3021,3,FALSE),0) -> 0 | U57: =T57-F57 -> 0 | W57: =IFERROR(VLOOKUP(B57,[1]Todos!$A$2:$B$3021,2,FALSE),0) -> 0 | X57: =W57-E57 -> 0
A58: =VLOOKUP(B58,Grupos!$A$2:$B$619,2,FALSE) -> CAJAS EMPALME | B58: CE13-13-8B | C58: CAJA DE EMPALME 13X13X8 BLANCA | D58: 360 | E58: 2813.7 | F58: 426.22 | G58: =E58+F58 -> 3239.92 | H58: =E58*D58 -> 1012932 | I58: =F58*D58 -> 153439.2 | J58: =G58*D58 -> 1166371.2 | K58: =J58/$J$308 -> 0.00069602396 | L58: =$K$383*K58/D58 -> 806.5848 | M58: =F58*$M$382 -> 2507.9741 | N58: =G58+L58+M58 -> 6554.4789 | O58: =N58*D58 -> 2359612.4 | P58: =Q58/D58 -> 11357.55 | Q58: 4088717.9 | R58: =O58/Q58 -> 0.57710324 | T58: =IFERROR(VLOOKUP(B58,[1]Todos!$A$2:$C$3021,3,FALSE),0) -> 426.22 | U58: =T58-F58 -> 0 | W58: =IFERROR(VLOOKUP(B58,[1]Todos!$A$2:$B$3021,2,FALSE),0) -> 2813.7 | X58: =W58-E58 -> 0
A59: =VLOOKUP(B59,Grupos!$A$2:$B$619,2,FALSE) -> CAJAS EMPALME | B59: CE15-15-10B | C59: CAJA DE EMPALME 15X15X10 BLANCA | D59: 1707 | E59: 3808.35 | F59: 680.53 | G59: =E59+F59 -> 4488.88 | H59: =E59*D59 -> 6500853.5 | I59: =F59*D59 -> 1161664.7 | J59: =G59*D59 -> 7662518.2 | K59: =J59/$J$308 -> 0.0045725548 | L59: =$K$383*K59/D59 -> 1117.516 | M59: =F59*$M$382 -> 4004.3911 | N59: =G59+L59+M59 -> 9610.7871 | O59: =N59*D59 -> 16405614 | P59: =Q59/D59 -> 12991.444 | Q59: 22176396 | R59: =O59/Q59 -> 0.73977818 | T59: =IFERROR(VLOOKUP(B59,[1]Todos!$A$2:$C$3021,3,FALSE),0) -> 680.53 | U59: =T59-F59 -> 0 | W59: =IFERROR(VLOOKUP(B59,[1]Todos!$A$2:$B$3021,2,FALSE),0) -> 3808.35 | X59: =W59-E59 -> 0
A60: =VLOOKUP(B60,Grupos!$A$2:$B$619,2,FALSE) -> CAJAS EMPALME | B60: CE20-15-10B | C60: CAJA DE EMPALME 20X15X10 BLANCA | D60: 220 | E60: 4623.52 | F60: 408.44 | G60: =E60+F60 -> 5031.96 | H60: =E60*D60 -> 1017174.4 | I60: =F60*D60 -> 89856.8 | J60: =G60*D60 -> 1107031.2 | K60: =J60/$J$308 -> 0.00066061322 | L60: =$K$383*K60/D60 -> 1252.7169 | M60: =F60*$M$382 -> 2403.3525 | N60: =G60+L60+M60 -> 8688.0294 | O60: =N60*D60 -> 1911366.5 | P60: =Q60/D60 -> 16041.15 | Q60: 3529053 | R60: =O60/Q60 -> 0.54160889 | T60: =IFERROR(VLOOKUP(B60,[1]Todos!$A$2:$C$3021,3,FALSE),0) -> 408.44 | U60: =T60-F60 -> 0 | W60: =IFERROR(VLOOKUP(B60,[1]Todos!$A$2:$B$3021,2,FALSE),0) -> 4623.52 | X60: =W60-E60 -> 0
A61: =VLOOKUP(B61,Grupos!$A$2:$B$619,2,FALSE) -> CAJAS EMPALME | B61: CE20-20-10B | C61: CAJA DE EMPALME 20X20X10 BLANCA | D61: 2576 | E61: 5549.93 | F61: 701.09 | G61: =E61+F61 -> 6251.02 | H61: =E61*D61 -> 14296620 | I61: =F61*D61 -> 1806007.8 | J61: =G61*D61 -> 16102628 | K61: =J61/$J$308 -> 0.0096091317 | L61: =$K$383*K61/D61 -> 1556.2044 | M61: =F61*$M$382 -> 4125.3708 | N61: =G61+L61+M61 -> 11932.595 | O61: =N61*D61 -> 30738365 | P61: =Q61/D61 -> 18127.31 | Q61: 46695951 | R61: =O61/Q61 -> 0.65826618 | T61: =IFERROR(VLOOKUP(B61,[1]Todos!$A$2:$C$3021,3,FALSE),0) -> 701.09 | U61: =T61-F61 -> 0 | W61: =IFERROR(VLOOKUP(B61,[1]Todos!$A$2:$B$3021,2,FALSE),0) -> 5549.93 | X61: =W61-E61 -> 0
A62: =VLOOKUP(B62,Grupos!$A$2:$B$619,2,FALSE) -> CAJAS EMPALME | B62: CE20-20-15B | C62: CAJA DE EMPALME 20X20X15 BLANCA | D62: 1376 | E62: 6787.81 | F62: 539.74 | G62: =E62+F62 -> 7327.55 | H62: =E62*D62 -> 9340026.6 | I62: =F62*D62 -> 742682.24 | J62: =G62*D62 -> 10082709 | K62: =J62/$J$308 -> 0.0060167868 | L62: =$K$383*K62/D62 -> 1824.2088 | M62: =F62*$M$382 -> 3175.9512 | N62: =G62+L62+M62 -> 12327.71 | O62: =N62*D62 -> 16962929 | P62: =Q62/D62 -> 22835.901 | Q62: 31422199 | R62: =O62/Q62 -> 0.53983901 | T62: =IFERROR(VLOOKUP(B62,[1]Todos!$A$2:$C$3021,3,FALSE),0) -> 539.74 | U62: =T62-F62 -> 0 | W62: =IFERROR(VLOOKUP(B62,[1]Todos!$A$2:$B$3021,2,FALSE),0) -> 6787.81 | X62: =W62-E62 -> 0
A63: =VLOOKUP(B63,Grupos!$A$2:$B$619,2,FALSE) -> CAJAS EMPALME | B63: CE25-20-10B | C63: CAJA DE EMPALME 25X20X10 BLANCA | D63: 216 | E63: 6420.01 | F63: 404.9 | G63: =E63+F63 -> 6824.91 | H63: =E63*D63 -> 1386722.2 | I63: =F63*D63 -> 87458.4 | J63: =G63*D63 -> 1474180.6 | K63: =J63/$J$308 -> 0.00087970707 | L63: =$K$383*K63/D63 -> 1699.0755 | M63: =F63*$M$382 -> 2382.5224 | N63: =G63+L63+M63 -> 10906.508 | O63: =N63*D63 -> 2355805.7 | P63: =Q63/D63 -> 23023.084 | Q63: 4972986.1 | R63: =O63/Q63 -> 0.47372055 | T63: =IFERROR(VLOOKUP(B63,[1]Todos!$A$2:$C$3021,3,FALSE),0) -> 404.9 | U63: =T63-F63 -> 0 | W63: =IFERROR(VLOOKUP(B63,[1]Todos!$A$2:$B$3021,2,FALSE),0) -> 6420.01 | X63: =W63-E63 -> 0
A64: =VLOOKUP(B64,Grupos!$A$2:$B$619,2,FALSE) -> CAJAS EMPALME | B64: CE25-25-10B | C64: CAJA DE EMPALME 25X25X10 BLANCA | D64: 336 | E64: 7687.44 | F64: 497.98 | G64: =E64+F64 -> 8185.42 | H64: =E64*D64 -> 2582979.8 | I64: =F64*D64 -> 167321.28 | J64: =G64*D64 -> 2750301.1 | K64: =J64/$J$308 -> 0.0016412232 | L64: =$K$383*K64/D64 -> 2037.7773 | M64: =F64*$M$382 -> 2930.226 | N64: =G64+L64+M64 -> 13153.423 | O64: =N64*D64 -> 4419550.2 | P64: =Q64/D64 -> 27449.678 | Q64: 9223091.8 | R64: =O64/Q64 -> 0.47918315 | T64: =IFERROR(VLOOKUP(B64,[1]Todos!$A$2:$C$3021,3,FALSE),0) -> 497.98 | U64: =T64-F64 -> 0 | W64: =IFERROR(VLOOKUP(B64,[1]Todos!$A$2:$B$3021,2,FALSE),0) -> 7687.44 | X64: =W64-E64 -> 0
A65: =VLOOKUP(B65,Grupos!$A$2:$B$619,2,FALSE) -> CAJAS EMPALME | B65: CE25-25-15B | C65: CAJA DE EMPALME 25X25X15 BLANCA | D65: 312 | E65: 9070.97 | F65: 501.95 | G65: =E65+F65 -> 9572.92 | H65: =E65*D65 -> 2830142.6 | I65: =F65*D65 -> 156608.4 | J65: =G65*D65 -> 2986751 | K65: =J65/$J$308 -> 0.0017823231 | L65: =$K$383*K65/D65 -> 2383.1983 | M65: =F65*$M$382 -> 2953.5864 | N65: =G65+L65+M65 -> 14909.705 | O65: =N65*D65 -> 4651827.8 | P65: =Q65/D65 -> 30801.057 | Q65: 9609929.8 | R65: =O65/Q65 -> 0.4840647 | T65: =IFERROR(VLOOKUP(B65,[1]Todos!$A$2:$C$3021,3,FALSE),0) -> 501.95 | U65: =T65-F65 -> 0 | W65: =IFERROR(VLOOKUP(B65,[1]Todos!$A$2:$B$3021,2,FALSE),0) -> 9070.97 | X65: =W65-E65 -> 0
A66: =VLOOKUP(B66,Grupos!$A$2:$B$619,2,FALSE) -> CAJAS EMPALME | B66: CE30-30-10B | C66: CAJA DE EMPALME 30X30X10 BLANCA | D66: 992 | E66: 10016.3 | F66: 527.86 | G66: =E66+F66 -> 10544.16 | H66: =E66*D66 -> 9936169.6 | I66: =F66*D66 -> 523637.12 | J66: =G66*D66 -> 10459807 | K66: =J66/$J$308 -> 0.0062418174 | L66: =$K$383*K66/D66 -> 2624.9905 | M66: =F66*$M$382 -> 3106.0466 | N66: =G66+L66+M66 -> 16275.197 | O66: =N66*D66 -> 16144996 | P66: =Q66/D66 -> 33443.025 | Q66: 33175481 | R66: =O66/Q66 -> 0.48665445 | T66: =IFERROR(VLOOKUP(B66,[1]Todos!$A$2:$C$3021,3,FALSE),0) -> 527.86 | U66: =T66-F66 -> 0 | W66: =IFERROR(VLOOKUP(B66,[1]Todos!$A$2:$B$3021,2,FALSE),0) -> 10016.3 | X66: =W66-E66 -> 0
A67: =VLOOKUP(B67,Grupos!$A$2:$B$619,2,FALSE) -> CAJAS EMPALME | B67: CE30-30-15B | C67: CAJA DE EMPALME 30X30X15 BLANCA | D67: 1056 | E67: 11678.42 | F67: 664.85 | G67: =E67+F67 -> 12343.27 | H67: =E67*D67 -> 12332412 | I67: =F67*D67 -> 702081.6 | J67: =G67*D67 -> 13034493 | K67: =J67/$J$308 -> 0.0077782437 | L67: =$K$383*K67/D67 -> 3072.8826 | M67: =F67*$M$382 -> 3912.1265 | N67: =G67+L67+M67 -> 19328.279 | O67: =N67*D67 -> 20410663 | P67: =Q67/D67 -> 38817.513 | Q67: 40991294 | R67: =O67/Q67 -> 0.49792677 | T67: =IFERROR(VLOOKUP(B67,[1]Todos!$A$2:$C$3021,3,FALSE),0) -> 664.85 | U67: =T67-F67 -> 0 | W67: =IFERROR(VLOOKUP(B67,[1]Todos!$A$2:$B$3021,2,FALSE),0) -> 11678.42 | X67: =W67-E67 -> 0
A68: =VLOOKUP(B68,Grupos!$A$2:$B$619,2,FALSE) -> CAJAS EMPALME | B68: CE30-30-20B | C68: CAJA DE EMPALME 30X30X20 BLANCA | D68: 105 | E68: 14783.94 | F68: 656.71 | G68: =E68+F68 -> 15440.65 | H68: =E68*D68 -> 1552313.7 | I68: =F68*D68 -> 68954.55 | J68: =G68*D68 -> 1621268.3 | K68: =J68/$J$308 -> 0.00096748063 | L68: =$K$383*K68/D68 -> 3843.9818 | M68: =F68*$M$382 -> 3864.2289 | N68: =G68+L68+M68 -> 23148.861 | O68: =N68*D68 -> 2430630.4 | P68: =Q68/D68 -> 45714 | Q68: 4799970 | R68: =O68/Q68 -> 0.5063845 | T68: =IFERROR(VLOOKUP(B68,[1]Todos!$A$2:$C$3021,3,FALSE),0) -> 656.71 | U68: =T68-F68 -> 0 | W68: =IFERROR(VLOOKUP(B68,[1]Todos!$A$2:$B$3021,2,FALSE),0) -> 14783.94 | X68: =W68-E68 -> 0
A69: =VLOOKUP(B69,Grupos!$A$2:$B$619,2,FALSE) -> CAJAS EMPALME | B69: CE40-40-15B | C69: CAJA DE EMPALME 40X40X15 BLANCA | D69: 540 | E69: 18356.19 | F69: 904.07 | G69: =E69+F69 -> 19260.26 | H69: =E69*D69 -> 9912342.6 | I69: =F69*D69 -> 488197.8 | J69: =G69*D69 -> 10400540 | K69: =J69/$J$308 -> 0.0062064506 | L69: =$K$383*K69/D69 -> 4794.8816 | M69: =F69*$M$382 -> 5319.7506 | N69: =G69+L69+M69 -> 29374.892 | O69: =N69*D69 -> 15862442 | P69: =Q69/D69 -> 57736.833 | Q69: 31177890 | R69: =O69/Q69 -> 0.50877214 | T69: =IFERROR(VLOOKUP(B69,[1]Todos!$A$2:$C$3021,3,FALSE),0) -> 904.07 | U69: =T69-F69 -> 0 | W69: =IFERROR(VLOOKUP(B69,[1]Todos!$A$2:$B$3021,2,FALSE),0) -> 18356.19 | X69: =W69-E69 -> 0
... A76: =VLOOKUP(B76,Grupos!$A$2:$B$619,2,FALSE) -> CAJAS EMPALME | B76: CI-BU | C76: CAJA INDUSTRIAL BREAKER UNIVERSAL 100 AMP | D76: 799 | E76: 9097.36 | F76: 498.29 | G76: =E76+F76 -> 9595.65 | H76: =E76*D76 -> 7268790.6 | I76: =F76*D76 -> 398133.71 | J76: =G76*D76 -> 7666924.4 | K76: =J76/$J$308 -> 0.0045751841 | L76: =$K$383*K76/D76 -> 2388.8569 | M76: =F76*$M$382 -> 2932.0501 | N76: =G76+L76+M76 -> 14916.557 | O76: =N76*D76 -> 11918329 | P76: =Q76/D76 -> 38526.556 | Q76: 30782718 | R76: =O76/Q76 -> 0.38717598 | T76: =IFERROR(VLOOKUP(B76,[1]Todos!$A$2:$C$3021,3,FALSE),0) -> 498.29 | U76: =T76-F76 -> 0 | W76: =IFERROR(VLOOKUP(B76,[1]Todos!$A$2:$B$3021,2,FALSE),0) -> 8869.64 | X76: =W76-E76 -> -227.72
A77: Total CAJAS EMPALME | D77: =SUBTOTAL(9,D58:D76) -> 11564 | H77: =SUBTOTAL(9,H58:H76) -> 1.0111142e+08 | I77: =SUBTOTAL(9,I58:I76) -> 7250908.4 | J77: =SUBTOTAL(9,J58:J76) -> 1.0836233e+08 | O77: =SUBTOTAL(9,O58:O76) -> 1.7800533e+08 | Q77: =SUBTOTAL(9,Q58:Q76) -> 3.3649502e+08 | R77: =O77/Q77 -> 0.52899841 | S77: =Q77/$Q$308 -> 0.077710629 | T77: =IFERROR(VLOOKUP(B77,[1]Todos!$A$2:$C$3021,3,FALSE),0) -> 0 | U77: =T77-F77 -> 0 | W77: =IFERROR(VLOOKUP(B77,[1]Todos!$A$2:$B$3021,2,FALSE),0) -> 0 | X77: =W77-E77 -> 0
A78: =VLOOKUP(B78,Grupos!$A$2:$B$619,2,FALSE) -> CAJAS PLASTICAS CC | B78: CP2X4-CC | C78: CAJA PLASTICA 2X4 BLANCA | D78: 488160 | E78: 170.54 | F78: 7.88 | G78: =E78+F78 -> 178.42 | H78: =E78*D78 -> 83250806 | I78: =F78*D78 -> 3846700.8 | J78: =G78*D78 -> 87097507 | K78: =J78/$J$308 -> 0.051974836 | L78: =$K$383*K78/D78 -> 44.418029 | M78: =F78*$M$382 -> 46.367687 | N78: =G78+L78+M78 -> 269.20572 | O78: =N78*D78 -> 1.3141546e+08 | P78: =Q78/D78 -> 311.84957 | Q78: 1.5223249e+08 | R78: =O78/Q78 -> 0.86325505 | T78: =IFERROR(VLOOKUP(B78,[1]Todos!$A$2:$C$3021,3,FALSE),0) -> 7.55 | U78: =T78-F78 -> -0.33 | W78: =IFERROR(VLOOKUP(B78,[1]Todos!$A$2:$B$3021,2,FALSE),0) -> 162.25 | X78: =W78-E78 -> -8.29
A79: =VLOOKUP(B79,Grupos!$A$2:$B$619,2,FALSE) -> CAJAS PLASTICAS CC | B79: CP4X4-CC | C79: CAJA PLASTICA 4X4 BLANCA | D79: 386640 | E79: 265.37 | F79: 10.76 | G79: =E79+F79 -> 276.13 | H79: =E79*D79 -> 1.0260266e+08 | I79: =F79*D79 -> 4160246.4 | J79: =G79*D79 -> 1.067629e+08 | K79: =J79/$J$308 -> 0.063710025 | L79: =$K$383*K79/D79 -> 68.743136 | M79: =F79*$M$382 -> 63.314253 | N79: =G79+L79+M79 -> 408.18739 | O79: =N79*D79 -> 1.5782157e+08 | P79: =Q79/D79 -> 465.22453 | Q79: 1.7987441e+08 | R79: =O79/Q79 -> 0.87739869 | T79: =IFERROR(VLOOKUP(B79,[1]Todos!$A$2:$C$3021,3,FALSE),0) -> 10.32 | U79: =T79-F79 -> -0.44 | W79: =IFERROR(VLOOKUP(B79,[1]Todos!$A$2:$B$3021,2,FALSE),0) -> 252.52 | X79: =W79-E79 -> -12.85
A80: =VLOOKUP(B80,Grupos!$A$2:$B$619,2,FALSE) -> CAJAS PLASTICAS CC | B80: CPOCTOGONAL-CC | C80: CAJA PLASTICA OCTOGONAL BLANCA | D80: 180360 | E80: 214.83 | F80: 9.15 | G80: =E80+F80 -> 223.98 | H80: =E80*D80 -> 38746739 | I80: =F80*D80 -> 1650294 | J80: =G80*D80 -> 40397033 | K80: =J80/$J$308 -> 0.02410665 | L80: =$K$383*K80/D80 -> 55.760285 | M80: =F80*$M$382 -> 53.840652 | N80: =G80+L80+M80 -> 333.58094 | O80: =N80*D80 -> 60164658 | P80: =Q80/D80 -> 467.23504 | Q80: 84270512 | R80: =O80/Q80 -> 0.71394674 | T80: =IFERROR(VLOOKUP(B80,[1]Todos!$A$2:$C$3021,3,FALSE),0) -> 8.87 | U80: =T80-F80 -> -0.28 | W80: =IFERROR(VLOOKUP(B80,[1]Todos!$A$2:$B$3021,2,FALSE),0) -> 204.73 | X80: =W80-E80 -> -10.1
A81: Total CAJAS PLASTICAS CC | D81: =SUBTOTAL(9,D78:D80) -> 1055160 | H81: =SUBTOTAL(9,H78:H80) -> 224600202 | I81: =SUBTOTAL(9,I78:I80) -> 9657241.2 | J81: =SUBTOTAL(9,J78:J80) -> 2.3425744e+08 | O81: =SUBTOTAL(9,O78:O80) -> 3.4940169e+08 | Q81: =SUBTOTAL(9,Q78:Q80) -> 4.1637741e+08 | R81: =O81/Q81 -> 0.83914661 | S81: =Q81/$Q$308 -> 0.09615878 | T81: =IFERROR(VLOOKUP(B81,[1]Todos!$A$2:$C$3021,3,FALSE),0) -> 0 | U81: =T81-F81 -> 0 | W81: =IFERROR(VLOOKUP(B81,[1]Todos!$A$2:$B$3021,2,FALSE),0) -> 0 | X81: =W81-E81 -> 0
A82: =VLOOKUP(B82,Grupos!$A$2:$B$619,2,FALSE) -> CAJAS PLASTICAS LH | B82: CP2X4-LH | C82: CAJA PLASTICA 2X4 LIBRE DE HALOGENOS | D82: 25920 | E82: 172.66 | F82: 8.04 | G82: =E82+F82 -> 180.7 | H82: =E82*D82 -> 4475347.2 | I82: =F82*D82 -> 208396.8 | J82: =G82*D82 -> 4683744 | K82: =J82/$J$308 -> 0.0027949919 | L82: =$K$383*K82/D82 -> 44.985639 | M82: =F82*$M$382 -> 47.309163 | N82: =G82+L82+M82 -> 272.9948 | O82: =N82*D82 -> 7076025.3 | P82: =Q82/D82 -> 337.98335 | Q82: 8760528.3 | R82: =O82/Q82 -> 0.80771673 | T82: =IFERROR(VLOOKUP(B82,[1]Todos!$A$2:$C$3021,3,FALSE),0) -> 7.47 | U82: =T82-F82 -> -0.57 | W82: =IFERROR(VLOOKUP(B82,[1]Todos!$A$2:$B$3021,2,FALSE),0) -> 192.91 | X82: =W82-E82 -> 20.25
A83: =VLOOKUP(B83,Grupos!$A$2:$B$619,2,FALSE) -> CAJAS PLASTICAS LH | B83: CP4X4-LH | C83: CAJA PLASTICA 4X4 LIBRE DE HALOGENOS | D83: 51570 | E83: 265.54 | F83: 11.36 | G83: =E83+F83 -> 276.9 | H83: =E83*D83 -> 13693898 | I83: =F83*D83 -> 585835.2 | J83: =G83*D83 -> 14279733 | K83: =J83/$J$308 -> 0.008521332 | L83: =$K$383*K83/D83 -> 68.934829 | M83: =F83*$M$382 -> 66.844787 | N83: =G83+L83+M83 -> 412.67962 | O83: =N83*D83 -> 21281888 | P83: =Q83/D83 -> 490.71207 | Q83: 25306021 | R83: =O83/Q83 -> 0.84098119 | T83: =IFERROR(VLOOKUP(B83,[1]Todos!$A$2:$C$3021,3,FALSE),0) -> 10.69 | U83: =T83-F83 -> -0.67 | W83: =IFERROR(VLOOKUP(B83,[1]Todos!$A$2:$B$3021,2,FALSE),0) -> 296.54 | X83: =W83-E83 -> 31
A84: =VLOOKUP(B84,Grupos!$A$2:$B$619,2,FALSE) -> CAJAS PLASTICAS LH | B84: CPOCT-LH | C84: CAJA PLASTICA OCTOGONAL LIBRE DE HALOGENOS | D84: 33210 | E84: 224.71 | F84: 8.37 | G84: =E84+F84 -> 233.08 | H84: =E84*D84 -> 7462619.1 | I84: =F84*D84 -> 277967.7 | J84: =G84*D84 -> 7740586.8 | K84: =J84/$J$308 -> 0.0046191417 | L84: =$K$383*K84/D84 -> 58.025749 | M84: =F84*$M$382 -> 49.250957 | N84: =G84+L84+M84 -> 340.35671 | O84: =N84*D84 -> 11303246 | P84: =Q84/D84 -> 487.49594 | Q84: 16189740 | R84: =O84/Q84 -> 0.69817342 | T84: =IFERROR(VLOOKUP(B84,[1]Todos!$A$2:$C$3021,3,FALSE),0) -> 8.28 | U84: =T84-F84 -> -0.09 | W84: =IFERROR(VLOOKUP(B84,[1]Todos!$A$2:$B$3021,2,FALSE),0) -> 250.34 | X84: =W84-E84 -> 25.63
A85: Total CAJAS PLASTICAS LH | D85: =SUBTOTAL(9,D82:D84) -> 110700 | H85: =SUBTOTAL(9,H82:H84) -> 25631864 | I85: =SUBTOTAL(9,I82:I84) -> 1072199.7 | J85: =SUBTOTAL(9,J82:J84) -> 26704064 | O85: =SUBTOTAL(9,O82:O84) -> 39661159 | Q85: =SUBTOTAL(9,Q82:Q84) -> 50256290 | R85: =O85/Q85 -> 0.78917802 | S85: =Q85/$Q$308 -> 0.011606258 | T85: =IFERROR(VLOOKUP(B85,[1]Todos!$A$2:$C$3021,3,FALSE),0) -> 0 | U85: =T85-F85 -> 0 | W85: =IFERROR(VLOOKUP(B85,[1]Todos!$A$2:$B$3021,2,FALSE),0) -> 0 | X85: =W85-E85 -> 0
A86: =VLOOKUP(B86,Grupos!$A$2:$B$619,2,FALSE) -> CAJAS TELEFONICAS | B86: CT15-15-10 | C86: CAJA TELEFONICA 15X15X10 | D86: 120 | E86: 4707.25 | F86: 472.02 | G86: =E86+F86 -> 5179.27 | H86: =E86*D86 -> 564870 | I86: =F86*D86 -> 56642.4 | J86: =G86*D86 -> 621512.4 | K86: =J86/$J$308 -> 0.00037088323 | L86: =$K$383*K86/D86 -> 1289.39 | M86: =F86*$M$382 -> 2777.4715 | N86: =G86+L86+M86 -> 9246.1315 | O86: =N86*D86 -> 1109535.8 | P86: =Q86/D86 -> 28600.126 | Q86: 3432015.1 | R86: =O86/Q86 -> 0.32328989 | T86: =IFERROR(VLOOKUP(B86,[1]Todos!$A$2:$C$3021,3,FALSE),0) -> 472.02 | U86: =T86-F86 -> 0 | W86: =IFERROR(VLOOKUP(B86,[1]Todos!$A$2:$B$3021,2,FALSE),0) -> 4707.25 | X86: =W86-E86 -> 0
A87: =VLOOKUP(B87,Grupos!$A$2:$B$619,2,FALSE) -> CAJAS TELEFONICAS | B87: CT20-20-10 | C87: CAJA TELEFONICA 20X20X10 | D87: 598 | E87: 5915.72 | F87: 572.53 | G87: =E87+F87 -> 6488.25 | H87: =E87*D87 -> 3537600.6 | I87: =F87*D87 -> 342372.94 | J87: =G87*D87 -> 3879973.5 | K87: =J87/$J$308 -> 0.0023153474 | L87: =$K$383*K87/D87 -> 1615.2633 | M87: =F87*$M$382 -> 3368.8949 | N87: =G87+L87+M87 -> 11472.408 | O87: =N87*D87 -> 6860500.1 | P87: =Q87/D87 -> 33254.905 | Q87: 19886433 | R87: =O87/Q87 -> 0.34498395 | T87: =IFERROR(VLOOKUP(B87,[1]Todos!$A$2:$C$3021,3,FALSE),0) -> 572.53 | U87: =T87-F87 -> 0 | W87: =IFERROR(VLOOKUP(B87,[1]Todos!$A$2:$B$3021,2,FALSE),0) -> 5915.72 | X87: =W87-E87 -> 0
A88: =VLOOKUP(B88,Grupos!$A$2:$B$619,2,FALSE) -> CAJAS TELEFONICAS | B88: CT30-30-10 | C88: CAJA TELEFONICA 30X30X10 | D88: 310 | E88: 11364.94 | F88: 524.96 | G88: =E88+F88 -> 11889.9 | H88: =E88*D88 -> 3523131.4 | I88: =F88*D88 -> 162737.6 | J88: =G88*D88 -> 3685869 | K88: =J88/$J$308 -> 0.0021995169 | L88: =$K$383*K88/D88 -> 2960.0152 | M88: =F88*$M$382 -> 3088.9824 | N88: =G88+L88+M88 -> 17938.898 | O88: =N88*D88 -> 5561058.3 | P88: =Q88/D88 -> 42227.741 | Q88: 13090600 | R88: =O88/Q88 -> 0.4248131 | T88: =IFERROR(VLOOKUP(B88,[1]Todos!$A$2:$C$3021,3,FALSE),0) -> 524.96 | U88: =T88-F88 -> 0 | W88: =IFERROR(VLOOKUP(B88,[1]Todos!$A$2:$B$3021,2,FALSE),0) -> 11364.94 | X88: =W88-E88 -> 0
A89: =VLOOKUP(B89,Grupos!$A$2:$B$619,2,FALSE) -> CAJAS TELEFONICAS | B89: CT30-30-15 | C89: CAJA TELEFONICA 30X30X15 | D89: 54 | E89: 13220.83 | F89: 484.41 | G89: =E89+F89 -> 13705.24 | H89: =E89*D89 -> 713924.82 | I89: =F89*D89 -> 26158.14 | J89: =G89*D89 -> 740082.96 | K89: =J89/$J$308 -> 0.00044163939 | L89: =$K$383*K89/D89 -> 3411.9479 | M89: =F89*$M$382 -> 2850.3771 | N89: =G89+L89+M89 -> 19967.565 | O89: =N89*D89 -> 1078248.5 | P89: =Q89/D89 -> 50331.11 | Q89: 2717879.9 | R89: =O89/Q89 -> 0.39672412 | T89: =IFERROR(VLOOKUP(B89,[1]Todos!$A$2:$C$3021,3,FALSE),0) -> 484.41 | U89: =T89-F89 -> 0 | W89: =IFERROR(VLOOKUP(B89,[1]Todos!$A$2:$B$3021,2,FALSE),0) -> 13220.83 | X89: =W89-E89 -> 0
A90: =VLOOKUP(B90,Grupos!$A$2:$B$619,2,FALSE) -> CAJAS TELEFONICAS | B90: CT40-40-15 | C90: CAJA TELEFONICA 40X40X15 | D90: 65 | E90: 20766.8 | F90: 519.24 | G90: =E90+F90 -> 21286.04 | H90: =E90*D90 -> 1349842 | I90: =F90*D90 -> 33750.6 | J90: =G90*D90 -> 1383592.6 | K90: =J90/$J$308 -> 0.00082564933 | L90: =$K$383*K90/D90 -> 5299.2038 | M90: =F90*$M$382 -> 3055.3246 | N90: =G90+L90+M90 -> 29640.568 | O90: =N90*D90 -> 1926636.9 | P90: =Q90/D90 -> 71307.154 | Q90: 4634965 | R90: =O90/Q90 -> 0.41567454 | T90: =IFERROR(VLOOKUP(B90,[1]Todos!$A$2:$C$3021,3,FALSE),0) -> 519.24 | U90: =T90-F90 -> 0 | W90: =IFERROR(VLOOKUP(B90,[1]Todos!$A$2:$B$3021,2,FALSE),0) -> 20766.8 | X90: =W90-E90 -> 0
A91: =VLOOKUP(B91,Grupos!$A$2:$B$619,2,FALSE) -> CAJAS TELEFONICAS | B91: CT40-40-20 | C91: CAJA TELEFONICA 40X40X20 | D91: 16 | E91: 22935.13 | F91: 503.76 | G91: =E91+F91 -> 23438.89 | H91: =E91*D91 -> 366962.08 | I91: =F91*D91 -> 8060.16 | J91: =G91*D91 -> 375022.24 | K91: =J91/$J$308 -> 0.00022379193 | L91: =$K$383*K91/D91 -> 5835.1602 | M91: =F91*$M$382 -> 2964.2368 | N91: =G91+L91+M91 -> 32238.287 | O91: =N91*D91 -> 515812.59 | P91: =Q91/D91 -> 85833.129 | Q91: 1373330.1 | R91: =O91/Q91 -> 0.37559259 | T91: =IFERROR(VLOOKUP(B91,[1]Todos!$A$2:$C$3021,3,FALSE),0) -> 503.76 | U91: =T91-F91 -> 0 | W91: =IFERROR(VLOOKUP(B91,[1]Todos!$A$2:$B$3021,2,FALSE),0) -> 22935.13 | X91: =W91-E91 -> 0
A92: =VLOOKUP(B92,Grupos!$A$2:$B$619,2,FALSE) -> CAJAS TELEFONICAS | B92: CT40-60-15 | C92: CAJA TELEFONICA 40X60X15 | D92: 18 | E92: 27365.37 | F92: 1111.33 | G92: =E92+F92 -> 28476.7 | H92: =E92*D92 -> 492576.66 | I92: =F92*D92 -> 20003.94 | J92: =G92*D92 -> 512580.6 | K92: =J92/$J$308 -> 0.00030587893 | L92: =$K$383*K92/D92 -> 7089.3335 | M92: =F92*$M$382 -> 6539.3149 | N92: =G92+L92+M92 -> 42105.348 | O92: =N92*D92 -> 757896.27 | P92: =Q92/D92 -> 114660 | Q92: 2063880 | R92: =O92/Q92 -> 0.36721916 | T92: =IFERROR(VLOOKUP(B92,[1]Todos!$A$2:$C$3021,3,FALSE),0) -> 1111.33 | U92: =T92-F92 -> 0 | W92: =IFERROR(VLOOKUP(B92,[1]Todos!$A$2:$B$3021,2,FALSE),0) -> 27365.37 | X92: =W92-E92 -> 0
A93: =VLOOKUP(B93,Grupos!$A$2:$B$619,2,FALSE) -> CAJAS TELEFONICAS | B93: CT60-80-15 | C93: CAJA TELEFONICA 60X80X15 | D93: 25 | E93: 50373.89 | F93: 1363.87 | G93: =E93+F93 -> 51737.76 | H93: =E93*D93 -> 1259347.2 | I93: =F93*D93 -> 34096.75 | J93: =G93*D93 -> 1293444 | K93: =J93/$J$308 -> 0.00077185377 | L93: =$K$383*K93/D93 -> 12880.223 | M93: =F93*$M$382 -> 8025.3169 | N93: =G93+L93+M93 -> 72643.299 | O93: =N93*D93 -> 1816082.5 | P93: =Q93/D93 -> 168809.26 | Q93: 4220231.4 | R93: =O93/Q93 -> 0.4303277 | T93: =IFERROR(VLOOKUP(B93,[1]Todos!$A$2:$C$3021,3,FALSE),0) -> 1363.87 | U93: =T93-F93 -> 0 | W93: =IFERROR(VLOOKUP(B93,[1]Todos!$A$2:$B$3021,2,FALSE),0) -> 50373.89 | X93: =W93-E93 -> 0
A94: Total CAJAS TELEFONICAS | D94: =SUBTOTAL(9,D86:D93) -> 1206 | H94: =SUBTOTAL(9,H86:H93) -> 11808255 | I94: =SUBTOTAL(9,I86:I93) -> 683822.53 | J94: =SUBTOTAL(9,J86:J93) -> 12492077 | O94: =SUBTOTAL(9,O86:O93) -> 19625771 | Q94: =SUBTOTAL(9,Q86:Q93) -> 51419334 | R94: =O94/Q94 -> 0.38168077 | S94: =Q94/$Q$308 -> 0.011874853 | T94: =IFERROR(VLOOKUP(B94,[1]Todos!$A$2:$C$3021,3,FALSE),0) -> 0 | U94: =T94-F94 -> 0 | W94: =IFERROR(VLOOKUP(B94,[1]Todos!$A$2:$B$3021,2,FALSE),0) -> 0 | X94: =W94-E94 -> 0
A95: =VLOOKUP(B95,Grupos!$A$2:$B$619,2,FALSE) -> CE 125 | B95: CE125LE | C95: CAJA 12X12X5 TAPA LEVITON GRIS | D95: 3240 | E95: 1987.78 | F95: 304.75 | G95: =E95+F95 -> 2292.53 | H95: =E95*D95 -> 6440407.2 | I95: =F95*D95 -> 987390 | J95: =G95*D95 -> 7427797.2 | K95: =J95/$J$308 -> 0.0044324867 | L95: =$K$383*K95/D95 -> 570.73009 | M95: =F95*$M$382 -> 1793.2173 | N95: =G95+L95+M95 -> 4656.4774 | O95: =N95*D95 -> 15086987 | P95: =Q95/D95 -> 4939.5556 | Q95: 16004160 | R95: =O95/Q95 -> 0.94269157 | T95: =IFERROR(VLOOKUP(B95,[1]Todos!$A$2:$C$3021,3,FALSE),0) -> 304.75 | U95: =T95-F95 -> 0 | W95: =IFERROR(VLOOKUP(B95,[1]Todos!$A$2:$B$3021,2,FALSE),0) -> 1987.78 | X95: =W95-E95 -> 0
A96: =VLOOKUP(B96,Grupos!$A$2:$B$619,2,FALSE) -> CE 125 | B96: CE125LEB | C96: CAJA 12X12X5 TAPA LEVITON BLANCA | D96: 480 | E96: 1946.49 | F96: 334.79 | G96: =E96+F96 -> 2281.28 | H96: =E96*D96 -> 934315.2 | I96: =F96*D96 -> 160699.2 | J96: =G96*D96 -> 1095014.4 | K96: =J96/$J$308 -> 0.00065344228 | L96: =$K$383*K96/D96 -> 567.92938 | M96: =F96*$M$382 -> 1969.9794 | N96: =G96+L96+M96 -> 4819.1888 | O96: =N96*D96 -> 2313210.6 | P96: =Q96/D96 -> 5178.5 | Q96: 2485680 | R96: =O96/Q96 -> 0.93061481 | T96: =IFERROR(VLOOKUP(B96,[1]Todos!$A$2:$C$3021,3,FALSE),0) -> 334.79 | U96: =T96-F96 -> 0 | W96: =IFERROR(VLOOKUP(B96,[1]Todos!$A$2:$B$3021,2,FALSE),0) -> 1946.49 | X96: =W96-E96 -> 0
A97: =VLOOKUP(B97,Grupos!$A$2:$B$619,2,FALSE) -> CE 125 | B97: CE125LED | C97: CAJA 12X12X5 TAPA LEVITON DOBLE GRIS | D97: 1080 | E97: 1861.23 | F97: 369.61 | G97: =E97+F97 -> 2230.84 | H97: =E97*D97 -> 2010128.4 | I97: =F97*D97 -> 399178.8 | J97: =G97*D97 -> 2409307.2 | K97: =J97/$J$308 -> 0.0014377374 | L97: =$K$383*K97/D97 -> 555.37224 | M97: =F97*$M$382 -> 2174.8681 | N97: =G97+L97+M97 -> 4961.0804 | O97: =N97*D97 -> 5357966.8 | P97: =Q97/D97 -> 5004.7778 | Q97: 5405160 | R97: =O97/Q97 -> 0.99126886 | T97: =IFERROR(VLOOKUP(B97,[1]Todos!$A$2:$C$3021,3,FALSE),0) -> 369.61 | U97: =T97-F97 -> 0 | W97: =IFERROR(VLOOKUP(B97,[1]Todos!$A$2:$B$3021,2,FALSE),0) -> 1861.23 | X97: =W97-E97 -> 0
A98: =VLOOKUP(B98,Grupos!$A$2:$B$619,2,FALSE) -> CE 125 | B98: CE125LEDB | C98: CAJA 12X12X5 TAPA LEVITON DOBLE BLANCA | D98: 240 | E98: 1829.98 | F98: 430.92 | G98: =E98+F98 -> 2260.9 | H98: =E98*D98 -> 439195.2 | I98: =F98*D98 -> 103420.8 | J98: =G98*D98 -> 542616 | K98: =J98/$J$308 -> 0.00032380235 | L98: =$K$383*K98/D98 -> 562.85574 | M98: =F98*$M$382 -> 2535.6299 | N98: =G98+L98+M98 -> 5359.3856 | O98: =N98*D98 -> 1286252.6 | P98: =Q98/D98 -> 5582 | Q98: 1339680 | R98: =O98/Q98 -> 0.96011925 | T98: =IFERROR(VLOOKUP(B98,[1]Todos!$A$2:$C$3021,3,FALSE),0) -> 430.92 | U98: =T98-F98 -> 0 | W98: =IFERROR(VLOOKUP(B98,[1]Todos!$A$2:$B$3021,2,FALSE),0) -> 1829.98 | X98: =W98-E98 -> 0
A99: =VLOOKUP(B99,Grupos!$A$2:$B$619,2,FALSE) -> CE 125 | B99: CE125LI | C99: CAJA 12X12X5 TAPA LISA GRIS | D99: 11640 | E99: 1987.78 | F99: 324.11 | G99: =E99+F99 -> 2311.89 | H99: =E99*D99 -> 23137759 | I99: =F99*D99 -> 3772640.4 | J99: =G99*D99 -> 26910400 | K99: =J99/$J$308 -> 0.016058595 | L99: =$K$383*K99/D99 -> 575.54981 | M99: =F99*$M$382 -> 1907.1359 | N99: =G99+L99+M99 -> 4794.5757 | O99: =N99*D99 -> 55808861 | P99: =Q99/D99 -> 4973.433 | Q99: 57890760 | R99: =O99/Q99 -> 0.96403747 | T99: =IFERROR(VLOOKUP(B99,[1]Todos!$A$2:$C$3021,3,FALSE),0) -> 324.11 | U99: =T99-F99 -> 0 | W99: =IFERROR(VLOOKUP(B99,[1]Todos!$A$2:$B$3021,2,FALSE),0) -> 1987.78 | X99: =W99-E99 -> 0
A100: =VLOOKUP(B100,Grupos!$A$2:$B$619,2,FALSE) -> CE 125 | B100: CE125LIB | C100: CAJA 12X12X5 TAPA LISA BLANCA | D100: 3300 | E100: 1946.49 | F100: 311.53 | G100: =E100+F100 -> 2258.02 | H100: =E100*D100 -> 6423417 | I100: =F100*D100 -> 1028049 | J100: =G100*D100 -> 7451466 | K100: =J100/$J$308 -> 0.0044466109 | L100: =$K$383*K100/D100 -> 562.13876 | M100: =F100*$M$382 -> 1833.1124 | N100: =G100+L100+M100 -> 4653.2711 | O100: =N100*D100 -> 15355795 | P100: =Q100/D100 -> 5082.9455 | Q100: 16773720 | R100: =O100/Q100 -> 0.91546745 | T100: =IFERROR(VLOOKUP(B100,[1]Todos!$A$2:$C$3021,3,FALSE),0) -> 311.53 | U100: =T100-F100 -> 0 | W100: =IFERROR(VLOOKUP(B100,[1]Todos!$A$2:$B$3021,2,FALSE),0) -> 1946.49 | X100: =W100-E100 -> 0
A101: =VLOOKUP(B101,Grupos!$A$2:$B$619,2,FALSE) -> CE 125 | B101: CE125LX | C101: CAJA 12X12X5 TAPA DATOS GRIS | D101: 4560 | E101: 1984.17 | F101: 359.89 | G101: =E101+F101 -> 2344.06 | H101: =E101*D101 -> 9047815.2 | I101: =F101*D101 -> 1641098.4 | J101: =G101*D101 -> 10688914 | K101: =J101/$J$308 -> 0.0063785354 | L101: =$K$383*K101/D101 -> 583.55859 | M101: =F101*$M$382 -> 2117.6735 | N101: =G101+L101+M101 -> 5045.2921 | O101: =N101*D101 -> 23006532 | P101: =Q101/D101 -> 4897.4737 | Q101: 22332480 | R101: =O101/Q101 -> 1.0301826 | T101: =IFERROR(VLOOKUP(B101,[1]Todos!$A$2:$C$3021,3,FALSE),0) -> 359.89 | U101: =T101-F101 -> 0 | W101: =IFERROR(VLOOKUP(B101,[1]Todos!$A$2:$B$3021,2,FALSE),0) -> 1984.17 | X101: =W101-E101 -> 0
A102: =VLOOKUP(B102,Grupos!$A$2:$B$619,2,FALSE) -> CE 125 | B102: CE125LXB | C102: CAJA 12X12X5 TAPA DATOS BLANCA | D102: 120 | E102: 1946.49 | F102: 366.71 | G102: =E102+F102 -> 2313.2 | H102: =E102*D102 -> 233578.8 | I102: =F102*D102 -> 44005.2 | J102: =G102*D102 -> 277584 | K102: =J102/$J$308 -> 0.00016564633 | L102: =$K$383*K102/D102 -> 575.87593 | M102: =F102*$M$382 -> 2157.8039 | N102: =G102+L102+M102 -> 5046.8798 | O102: =N102*D102 -> 605625.58 | P102: =Q102/D102 -> 4800 | Q102: 576000 | R102: =O102/Q102 -> 1.0514333 | T102: =IFERROR(VLOOKUP(B102,[1]Todos!$A$2:$C$3021,3,FALSE),0) -> 366.71 | U102: =T102-F102 -> 0 | W102: =IFERROR(VLOOKUP(B102,[1]Todos!$A$2:$B$3021,2,FALSE),0) -> 1946.49 | X102: =W102-E102 -> 0
A103: Total CE 125 | D103: =SUBTOTAL(9,D95:D102) -> 24660 | H103: =SUBTOTAL(9,H95:H102) -> 48666616 | I103: =SUBTOTAL(9,I95:I102) -> 8136481.8 | J103: =SUBTOTAL(9,J95:J102) -> 56803098 | O103: =SUBTOTAL(9,O95:O102) -> 1.1882123e+08 | Q103: =SUBTOTAL(9,Q95:Q102) -> 1.2280764e+08 | R103: =O103/Q103 -> 0.9675394 | S103: =Q103/$Q$308 -> 0.028361368 | T103: =IFERROR(VLOOKUP(B103,[1]Todos!$A$2:$C$3021,3,FALSE),0) -> 0 | U103: =T103-F103 -> 0 | W103: =IFERROR(VLOOKUP(B103,[1]Todos!$A$2:$B$3021,2,FALSE),0) -> 0 | X103: =W103-E103 -> 0
A104: =VLOOKUP(B104,Grupos!$A$2:$B$619,2,FALSE) -> EXCEDENTES INDUSTRIALES | B104: EXCARTON | C104: EXCEDENTES INDUSTRIALES DE CATON | D104: 315 | E104: 0 | F104: 0 | G104: =E104+F104 -> 0 | H104: =E104*D104 -> 0 | I104: =F104*D104 -> 0 | J104: =G104*D104 -> 0 | K104: =J104/$J$308 -> 0 | L104: =$K$383*K104/D104 -> 0 | M104: =F104*$M$382 -> 0 | N104: =G104+L104+M104 -> 0 | O104: =N104*D104 -> 0 | P104: =Q104/D104 -> 250 | Q104: 78750 | R104: =O104/Q104 -> 0 | T104: =IFERROR(VLOOKUP(B104,[1]Todos!$A$2:$C$3021,3,FALSE),0) -> 0 | U104: =T104-F104 -> 0 | W104: =IFERROR(VLOOKUP(B104,[1]Todos!$A$2:$B$3021,2,FALSE),0) -> 0 | X104: =W104-E104 -> 0
A105: =VLOOKUP(B105,Grupos!$A$2:$B$619,2,FALSE) -> EXCEDENTES INDUSTRIALES | B105: EXCERETALAL | C105: EXCEDENTES INDUSTRIALES - RETAL ALUMINIO | D105: 135.6 | E105: 0 | F105: 0 | G105: =E105+F105 -> 0 | H105: =E105*D105 -> 0 | I105: =F105*D105 -> 0 | J105: =G105*D105 -> 0 | K105: =J105/$J$308 -> 0 | L105: =$K$383*K105/D105 -> 0 | M105: =F105*$M$382 -> 0 | N105: =G105+L105+M105 -> 0 | O105: =N105*D105 -> 0 | P105: =Q105/D105 -> 6800 | Q105: 922080 | R105: =O105/Q105 -> 0 | T105: =IFERROR(VLOOKUP(B105,[1]Todos!$A$2:$C$3021,3,FALSE),0) -> 0 | U105: =T105-F105 -> 0 | W105: =IFERROR(VLOOKUP(B105,[1]Todos!$A$2:$B$3021,2,FALSE),0) -> 0 | X105: =W105-E105 -> 0
A106: =VLOOKUP(B106,Grupos!$A$2:$B$619,2,FALSE) -> EXCEDENTES INDUSTRIALES | B106: EXCERETALCU | C106: EXCEDENTES INDUSTRIALES - RETAL COBRE | D106: 326.7 | E106: 0 | F106: 0 | G106: =E106+F106 -> 0 | H106: =E106*D106 -> 0 | I106: =F106*D106 -> 0 | J106: =G106*D106 -> 0 | K106: =J106/$J$308 -> 0 | L106: =$K$383*K106/D106 -> 0 | M106: =F106*$M$382 -> 0 | N106: =G106+L106+M106 -> 0 | O106: =N106*D106 -> 0 | P106: =Q106/D106 -> 38200 | Q106: 12479940 | R106: =O106/Q106 -> 0 | T106: =IFERROR(VLOOKUP(B106,[1]Todos!$A$2:$C$3021,3,FALSE),0) -> 0 | U106: =T106-F106 -> 0 | W106: =IFERROR(VLOOKUP(B106,[1]Todos!$A$2:$B$3021,2,FALSE),0) -> 0 | X106: =W106-E106 -> 0
A107: Total EXCEDENTES INDUSTRIALES | D107: =SUBTOTAL(9,D104:D106) -> 777.3 | H107: =SUBTOTAL(9,H104:H106) -> 0 | I107: =SUBTOTAL(9,I104:I106) -> 0 | J107: =SUBTOTAL(9,J104:J106) -> 0 | O107: =SUBTOTAL(9,O104:O106) -> 0 | Q107: =SUBTOTAL(9,Q104:Q106) -> 13480770 | R107: =O107/Q107 -> 0 | S107: =Q107/$Q$308 -> 0.0031132678 | T107: =IFERROR(VLOOKUP(B107,[1]Todos!$A$2:$C$3021,3,FALSE),0) -> 0 | U107: =T107-F107 -> 0 | W107: =IFERROR(VLOOKUP(B107,[1]Todos!$A$2:$B$3021,2,FALSE),0) -> 0 | X107: =W107-E107 -> 0
A108: =VLOOKUP(B108,Grupos!$A$2:$B$619,2,FALSE) -> INTERIORES | B108: I12P | C108: INTERIOR 12 CTOS 2F 125 AMP | D108: 11 | E108: 15396.14 | F108: 883.37 | G108: =E108+F108 -> 16279.51 | H108: =E108*D108 -> 169357.54 | I108: =F108*D108 -> 9717.07 | J108: =G108*D108 -> 179074.61 | K108: =J108/$J$308 -> 0.00010686154 | L108: =$K$383*K108/D108 -> 4052.8177 | M108: =F108*$M$382 -> 5197.9472 | N108: =G108+L108+M108 -> 25530.275 | O108: =N108*D108 -> 280833.02 | P108: =Q108/D108 -> 68860.36 | Q108: 757463.96 | R108: =O108/Q108 -> 0.3707543 | T108: =IFERROR(VLOOKUP(B108,[1]Todos!$A$2:$C$3021,3,FALSE),0) -> 848.26 | U108: =T108-F108 -> -35.11 | W108: =IFERROR(VLOOKUP(B108,[1]Todos!$A$2:$B$3021,2,FALSE),0) -> 15188.54 | X108: =W108-E108 -> -207.6
A109: =VLOOKUP(B109,Grupos!$A$2:$B$619,2,FALSE) -> INTERIORES | B109: I18P-BIMETALICO | C109: INTERIOR 18 CTOS 2 FASES TB18P BIMETALICO | D109: -7 | E109: 8581 | F109: 1041.09 | G109: =E109+F109 -> 9622.09 | H109: =E109*D109 -> -60067 | I109: =F109*D109 -> -7287.63 | J109: =G109*D109 -> -67354.63 | K109: =J109/$J$308 -> -4.019341e-05 | L109: =$K$383*K109/D109 -> 2395.4392 | M109: =F109*$M$382 -> 6126.007 | N109: =G109+L109+M109 -> 18143.536 | O109: =N109*D109 -> -127004.75 | P109: =Q109/D109 -> 89790.006 | Q109: -628530.04 | R109: =O109/Q109 -> 0.20206632 | T109: =IFERROR(VLOOKUP(B109,[1]Todos!$A$2:$C$3021,3,FALSE),0) -> 0 | U109: =T109-F109 -> -1041.09 | W109: =IFERROR(VLOOKUP(B109,[1]Todos!$A$2:$B$3021,2,FALSE),0) -> 0 | X109: =W109-E109 -> -8581
A110: =VLOOKUP(B110,Grupos!$A$2:$B$619,2,FALSE) -> INTERIORES | B110: I224 | C110: INTERIOR 24 CTOS 2F 225 AMP | D110: 1 | E110: 40418.06 | F110: 2027.61 | G110: =E110+F110 -> 42445.67 | H110: =E110*D110 -> 40418.06 | I110: =F110*D110 -> 2027.61 | J110: =G110*D110 -> 42445.67 | K110: =J110/$J$308 -> 2.532916e-05 | L110: =$K$383*K110/D110 -> 10566.937 | M110: =F110*$M$382 -> 11930.912 | N110: =G110+L110+M110 -> 64943.519 | O110: =N110*D110 -> 64943.519 | P110: =Q110/D110 -> 143963 | Q110: 143963 | R110: =O110/Q110 -> 0.45111257 | T110: =IFERROR(VLOOKUP(B110,[1]Todos!$A$2:$C$3021,3,FALSE),0) -> 2027.61 | U110: =T110-F110 -> 0 | W110: =IFERROR(VLOOKUP(B110,[1]Todos!$A$2:$B$3021,2,FALSE),0) -> 40097.47 | X110: =W110-E110 -> -320.59
A111: =VLOOKUP(B111,Grupos!$A$2:$B$619,2,FALSE) -> INTERIORES | B111: I230 | C111: INTERIOR 30 CTOS 2F 225 AMP | D111: 2 | E111: 50412.3 | F111: 1981.32 | G111: =E111+F111 -> 52393.62 | H111: =E111*D111 -> 100824.6 | I111: =F111*D111 -> 3962.64 | J111: =G111*D111 -> 104787.24 | K111: =J111/$J$308 -> 6.2531062e-05 | L111: =$K$383*K111/D111 -> 13043.5 | M111: =F111*$M$382 -> 11658.531 | N111: =G111+L111+M111 -> 77095.651 | O111: =N111*D111 -> 154191.3 | P111: =Q111/D111 -> 189599.99 | Q111: 379199.98 | R111: =O111/Q111 -> 0.40662266 | T111: =IFERROR(VLOOKUP(B111,[1]Todos!$A$2:$C$3021,3,FALSE),0) -> 1981.32 | U111: =T111-F111 -> 0 | W111: =IFERROR(VLOOKUP(B111,[1]Todos!$A$2:$B$3021,2,FALSE),0) -> 50029.84 | X111: =W111-E111 -> -382.46
A112: =VLOOKUP(B112,Grupos!$A$2:$B$619,2,FALSE) -> INTERIORES | B112: I236 | C112: INTERIOR 36 CTOS 2F 225 AMP | D112: 4 | E112: 59241.59 | F112: 2622.81 | G112: =E112+F112 -> 61864.4 | H112: =E112*D112 -> 236966.36 | I112: =F112*D112 -> 10491.24 | J112: =G112*D112 -> 247457.6 | K112: =J112/$J$308 -> 0.00014766861 | L112: =$K$383*K112/D112 -> 15401.271 | M112: =F112*$M$382 -> 15433.202 | N112: =G112+L112+M112 -> 92698.873 | O112: =N112*D112 -> 370795.49 | P112: =Q112/D112 -> 200602 | Q112: 802407.99 | R112: =O112/Q112 -> 0.46210344 | T112: =IFERROR(VLOOKUP(B112,[1]Todos!$A$2:$C$3021,3,FALSE),0) -> 2622.81 | U112: =T112-F112 -> 0 | W112: =IFERROR(VLOOKUP(B112,[1]Todos!$A$2:$B$3021,2,FALSE),0) -> 58797.23 | X112: =W112-E112 -> -444.36
A113: =VLOOKUP(B113,Grupos!$A$2:$B$619,2,FALSE) -> INTERIORES | B113: I312-125 | C113: INTERIOR 12 CTOS 3F 125 AMP | D113: 4 | E113: 20849.5 | F113: 1232.3 | G113: =E113+F113 -> 22081.8 | H113: =E113*D113 -> 83398 | I113: =F113*D113 -> 4929.2 | J113: =G113*D113 -> 88327.2 | K113: =J113/$J$308 -> 5.2708646e-05 | L113: =$K$383*K113/D113 -> 5497.3099 | M113: =F113*$M$382 -> 7251.1295 | N113: =G113+L113+M113 -> 34830.239 | O113: =N113*D113 -> 139320.96 | P113: =Q113/D113 -> 80926.003 | Q113: 323704.01 | R113: =O113/Q113 -> 0.43039614 | T113: =IFERROR(VLOOKUP(B113,[1]Todos!$A$2:$C$3021,3,FALSE),0) -> 1215.18 | U113: =T113-F113 -> -17.12 | W113: =IFERROR(VLOOKUP(B113,[1]Todos!$A$2:$B$3021,2,FALSE),0) -> 20688.9 | X113: =W113-E113 -> -160.6
A114: =VLOOKUP(B114,Grupos!$A$2:$B$619,2,FALSE) -> INTERIORES | B114: I318 | C114: INTERIOR 18 CTOS 3F 225 AMP | D114: 1 | E114: 38158.32 | F114: 1956.45 | G114: =E114+F114 -> 40114.77 | H114: =E114*D114 -> 38158.32 | I114: =F114*D114 -> 1956.45 | J114: =G114*D114 -> 40114.77 | K114: =J114/$J$308 -> 2.3938212e-05 | L114: =$K$383*K114/D114 -> 9986.6551 | M114: =F114*$M$382 -> 11512.191 | N114: =G114+L114+M114 -> 61613.616 | O114: =N114*D114 -> 61613.616 | P114: =Q114/D114 -> 119073 | Q114: 119073 | R114: =O114/Q114 -> 0.51744405 | T114: =IFERROR(VLOOKUP(B114,[1]Todos!$A$2:$C$3021,3,FALSE),0) -> 1956.45 | U114: =T114-F114 -> 0 | W114: =IFERROR(VLOOKUP(B114,[1]Todos!$A$2:$B$3021,2,FALSE),0) -> 37890.61 | X114: =W114-E114 -> -267.71
A115: =VLOOKUP(B115,Grupos!$A$2:$B$619,2,FALSE) -> INTERIORES | B115: I324 | C115: INTERIOR 24 CTOS 3F 225 AMP | D115: 3 | E115: 50110.49 | F115: 2292.84 | G115: =E115+F115 -> 52403.33 | H115: =E115*D115 -> 150331.47 | I115: =F115*D115 -> 6878.52 | J115: =G115*D115 -> 157209.99 | K115: =J115/$J$308 -> 9.3813976e-05 | L115: =$K$383*K115/D115 -> 13045.918 | M115: =F115*$M$382 -> 13491.585 | N115: =G115+L115+M115 -> 78940.832 | O115: =N115*D115 -> 236822.5 | P115: =Q115/D115 -> 143963 | Q115: 431889 | R115: =O115/Q115 -> 0.54834112 | T115: =IFERROR(VLOOKUP(B115,[1]Todos!$A$2:$C$3021,3,FALSE),0) -> 2292.84 | U115: =T115-F115 -> 0 | W115: =IFERROR(VLOOKUP(B115,[1]Todos!$A$2:$B$3021,2,FALSE),0) -> 49777.86 | X115: =W115-E115 -> -332.63
A116: =VLOOKUP(B116,Grupos!$A$2:$B$619,2,FALSE) -> INTERIORES | B116: I330 | C116: INTERIOR 30 CTOS 3F 225 AMP | D116: 5 | E116: 62015.94 | F116: 2606.24 | G116: =E116+F116 -> 64622.18 | H116: =E116*D116 -> 310079.7 | I116: =F116*D116 -> 13031.2 | J116: =G116*D116 -> 323110.9 | K116: =J116/$J$308 -> 0.0001928142 | L116: =$K$383*K116/D116 -> 16087.826 | M116: =F116*$M$382 -> 15335.701 | N116: =G116+L116+M116 -> 96045.706 | O116: =N116*D116 -> 480228.53 | P116: =Q116/D116 -> 182400 | Q116: 912000 | R116: =O116/Q116 -> 0.52656637 | T116: =IFERROR(VLOOKUP(B116,[1]Todos!$A$2:$C$3021,3,FALSE),0) -> 2535.17 | U116: =T116-F116 -> -71.07 | W116: =IFERROR(VLOOKUP(B116,[1]Todos!$A$2:$B$3021,2,FALSE),0) -> 61618.43 | X116: =W116-E116 -> -397.51
A117: =VLOOKUP(B117,Grupos!$A$2:$B$619,2,FALSE) -> INTERIORES | B117: I8TP-BIMETALICO | C117: INTERIOR 8 CTOS 85 AMP BIMETALICO | D117: 42 | E117: 8581 | F117: 1041.09 | G117: =E117+F117 -> 9622.09 | H117: =E117*D117 -> 360402 | I117: =F117*D117 -> 43725.78 | J117: =G117*D117 -> 404127.78 | K117: =J117/$J$308 -> 0.00024116046 | L117: =$K$383*K117/D117 -> 2395.4392 | M117: =F117*$M$382 -> 6126.007 | N117: =G117+L117+M117 -> 18143.536 | O117: =N117*D117 -> 762028.52 | P117: =Q117/D117 -> 28359.998 | Q117: 1191119.9 | R117: =O117/Q117 -> 0.63975802 | T117: =IFERROR(VLOOKUP(B117,[1]Todos!$A$2:$C$3021,3,FALSE),0) -> 0 | U117: =T117-F117 -> -1041.09 | W117: =IFERROR(VLOOKUP(B117,[1]Todos!$A$2:$B$3021,2,FALSE),0) -> 0 | X117: =W117-E117 -> -8581
A118: Total INTERIORES | D118: =SUBTOTAL(9,D108:D117) -> 66 | H118: =SUBTOTAL(9,H108:H117) -> 1429869 | I118: =SUBTOTAL(9,I108:I117) -> 89432.08 | J118: =SUBTOTAL(9,J108:J117) -> 1519301.1 | O118: =SUBTOTAL(9,O108:O117) -> 2423772.7 | Q118: =SUBTOTAL(9,Q108:Q117) -> 4432290.8 | R118: =O118/Q118 -> 0.54684424 | S118: =Q118/$Q$308 -> 0.0010235994 | T118: =IFERROR(VLOOKUP(B118,[1]Todos!$A$2:$C$3021,3,FALSE),0) -> 0 | U118: =T118-F118 -> 0 | W118: =IFERROR(VLOOKUP(B118,[1]Todos!$A$2:$B$3021,2,FALSE),0) -> 0 | X118: =W118-E118 -> 0
A119: =VLOOKUP(B119,Grupos!$A$2:$B$619,2,FALSE) -> REGLETAS | B119: R6M | C119: REGLETA DE 6 CIRCUITOS MONO (R6TPEM) | D119: 108 | E119: 6845.2 | F119: 695.83 | G119: =E119+F119 -> 7541.03 | H119: =E119*D119 -> 739281.6 | I119: =F119*D119 -> 75149.64 | J119: =G119*D119 -> 814431.24 | K119: =J119/$J$308 -> 0.00048600622 | L119: =$K$383*K119/D119 -> 1877.355 | M119: =F119*$M$382 -> 4094.4198 | N119: =G119+L119+M119 -> 13512.805 | O119: =N119*D119 -> 1459382.9 | P119: =Q119/D119 -> 20918.333 | Q119: 2259179.9 | R119: =O119/Q119 -> 0.64597905 | T119: =IFERROR(VLOOKUP(B119,[1]Todos!$A$2:$C$3021,3,FALSE),0) -> 0 | U119: =T119-F119 -> -695.83 | W119: =IFERROR(VLOOKUP(B119,[1]Todos!$A$2:$B$3021,2,FALSE),0) -> 0 | X119: =W119-E119 -> -6845.2
A120: =VLOOKUP(B120,Grupos!$A$2:$B$619,2,FALSE) -> REGLETAS | B120: R8 | C120: REGLETA DE 8 CTOS 75 AMPERIOS | D120: 20 | E120: 9228.39 | F120: 764.91 | G120: =E120+F120 -> 9993.3 | H120: =E120*D120 -> 184567.8 | I120: =F120*D120 -> 15298.2 | J120: =G120*D120 -> 199866 | K120: =J120/$J$308 -> 0.00011926865 | L120: =$K$383*K120/D120 -> 2487.8527 | M120: =F120*$M$382 -> 4500.902 | N120: =G120+L120+M120 -> 16982.055 | O120: =N120*D120 -> 339641.09 | P120: =Q120/D120 -> 25419.998 | Q120: 508399.97 | R120: =O120/Q120 -> 0.66805884 | T120: =IFERROR(VLOOKUP(B120,[1]Todos!$A$2:$C$3021,3,FALSE),0) -> 0 | U120: =T120-F120 -> -764.91 | W120: =IFERROR(VLOOKUP(B120,[1]Todos!$A$2:$B$3021,2,FALSE),0) -> 0 | X120: =W120-E120 -> -9228.39
A121: Total REGLETAS | D121: =SUBTOTAL(9,D119:D120) -> 128 | H121: =SUBTOTAL(9,H119:H120) -> 923849.4 | I121: =SUBTOTAL(9,I119:I120) -> 90447.84 | J121: =SUBTOTAL(9,J119:J120) -> 1014297.2 | O121: =SUBTOTAL(9,O119:O120) -> 1799024 | Q121: =SUBTOTAL(9,Q119:Q120) -> 2767579.9 | R121: =O121/Q121 -> 0.65003507 | S121: =Q121/$Q$308 -> 0.00063914877 | T121: =IFERROR(VLOOKUP(B121,[1]Todos!$A$2:$C$3021,3,FALSE),0) -> 0 | U121: =T121-F121 -> 0 | W121: =IFERROR(VLOOKUP(B121,[1]Todos!$A$2:$B$3021,2,FALSE),0) -> 0 | X121: =W121-E121 -> 0
A122: =VLOOKUP(B122,Grupos!$A$2:$B$619,2,FALSE) -> RITEL | B122: GCOMP45-45-15G | C122: GABINETE COMPLEMENTARIO 45X45X15 GAL | D122: 4 | E122: 21236.87 | F122: 1292.35 | G122: =E122+F122 -> 22529.22 | H122: =E122*D122 -> 84947.48 | I122: =F122*D122 -> 5169.4 | J122: =G122*D122 -> 90116.88 | K122: =J122/$J$308 -> 5.3776626e-05 | L122: =$K$383*K122/D122 -> 5608.696 | M122: =F122*$M$382 -> 7604.4772 | N122: =G122+L122+M122 -> 35742.393 | O122: =N122*D122 -> 142969.57 | P122: =Q122/D122 -> 78250 | Q122: 313000 | R122: =O122/Q122 -> 0.4567718 | T122: =IFERROR(VLOOKUP(B122,[1]Todos!$A$2:$C$3021,3,FALSE),0) -> 783.97 | U122: =T122-F122 -> -508.38 | W122: =IFERROR(VLOOKUP(B122,[1]Todos!$A$2:$B$3021,2,FALSE),0) -> 19493.64 | X122: =W122-E122 -> -1743.23
A123: =VLOOKUP(B123,Grupos!$A$2:$B$619,2,FALSE) -> RITEL | B123: GPISO ESPECIAL | C123: GABINETE DE PISO MEDIDAS ESPECIALES | D123: 158 | E123: 75444.36 | F123: 4984.94 | G123: =E123+F123 -> 80429.3 | H123: =E123*D123 -> 11920209 | I123: =F123*D123 -> 787620.52 | J123: =G123*D123 -> 12707829 | K123: =J123/$J$308 -> 0.0075833094 | L123: =$K$383*K123/D123 -> 20023.041 | M123: =F123*$M$382 -> 29332.505 | N123: =G123+L123+M123 -> 129784.85 | O123: =N123*D123 -> 20506006 | P123: =Q123/D123 -> 245155.06 | Q123: 38734500 | R123: =O123/Q123 -> 0.529399 | T123: =IFERROR(VLOOKUP(B123,[1]Todos!$A$2:$C$3021,3,FALSE),0) -> 0 | U123: =T123-F123 -> -4984.94 | W123: =IFERROR(VLOOKUP(B123,[1]Todos!$A$2:$B$3021,2,FALSE),0) -> 0 | X123: =W123-E123 -> -75444.36
A124: =VLOOKUP(B124,Grupos!$A$2:$B$619,2,FALSE) -> RITEL | B124: GPISO100G | C124: GABINETE DE PISO 100X55X20 GAL | D124: 198 | E124: 99648.75 | F124: 4226.86 | G124: =E124+F124 -> 103875.61 | H124: =E124*D124 -> 19730452 | I124: =F124*D124 -> 836918.28 | J124: =G124*D124 -> 20567371 | K124: =J124/$J$308 -> 0.012273436 | L124: =$K$383*K124/D124 -> 25860.048 | M124: =F124*$M$382 -> 24871.792 | N124: =G124+L124+M124 -> 154607.45 | O124: =N124*D124 -> 30612275 | P124: =Q124/D124 -> 364472.22 | Q124: 72165500 | R124: =O124/Q124 -> 0.42419543 | T124: =IFERROR(VLOOKUP(B124,[1]Todos!$A$2:$C$3021,3,FALSE),0) -> 4226.86 | U124: =T124-F124 -> 0 | W124: =IFERROR(VLOOKUP(B124,[1]Todos!$A$2:$B$3021,2,FALSE),0) -> 99648.75 | X124: =W124-E124 -> 0
A125: =VLOOKUP(B125,Grupos!$A$2:$B$619,2,FALSE) -> RITEL | B125: GPISO7030G | C125: GABINETE DE PISO DE 70X50X30 GAL | D125: 58 | E125: 70790.58 | F125: 4031.56 | G125: =E125+F125 -> 74822.14 | H125: =E125*D125 -> 4105853.6 | I125: =F125*D125 -> 233830.48 | J125: =G125*D125 -> 4339684.1 | K125: =J125/$J$308 -> 0.0025896765 | L125: =$K$383*K125/D125 -> 18627.127 | M125: =F125*$M$382 -> 23722.603 | N125: =G125+L125+M125 -> 117171.87 | O125: =N125*D125 -> 6795968.5 | P125: =Q125/D125 -> 235000 | Q125: 13630000 | R125: =O125/Q125 -> 0.4986037 | T125: =IFERROR(VLOOKUP(B125,[1]Todos!$A$2:$C$3021,3,FALSE),0) -> 4031.56 | U125: =T125-F125 -> 0 | W125: =IFERROR(VLOOKUP(B125,[1]Todos!$A$2:$B$3021,2,FALSE),0) -> 70790.58 | X125: =W125-E125 -> 0
A126: =VLOOKUP(B126,Grupos!$A$2:$B$619,2,FALSE) -> RITEL | B126: GPISO70G | C126: GABINETE DE PISO 70X50X20 GAL | D126: 247 | E126: 71740.69 | F126: 3924.98 | G126: =E126+F126 -> 75665.67 | H126: =E126*D126 -> 17719950 | I126: =F126*D126 -> 969470.06 | J126: =G126*D126 -> 18689420 | K126: =J126/$J$308 -> 0.011152783 | L126: =$K$383*K126/D126 -> 18837.125 | M126: =F126*$M$382 -> 23095.462 | N126: =G126+L126+M126 -> 117598.26 | O126: =N126*D126 -> 29046770 | P126: =Q126/D126 -> 232018.22 | Q126: 57308500 | R126: =O126/Q126 -> 0.50684924 | T126: =IFERROR(VLOOKUP(B126,[1]Todos!$A$2:$C$3021,3,FALSE),0) -> 3924.98 | U126: =T126-F126 -> 0 | W126: =IFERROR(VLOOKUP(B126,[1]Todos!$A$2:$B$3021,2,FALSE),0) -> 71740.69 | X126: =W126-E126 -> 0
A127: =VLOOKUP(B127,Grupos!$A$2:$B$619,2,FALSE) -> RITEL | B127: PAU ESPECIAL | C127: CAJA PAU 30X50X6 ESTANTAR GALV | D127: 144 | E127: 15362.23 | F127: 580.02 | G127: =E127+F127 -> 15942.25 | H127: =E127*D127 -> 2212161.1 | I127: =F127*D127 -> 83522.88 | J127: =G127*D127 -> 2295684 | K127: =J127/$J$308 -> 0.0013699336 | L127: =$K$383*K127/D127 -> 3968.8562 | M127: =F127*$M$382 -> 3412.9677 | N127: =G127+L127+M127 -> 23324.074 | O127: =N127*D127 -> 3358666.6 | P127: =Q127/D127 -> 72900 | Q127: 10497600 | R127: =O127/Q127 -> 0.31994614 | T127: =IFERROR(VLOOKUP(B127,[1]Todos!$A$2:$C$3021,3,FALSE),0) -> 0 | U127: =T127-F127 -> -580.02 | W127: =IFERROR(VLOOKUP(B127,[1]Todos!$A$2:$B$3021,2,FALSE),0) -> 0 | X127: =W127-E127 -> -15362.23
A128: =VLOOKUP(B128,Grupos!$A$2:$B$619,2,FALSE) -> RITEL | B128: PAU506G | C128: CAJA PAU 30X50X6 PLUS GAL | D128: 290 | E128: 17761.33 | F128: 1105 | G128: =E128+F128 -> 18866.33 | H128: =E128*D128 -> 5150785.7 | I128: =F128*D128 -> 320450 | J128: =G128*D128 -> 5471235.7 | K128: =J128/$J$308 -> 0.0032649221 | L128: =$K$383*K128/D128 -> 4696.8119 | M128: =F128*$M$382 -> 6502.0678 | N128: =G128+L128+M128 -> 30065.21 | O128: =N128*D128 -> 8718910.8 | P128: =Q128/D128 -> 69599.655 | Q128: 20183900 | R128: =O128/Q128 -> 0.43197354 | T128: =IFERROR(VLOOKUP(B128,[1]Todos!$A$2:$C$3021,3,FALSE),0) -> 865.24 | U128: =T128-F128 -> -239.76 | W128: =IFERROR(VLOOKUP(B128,[1]Todos!$A$2:$B$3021,2,FALSE),0) -> 17761.33 | X128: =W128-E128 -> 0
A129: =VLOOKUP(B129,Grupos!$A$2:$B$619,2,FALSE) -> RITEL | B129: PAU506G-E | C129: CAJA PAU 30X50X6 ESTANDAR GAL | D129: 3411 | E129: 13894.41 | F129: 580.02 | G129: =E129+F129 -> 14474.43 | H129: =E129*D129 -> 47393833 | I129: =F129*D129 -> 1978448.2 | J129: =G129*D129 -> 49372281 | K129: =J129/$J$308 -> 0.029462567 | L129: =$K$383*K129/D129 -> 3603.4393 | M129: =F129*$M$382 -> 3412.9677 | N129: =G129+L129+M129 -> 21490.837 | O129: =N129*D129 -> 73305245 | P129: =Q129/D129 -> 38659.689 | Q129: 131868200 | R129: =O129/Q129 -> 0.55589782 | T129: =IFERROR(VLOOKUP(B129,[1]Todos!$A$2:$C$3021,3,FALSE),0) -> 522.83 | U129: =T129-F129 -> -57.19 | W129: =IFERROR(VLOOKUP(B129,[1]Todos!$A$2:$B$3021,2,FALSE),0) -> 13894.41 | X129: =W129-E129 -> 0
A130: =VLOOKUP(B130,Grupos!$A$2:$B$619,2,FALSE) -> RITEL | B130: PAU506G-EH | C130: CAJA PAU 30X50X6 TAPA ESTANDAR CAJA PLUS SIN DF | D130: 732 | E130: 12766.98 | F130: 417.95 | G130: =E130+F130 -> 13184.93 | H130: =E130*D130 -> 9345429.4 | I130: =F130*D130 -> 305939.4 | J130: =G130*D130 -> 9651368.8 | K130: =J130/$J$308 -> 0.0057593876 | L130: =$K$383*K130/D130 -> 3282.4156 | M130: =F130*$M$382 -> 2459.3115 | N130: =G130+L130+M130 -> 18926.657 | O130: =N130*D130 -> 13854313 | P130: =Q130/D130 -> 40263.115 | Q130: 29472600 | R130: =O130/Q130 -> 0.47007434 | T130: =IFERROR(VLOOKUP(B130,[1]Todos!$A$2:$C$3021,3,FALSE),0) -> 280.39 | U130: =T130-F130 -> -137.56 | W130: =IFERROR(VLOOKUP(B130,[1]Todos!$A$2:$B$3021,2,FALSE),0) -> 12766.98 | X130: =W130-E130 -> 0
A131: =VLOOKUP(B131,Grupos!$A$2:$B$619,2,FALSE) -> RITEL | B131: PAU506G-H | C131: CAJA PAU 30X50X6 TAPA PLUS CAJA ESTANDAR | D131: 140 | E131: 14799.95 | F131: 1279.07 | G131: =E131+F131 -> 16079.02 | H131: =E131*D131 -> 2071993 | I131: =F131*D131 -> 179069.8 | J131: =G131*D131 -> 2251062.8 | K131: =J131/$J$308 -> 0.0013433062 | L131: =$K$383*K131/D131 -> 4002.9053 | M131: =F131*$M$382 -> 7526.3347 | N131: =G131+L131+M131 -> 27608.26 | O131: =N131*D131 -> 3865156.4 | P131: =Q131/D131 -> 59207.143 | Q131: 8289000 | R131: =O131/Q131 -> 0.46629948 | T131: =IFERROR(VLOOKUP(B131,[1]Todos!$A$2:$C$3021,3,FALSE),0) -> 1154.7 | U131: =T131-F131 -> -124.37 | W131: =IFERROR(VLOOKUP(B131,[1]Todos!$A$2:$B$3021,2,FALSE),0) -> 14799.95 | X131: =W131-E131 -> 0
...

Sheet Feb PUV lista
A2: DETALLE DE VENTAS 2026
E3: COSTO SIT UNITARIO | H3: COSTO SIT CANTIDAD
A4: GRUPO | B4: REF. | C4: DESCRIPCION | D4: CANT | E4: CUMAT | F4: CUMO | G4: CUNago | H4: CTMAT | I4: CTMO | J4: CTSIT | K4: %PART | L4: CIFU | M4: MOU | N4: CTU | O4: CT | P4: PUV | Q4: PU-LISTA | R4: DCTO PIE FACT | S4: % | T4: PRECIOTOT | U4: %CTO | V4: %Part.
A5: =VLOOKUP(B5,Grupos!$A$2:$B$619,2,FALSE) -> ACCESORIOS | B5: BN-08 | C5: BANDEJA PARA INTERIOR *I-8P* | D5: 1 | E5: 1216.9 | F5: =VLOOKUP(B5,Feb!$B$6:$F$305,5,FALSE) -> 73.14 | G5: =E5+F5 -> 1290.04 | H5: =E5*D5 -> 1216.9 | I5: =F5*D5 -> 73.14 | J5: =G5*D5 -> 1290.04 | K5: =J5/$J$277 -> 7.3993233e-07 | L5: 303.2461 | M5: =VLOOKUP(B5,Feb!$B$6:$M$305,12,FALSE) -> 430.37216 | N5: =G5+L5+M5 -> 2023.6583 | O5: =N5*D5 -> 2023.6583 | P5: =T5/D5 -> 6762 | Q5: 16100 | R5: =Q5-P5 -> 9338 | S5: =R5/Q5 -> 0.58 | T5: 6762 | U5: =O5/T5 -> 0.29926919
A6: =VLOOKUP(B6,Grupos!$A$2:$B$619,2,FALSE) -> ACCESORIOS | B6: BN-18 | C6: BANDEJA PARA INTERIOR *I-18P,I-218,I-318 | D6: 1 | E6: 2120.5 | F6: =VLOOKUP(B6,Feb!$B$6:$F$305,5,FALSE) -> 123.35 | G6: =E6+F6 -> 2243.85 | H6: =E6*D6 -> 2120.5 | I6: =F6*D6 -> 123.35 | J6: =G6*D6 -> 2243.85 | K6: =J6/$J$277 -> 1.2870121e-06 | L6: 527.45556 | M6: =VLOOKUP(B6,Feb!$B$6:$M$305,12,FALSE) -> 725.81906 | N6: =G6+L6+M6 -> 3497.1246 | O6: =N6*D6 -> 3497.1246 | P6: =T6/D6 -> 11970 | Q6: 26600 | R6: =Q6-P6 -> 14630 | S6: =R6/Q6 -> 0.55 | T6: 11970 | U6: =O6/T6 -> 0.29215745
A7: =VLOOKUP(B7,Grupos!$A$2:$B$619,2,FALSE) -> ACCESORIOS | B7: BN-24 | C7: BANDEJA PARA INTERIOR *I-224,I-324* | D7: 1 | E7: 2376.63 | F7: =VLOOKUP(B7,Feb!$B$6:$F$305,5,FALSE) -> 87.07 | G7: =E7+F7 -> 2463.7 | H7: =E7*D7 -> 2376.63 | I7: =F7*D7 -> 87.07 | J7: =G7*D7 -> 2463.7 | K7: =J7/$J$277 -> 1.4131122e-06 | L7: 579.13508 | M7: =VLOOKUP(B7,Feb!$B$6:$M$305,12,FALSE) -> 512.3394 | N7: =G7+L7+M7 -> 3555.1745 | O7: =N7*D7 -> 3555.1745 | P7: =T7/D7 -> 26700 | Q7: 33600 | R7: =Q7-P7 -> 6900 | S7: =R7/Q7 -> 0.20535714 | T7: 26700 | U7: =O7/T7 -> 0.1331526
A8: =VLOOKUP(B8,Grupos!$A$2:$B$619,2,FALSE) -> ACCESORIOS | B8: BN-36 | C8: BANDEJA PARA INTERIOR *I-236,I-336* | D8: 1 | E8: 3286.26 | F8: =VLOOKUP(B8,Feb!$B$6:$F$305,5,FALSE) -> 157.35 | G8: =E8+F8 -> 3443.61 | H8: =E8*D8 -> 3286.26 | I8: =F8*D8 -> 157.35 | J8: =G8*D8 -> 3443.61 | K8: =J8/$J$277 -> 1.9751623e-06 | L8: 809.47979 | M8: =VLOOKUP(B8,Feb!$B$6:$M$305,12,FALSE) -> 925.88268 | N8: =G8+L8+M8 -> 5178.9725 | O8: =N8*D8 -> 5178.9725 | P8: =T8/D8 -> 38587.5 | Q8: 51450 | R8: =Q8-P8 -> 12862.5 | S8: =R8/Q8 -> 0.25 | T8: 38587.5 | U8: =O8/T8 -> 0.13421373
A9: =VLOOKUP(B9,Grupos!$A$2:$B$619,2,FALSE) -> ACCESORIOS | B9: BNTOTA | C9: BANDEJA PARA TOTALIZADOR | D9: 1 | E9: 2141.58 | F9: =VLOOKUP(B9,Feb!$B$6:$F$305,5,FALSE) -> 66.96 | G9: =E9+F9 -> 2208.54 | H9: =E9*D9 -> 2141.58 | I9: =F9*D9 -> 66.96 | J9: =G9*D9 -> 2208.54 | K9: =J9/$J$277 -> 1.2667593e-06 | L9: 519.15533 | M9: =VLOOKUP(B9,Feb!$B$6:$M$305,12,FALSE) -> 394.00766 | N9: =G9+L9+M9 -> 3121.703 | O9: =N9*D9 -> 3121.703 | P9: =T9/D9 -> 33112.5 | Q9: 44150 | R9: =Q9-P9 -> 11037.5 | S9: =R9/Q9 -> 0.25 | T9: 33112.5 | U9: =O9/T9 -> 0.094275666
A10: =VLOOKUP(B10,Grupos!$A$2:$B$619,2,FALSE) -> ACCESORIOS | B10: CHAPA-1 | C10: CHAPA GAVETA (TRPs) | D10: 20 | E10: 3200 | F10: =VLOOKUP(B10,Feb!$B$6:$F$305,5,FALSE) -> 0 | G10: =E10+F10 -> 3200 | H10: =E10*D10 -> 64000 | I10: =F10*D10 -> 0 | J10: =G10*D10 -> 64000 | K10: =J10/$J$277 -> 3.6708683e-05 | L10: 752.21507 | M10: =VLOOKUP(B10,Feb!$B$6:$M$305,12,FALSE) -> 0 | N10: =G10+L10+M10 -> 3952.2151 | O10: =N10*D10 -> 79044.301 | P10: =T10/D10 -> 7217.55 | Q10: 18650 | R10: =Q10-P10 -> 11432.45 | S10: =R10/Q10 -> 0.613 | T10: 144351 | U10: =O10/T10 -> 0.54758402
A11: =VLOOKUP(B11,Grupos!$A$2:$B$619,2,FALSE) -> ACCESORIOS | B11: CIERRE | C11: CIERRE DE TRINQUETE | D11: 20 | E11: 68.22 | F11: =VLOOKUP(B11,Feb!$B$6:$F$305,5,FALSE) -> 12.44 | G11: =E11+F11 -> 80.66 | H11: =E11*D11 -> 1364.4 | I11: =F11*D11 -> 248.8 | J11: =G11*D11 -> 1613.2 | K11: =J11/$J$277 -> 9.2528823e-07 | L11: 18.960521 | M11: =VLOOKUP(B11,Feb!$B$6:$M$305,12,FALSE) -> 73.19975 | N11: =G11+L11+M11 -> 172.82027 | O11: =N11*D11 -> 3456.4054 | P11: =T11/D11 -> 1540 | Q11: 3850 | R11: =Q11-P11 -> 2310 | S11: =R11/Q11 -> 0.6 | T11: 30800 | U11: =O11/T11 -> 0.11222095
A12: =VLOOKUP(B12,Grupos!$A$2:$B$619,2,FALSE) -> ACCESORIOS | B12: GRAPAM12-D | C12: GRAPA METALICA 1/2" DOBLE | D12: 13800 | E12: 59.89 | F12: =VLOOKUP(B12,Feb!$B$6:$F$305,5,FALSE) -> 35.07 | G12: =E12+F12 -> 94.96 | H12: =E12*D12 -> 826482 | I12: =F12*D12 -> 483966 | J12: =G12*D12 -> 1310448 | K12: =J12/$J$277 -> 0.00075163781 | L12: 22.321982 | M12: =VLOOKUP(B12,Feb!$B$6:$M$305,12,FALSE) -> 206.35974 | N12: =G12+L12+M12 -> 323.64173 | O12: =N12*D12 -> 4466255.8 | P12: =T12/D12 -> 120.3913 | Q12: 300 | R12: =Q12-P12 -> 179.6087 | S12: =R12/Q12 -> 0.59869566 | T12: 1661399.9 | U12: =O12/T12 -> 2.6882484
A13: =VLOOKUP(B13,Grupos!$A$2:$B$619,2,FALSE) -> ACCESORIOS | B13: GRAPAM12-S | C13: GRAPA METALICA 1/2" SENCILLA | D13: -2400 | E13: 43.39 | F13: =VLOOKUP(B13,Feb!$B$6:$F$305,5,FALSE) -> 43.22 | G13: =E13+F13 -> 86.61 | H13: =E13*D13 -> -104136 | I13: =F13*D13 -> -103728 | J13: =G13*D13 -> -207864 | K13: =J13/$J$277 -> -0.00011922521 | L13: 20.359171 | M13: =VLOOKUP(B13,Feb!$B$6:$M$305,12,FALSE) -> 254.31617 | N13: =G13+L13+M13 -> 361.28534 | O13: =N13*D13 -> -867084.82 | P13: =T13/D13 -> 102.50001 | Q13: 250 | R13: =Q13-P13 -> 147.49999 | S13: =R13/Q13 -> 0.58999997 | T13: -246000.02 | U13: =O13/T13 -> 3.5247348
A14: =VLOOKUP(B14,Grupos!$A$2:$B$619,2,FALSE) -> ACCESORIOS | B14: NEUTRO12 | C14: NEUTRO DE 12 CIRCUITOS | D14: 28 | E14: 2166.94 | F14: =VLOOKUP(B14,Feb!$B$6:$F$305,5,FALSE) -> 0 | G14: =E14+F14 -> 2166.94 | H14: =E14*D14 -> 60674.32 | I14: =F14*D14 -> 0 | J14: =G14*D14 -> 60674.32 | K14: =J14/$J$277 -> 3.4801162e-05 | L14: 509.37654 | M14: =VLOOKUP(B14,Feb!$B$6:$M$305,12,FALSE) -> 0 | N14: =G14+L14+M14 -> 2676.3165 | O14: =N14*D14 -> 74936.863 | P14: =T14/D14 -> 12970.286 | Q14: 31200 | R14: =Q14-P14 -> 18229.714 | S14: =R14/Q14 -> 0.58428571 | T14: 363168 | U14: =O14/T14 -> 0.20634214
A15: =VLOOKUP(B15,Grupos!$A$2:$B$619,2,FALSE) -> ACCESORIOS | B15: NEUTRO18 | C15: NEUTRO DE 18 CIRCUITOS | D15: 1 | E15: 3042.06 | F15: =VLOOKUP(B15,Feb!$B$6:$F$305,5,FALSE) -> 0 | G15: =E15+F15 -> 3042.06 | H15: =E15*D15 -> 3042.06 | I15: =F15*D15 -> 0 | J15: =G15*D15 -> 3042.06 | K15: =J15/$J$277 -> 1.744844e-06 | L15: 715.08856 | M15: =VLOOKUP(B15,Feb!$B$6:$M$305,12,FALSE) -> 0 | N15: =G15+L15+M15 -> 3757.1486 | O15: =N15*D15 -> 3757.1486 | P15: =T15/D15 -> 32812.5 | Q15: 43750 | R15: =Q15-P15 -> 10937.5 | S15: =R15/Q15 -> 0.25 | T15: 32812.5 | U15: =O15/T15 -> 0.11450358
A16: =VLOOKUP(B16,Grupos!$A$2:$B$619,2,FALSE) -> ACCESORIOS | B16: NEUTRO18R | C16: NEUTRO DE 18 CIRCUITOS REFORZADO | D16: 7 | E16: 7688.17 | F16: =VLOOKUP(B16,Feb!$B$6:$F$305,5,FALSE) -> 0 | G16: =E16+F16 -> 7688.17 | H16: =E16*D16 -> 53817.19 | I16: =F16*D16 -> 0 | J16: =G16*D16 -> 53817.19 | K16: =J16/$J$277 -> 3.0868096e-05 | L16: 1807.2367 | M16: =VLOOKUP(B16,Feb!$B$6:$M$305,12,FALSE) -> 0 | N16: =G16+L16+M16 -> 9495.4067 | O16: =N16*D16 -> 66467.847 | P16: =T16/D16 -> 24174 | Q16: 55300 | R16: =Q16-P16 -> 31126 | S16: =R16/Q16 -> 0.56285714 | T16: 169218 | U16: =O16/T16 -> 0.39279419
... A27: =VLOOKUP(B27,Grupos!$A$2:$B$619,2,FALSE) -> ACCESORIOS | B27: TAPA8P | C27: TAPA PARA TABLERO TB8P | D27: 16 | E27: 4356.76 | F27: =VLOOKUP(B27,Feb!$B$6:$F$305,5,FALSE) -> 36.38 | G27: =E27+F27 -> 4393.14 | H27: =E27*D27 -> 69708.16 | I27: =F27*D27 -> 582.08 | J27: =G27*D27 -> 70290.24 | K27: =J27/$J$277 -> 4.0316595e-05 | L27: 1032.6832 | M27: =VLOOKUP(B27,Feb!$B$6:$M$305,12,FALSE) -> 214.06808 | N27: =G27+L27+M27 -> 5639.8912 | O27: =N27*D27 -> 90238.26 | P27: =T27/D27 -> 31350 | Q27: 41800 | R27: =Q27-P27 -> 10450 | S27: =R27/Q27 -> 0.25 | T27: 501600 | U27: =O27/T27 -> 0.17990084
A28: =VLOOKUP(B28,Grupos!$A$2:$B$619,2,FALSE) -> ACCESORIOS | B28: TAPA-GA70 | C28: TAPA PARA GABINETE DE PISO 70X50 RITEL | D28: 2 | E28: 13959.25 | F28: =VLOOKUP(B28,Feb!$B$6:$F$305,5,FALSE) -> 2626.26 | G28: =E28+F28 -> 16585.51 | H28: =E28*D28 -> 27918.5 | I28: =F28*D28 -> 5252.52 | J28: =G28*D28 -> 33171.02 | K28: =J28/$J$277 -> 1.9026007e-05 | L28: 3898.7096 | M28: =VLOOKUP(B28,Feb!$B$6:$M$305,12,FALSE) -> 15453.503 | N28: =G28+L28+M28 -> 35937.722 | O28: =N28*D28 -> 71875.445 | P28: =T28/D28 -> 79500 | Q28: 79500 | S28: =R28/Q28 -> 0 | T28: 159000 | U28: =O28/T28 -> 0.45204682
A29: =VLOOKUP(B29,Grupos!$A$2:$B$619,2,FALSE) -> ACCESORIOS | B29: TAPAPAU506 | C29: TAPA PARA CAJA PAU 30X50 PLUS | D29: 4 | E29: 7152.29 | F29: =VLOOKUP(B29,Feb!$B$6:$F$305,5,FALSE) -> 595.45 | G29: =E29+F29 -> 7747.74 | H29: =E29*D29 -> 28609.16 | I29: =F29*D29 -> 2381.8 | J29: =G29*D29 -> 30990.96 | K29: =J29/$J$277 -> 1.7775583e-05 | L29: 1821.2396 | M29: =VLOOKUP(B29,Feb!$B$6:$M$305,12,FALSE) -> 3503.7613 | N29: =G29+L29+M29 -> 13072.741 | O29: =N29*D29 -> 52290.964 | P29: =T29/D29 -> 16500 | Q29: 22000 | R29: =Q29-P29 -> 5500 | S29: =R29/Q29 -> 0.25 | T29: 66000 | U29: =O29/T29 -> 0.79228733
A30: =VLOOKUP(B30,Grupos!$A$2:$B$619,2,FALSE) -> ACCESORIOS | B30: TCE1212L | C30: TAPA PARA CE-125 LISA. | D30: 203 | E30: 412.02 | F30: =VLOOKUP(B30,Feb!$B$6:$F$305,5,FALSE) -> 31.34 | G30: =E30+F30 -> 443.36 | H30: =E30*D30 -> 83640.06 | I30: =F30*D30 -> 6362.02 | J30: =G30*D30 -> 90002.08 | K30: =J30/$J$277 -> 5.1622778e-05 | L30: 104.2194 | M30: =VLOOKUP(B30,Feb!$B$6:$M$305,12,FALSE) -> 184.41159 | N30: =G30+L30+M30 -> 731.99099 | O30: =N30*D30 -> 148594.17 | P30: =T30/D30 -> 2702.5864 | Q30: 7500 | R30: =Q30-P30 -> 4797.4136 | S30: =R30/Q30 -> 0.63965515 | T30: 548625.03 | U30: =O30/T30 -> 0.27084832
A31: =VLOOKUP(B31,Grupos!$A$2:$B$619,2,FALSE) -> ACCESORIOS | B31: TCE1212LX | C31: TAPA CE-125 TROQUELADA LX | D31: 233 | E31: 412.02 | F31: =VLOOKUP(B31,Feb!$B$6:$F$305,5,FALSE) -> 31.34 | G31: =E31+F31 -> 443.36 | H31: =E31*D31 -> 96000.66 | I31: =F31*D31 -> 7302.22 | J31: =G31*D31 -> 103302.88 | K31: =J31/$J$277 -> 5.925176e-05 | L31: 104.2194 | M31: =VLOOKUP(B31,Feb!$B$6:$M$305,12,FALSE) -> 184.41159 | N31: =G31+L31+M31 -> 731.99099 | O31: =N31*D31 -> 170553.9 | P31: =T31/D31 -> 2867.7039 | Q31: 7500 | R31: =Q31-P31 -> 4632.2961 | S31: =R31/Q31 -> 0.61763948 | T31: 668175.01 | U31: =O31/T31 -> 0.25525333
A32: =VLOOKUP(B32,Grupos!$A$2:$B$619,2,FALSE) -> ACCESORIOS | B32: TCE1212T | C32: TAPA CE-125 TROQUELADA LEV | D32: 524 | E32: 412.02 | F32: =VLOOKUP(B32,Feb!$B$6:$F$305,5,FALSE) -> 31.34 | G32: =E32+F32 -> 443.36 | H32: =E32*D32 -> 215898.48 | I32: =F32*D32 -> 16422.16 | J32: =G32*D32 -> 232320.64 | K32: =J32/$J$277 -> 0.00013325288 | L32: 104.2194 | M32: =VLOOKUP(B32,Feb!$B$6:$M$305,12,FALSE) -> 184.41159 | N32: =G32+L32+M32 -> 731.99099 | O32: =N32*D32 -> 383563.28 | P32: =T32/D32 -> 2658.4925 | Q32: 7500 | R32: =Q32-P32 -> 4841.5075 | S32: =R32/Q32 -> 0.64553433 | T32: 1393050.1 | U32: =O32/T32 -> 0.27534062
A33: =VLOOKUP(B33,Grupos!$A$2:$B$619,2,FALSE) -> ACCESORIOS | B33: TIERRA12 | C33: TIERRA DE 12 CIRCUITOS | D33: 20 | E33: 2250.44 | F33: =VLOOKUP(B33,Feb!$B$6:$F$305,5,FALSE) -> 0 | G33: =E33+F33 -> 2250.44 | H33: =E33*D33 -> 45008.8 | I33: =F33*D33 -> 0 | J33: =G33*D33 -> 45008.8 | K33: =J33/$J$277 -> 2.581584e-05 | L33: 529.00465 | M33: =VLOOKUP(B33,Feb!$B$6:$M$305,12,FALSE) -> 0 | N33: =G33+L33+M33 -> 2779.4447 | O33: =N33*D33 -> 55588.893 | P33: =T33/D33 -> 13416 | Q33: 31200 | R33: =Q33-P33 -> 17784 | S33: =R33/Q33 -> 0.57 | T33: 268320 | U33: =O33/T33 -> 0.20717387
A34: =VLOOKUP(B34,Grupos!$A$2:$B$619,2,FALSE) -> ACCESORIOS | B34: TIERRA12R | C34: TIERRA DE 12 CIRCUITOS REFORZADA | D34: 6 | E34: 6037.37 | F34: =VLOOKUP(B34,Feb!$B$6:$F$305,5,FALSE) -> 0 | G34: =E34+F34 -> 6037.37 | H34: =E34*D34 -> 36224.22 | I34: =F34*D34 -> 0 | J34: =G34*D34 -> 36224.22 | K34: =J34/$J$277 -> 2.077724e-05 | L34: 1419.1877 | M34: =VLOOKUP(B34,Feb!$B$6:$M$305,12,FALSE) -> 0 | N34: =G34+L34+M34 -> 7456.5577 | O34: =N34*D34 -> 44739.346 | P34: =T34/D34 -> 17820 | Q34: 40500 | R34: =Q34-P34 -> 22680 | S34: =R34/Q34 -> 0.56 | T34: 106920 | U34: =O34/T34 -> 0.41843758
A35: =VLOOKUP(B35,Grupos!$A$2:$B$619,2,FALSE) -> ACCESORIOS | B35: TIERRA18 | C35: TIERRA DE 18 CIRCUITOS | D35: 1 | E35: 3125.57 | F35: =VLOOKUP(B35,Feb!$B$6:$F$305,5,FALSE) -> 0 | G35: =E35+F35 -> 3125.57 | H35: =E35*D35 -> 3125.57 | I35: =F35*D35 -> 0 | J35: =G35*D35 -> 3125.57 | K35: =J35/$J$277 -> 1.7927431e-06 | L35: 734.71902 | M35: =VLOOKUP(B35,Feb!$B$6:$M$305,12,FALSE) -> 0 | N35: =G35+L35+M35 -> 3860.289 | O35: =N35*D35 -> 3860.289 | P35: =T35/D35 -> 32812.5 | Q35: 43750 | R35: =Q35-P35 -> 10937.5 | S35: =R35/Q35 -> 0.25 | T35: 32812.5 | U35: =O35/T35 -> 0.1176469
A36: =VLOOKUP(B36,Grupos!$A$2:$B$619,2,FALSE) -> ACCESORIOS | B36: TIERRA18R | C36: TIERRA DE 18 CIRCUITOS REFORZADA | D36: 6 | E36: 8018.41 | F36: =VLOOKUP(B36,Feb!$B$6:$F$305,5,FALSE) -> 0 | G36: =E36+F36 -> 8018.41 | H36: =E36*D36 -> 48110.46 | I36: =F36*D36 -> 0 | J36: =G36*D36 -> 48110.46 | K36: =J36/$J$277 -> 2.7594869e-05 | L36: 1884.8653 | M36: =VLOOKUP(B36,Feb!$B$6:$M$305,12,FALSE) -> 0 | N36: =G36+L36+M36 -> 9903.2753 | O36: =N36*D36 -> 59419.652 | P36: =T36/D36 -> 24332 | Q36: 55300 | R36: =Q36-P36 -> 30968 | S36: =R36/Q36 -> 0.56 | T36: 145992 | U36: =O36/T36 -> 0.40700622
A37: =VLOOKUP(B37,Grupos!$A$2:$B$619,2,FALSE) -> ACCESORIOS | B37: TIERRA24R | C37: TIERRA DE 24 CIRCUITOS REFORZADA | D37: 1 | E37: 9999.41 | F37: =VLOOKUP(B37,Feb!$B$6:$F$305,5,FALSE) -> 0 | G37: =E37+F37 -> 9999.41 | H37: =E37*D37 -> 9999.41 | I37: =F37*D37 -> 0 | J37: =G37*D37 -> 9999.41 | K37: =J37/$J$277 -> 5.7353932e-06 | L37: 2350.5334 | M37: =VLOOKUP(B37,Feb!$B$6:$M$305,12,FALSE) -> 0 | N37: =G37+L37+M37 -> 12349.943 | O37: =N37*D37 -> 12349.943 | P37: =T37/D37 -> 51937.5 | Q37: 69250 | R37: =Q37-P37 -> 17312.5 | S37: =R37/Q37 -> 0.25 | T37: 51937.5 | U37: =O37/T37 -> 0.23778471
A38: =VLOOKUP(B38,Grupos!$A$2:$B$619,2,FALSE) -> ACCESORIOS | B38: TIERRA42R | C38: TIERRA DE 42 CIRCUITOS REFORZADA | D38: 1 | E38: 15942.4 | F38: =VLOOKUP(B38,Feb!$B$6:$F$305,5,FALSE) -> 0 | G38: =E38+F38 -> 15942.4 | H38: =E38*D38 -> 15942.4 | I38: =F38*D38 -> 0 | J38: =G38*D38 -> 15942.4 | K38: =J38/$J$277 -> 9.1441328e-06 | L38: 3747.5355 | M38: =VLOOKUP(B38,Feb!$B$6:$M$305,12,FALSE) -> 0 | N38: =G38+L38+M38 -> 19689.935 | O38: =N38*D38 -> 19689.935 | P38: =T38/D38 -> 85125 | Q38: 113500 | R38: =Q38-P38 -> 28375 | S38: =R38/Q38 -> 0.25 | T38: 85125 | U38: =O38/T38 -> 0.23130614
A39: =VLOOKUP(B39,Grupos!$A$2:$B$619,2,FALSE) -> ACCESORIOS | B39: TIERRA6 | C39: TIERRA DE 6 CIRCUITOS | D39: 6 | E39: 1271.15 | F39: =VLOOKUP(B39,Feb!$B$6:$F$305,5,FALSE) -> 0 | G39: =E39+F39 -> 1271.15 | H39: =E39*D39 -> 7626.9 | I39: =F39*D39 -> 0 | J39: =G39*D39 -> 7626.9 | K39: =J39/$J$277 -> 4.3745852e-06 | L39: 298.80568 | M39: =VLOOKUP(B39,Feb!$B$6:$M$305,12,FALSE) -> 0 | N39: =G39+L39+M39 -> 1569.9557 | O39: =N39*D39 -> 9419.7341 | P39: =T39/D39 -> 6776 | Q39: 15400 | R39: =Q39-P39 -> 8624 | S39: =R39/Q39 -> 0.56 | T39: 40656 | U39: =O39/T39 -> 0.23169358
A40: =VLOOKUP(B40,Grupos!$A$2:$B$619,2,FALSE) -> ACCESORIOS | B40: TIERRA8 | C40: TIERRA DE 8 CIRCUITOS | D40: 136 | E40: 1666.74 | F40: =VLOOKUP(B40,Feb!$B$6:$F$305,5,FALSE) -> 0 | G40: =E40+F40 -> 1666.74 | H40: =E40*D40 -> 226676.64 | I40: =F40*D40 -> 0 | J40: =G40*D40 -> 226676.64 | K40: =J40/$J$277 -> 0.00013001564 | L40: 391.79592 | M40: =VLOOKUP(B40,Feb!$B$6:$M$305,12,FALSE) -> 0 | N40: =G40+L40+M40 -> 2058.5359 | O40: =N40*D40 -> 279960.89 | P40: =T40/D40 -> 9227.0591 | Q40: 22000 | R40: =Q40-P40 -> 12772.941 | S40: =R40/Q40 -> 0.58058822 | T40: 1254880 | U40: =O40/T40 -> 0.22309773
... A276: =VLOOKUP(B276,Grupos!$A$2:$B$619,2,FALSE) -> TAPAS PLASTICAS | B276: TPL4X4-LH | C276: TAPA PLASTICA LISA 4X4 LIBRE DE HALOGENOS | D276: 33630 | E276: 96.41 | F276: =VLOOKUP(B276,Feb!$B$6:$F$305,5,FALSE) -> 21.71 | G276: =E276+F276 -> 118.12 | H276: =E276*D276 -> 3242268.3 | I276: =F276*D276 -> 730107.3 | J276: =G276*D276 -> 3972375.6 | K276: =J276/$J$277 -> 0.002278448 | L276: 28.01531 | M276: =VLOOKUP(B276,Feb!$B$6:$M$305,12,FALSE) -> 127.74651 | N276: =G276+L276+M276 -> 273.88182 | O276: =N276*D276 -> 9210645.5 | P276: =T276/D276 -> 278.77967 | Q276: 800 | R276: =Q276-P276 -> 521.22033 | S276: =R276/Q276 -> 0.65152541 | T276: 9375360.3 | U276: =O276/T276 -> 0.9824311
A277: TOTAL FABRICADO | D277: 2984608.3 | H277: =SUM(H5:H276) -> 1.630374e+09 | I277: =SUM(I5:I276) -> 1.1308272e+08 | J277: =SUM(J5:J276) -> 1.7434567e+09 | K277: 1 | O277: =SUM(O5:O276) -> 2.8260455e+09 | R277: =Q277-P277 -> 0 | T277: =SUM(T5:T276) -> 4.3308765e+09 | U277: =O277/T277 -> 0.65253432 | V277: =T277/$T$346 -> 0.83499992
A278: =VLOOKUP(B278,Grupos!$A$2:$B$619,2,FALSE) -> SETI | B278: G-SETI/SETS 2 X 1.5 | C278: GABINETE TELECOMUNICACION 2 M X 1.5 M X 50 CM | D278: 2 | E278: 2550000 | F278: 0 | G278: =E278+F278 -> 2550000 | H278: =E278*D278 -> 5100000 | I278: =F278*D278 -> 0 | J278: =G278*D278 -> 5100000 | K278: =J278/J280 -> 0.67819149 | M278: 0 | N278: =G278+L278+M278 -> 2550000 | O278: =N278*D278 -> 5100000 | P278: =T278/D278 -> 4100000 | Q278: 3950000 | R278: =Q278-P278 -> -150000 | S278: =R278/Q278 -> -0.037974684 | T278: 8200000 | U278: =O278/T278 -> 0.62195122
A279: =VLOOKUP(B279,Grupos!$A$2:$B$619,2,FALSE) -> SETI | B279: G-SETI/SETS 2 X1 | C279: GABINETE TELECOMUNICACION 2 M X 1 M X 50 CM | D279: 1 | E279: 2420000 | F279: 0 | G279: =E279+F279 -> 2420000 | H279: =E279*D279 -> 2420000 | I279: =F279*D279 -> 0 | J279: =G279*D279 -> 2420000 | K279: =J279/J280 -> 0.32180851 | M279: 0 | N279: =G279+L279+M279 -> 2420000 | O279: =N279*D279 -> 2420000 | P279: =T279/D279 -> 2970000 | Q279: 3800000 | R279: =Q279-P279 -> 830000 | S279: =R279/Q279 -> 0.21842105 | T279: 2970000 | U279: =O279/T279 -> 0.81481481
A280: TOTAL SETI | D280: =SUM(D278:D279) -> 3 | H280: =SUM(H278:H279) -> 7520000 | I280: =SUM(I278:I279) -> 0 | J280: =SUM(J278:J279) -> 7520000 | K280: 1 | O280: =SUM(O278:O279) -> 7520000 | R280: =Q280-P280 -> 0 | T280: =SUM(T278:T279) -> 11170000 | U280: =O280/T280 -> 0.67323187 | V280: =T280/$T$346 -> 0.0021535939
A281: =VLOOKUP(B281,Grupos!$A$2:$B$619,2,FALSE) -> BREAKERS | B281: ITM115 | C281: INTERRUPTOR TERMOMAGNETICO 1P 15 AMP BLANCO | D281: 1272 | E281: 5808.8316 | G281: =E281+F281 -> 5808.8316 | H281: =E281*D281 -> 7388833.8 | I281: =F281*D281 -> 0 | J281: =G281*D281 -> 7388833.8 | K281: =J281/$J$332 -> 0.024320058 | M281: 0 | N281: =G281+L281+M281 -> 5808.8316 | O281: =N281*D281 -> 7388833.8 | P281: =T281/D281 -> 7016.0377 | Q281: 21250 | R281: =Q281-P281 -> 14233.962 | S281: =R281/Q281 -> 0.66983352 | T281: 8924400 | U281: =O281/T281 -> 0.8279362
A282: =VLOOKUP(B282,Grupos!$A$2:$B$619,2,FALSE) -> BREAKERS | B282: ITM115NG | C282: INTERRUPTOR TERMOMAGNETICO 1P 15 AMP NEGRO | D282: 1632 | E282: 5815.0243 | G282: =E282+F282 -> 5815.0243 | H282: =E282*D282 -> 9490119.7 | I282: =F282*D282 -> 0 | J282: =G282*D282 -> 9490119.7 | K282: =J282/$J$332 -> 0.031236359 | M282: 0 | N282: =G282+L282+M282 -> 5815.0243 | O282: =N282*D282 -> 9490119.7 | P282: =T282/D282 -> 6932.3529 | Q282: 21250 | R282: =Q282-P282 -> 14317.647 | S282: =R282/Q282 -> 0.67377163 | T282: 11313600 | U282: =O282/T282 -> 0.83882404
A283: =VLOOKUP(B283,Grupos!$A$2:$B$619,2,FALSE) -> BREAKERS | B283: ITM120 | C283: INTERRUPTOR TERMOMAGNETICO 1P 20 AMP BLANCO | D283: 20208 | E283: 5145.9468 | G283: =E283+F283 -> 5145.9468 | H283: =E283*D283 -> 1.0398929e+08 | I283: =F283*D283 -> 0 | J283: =G283*D283 -> 1.0398929e+08 | K283: =J283/$J$332 -> 0.34227671 | M283: 0 | N283: =G283+L283+M283 -> 5145.9468 | O283: =N283*D283 -> 1.0398929e+08 | P283: =T283/D283 -> 6950.5048 | Q283: 21250 | R283: =Q283-P283 -> 14299.495 | S283: =R283/Q283 -> 0.67291742 | T283: 140455800 | U283: =O283/T283 -> 0.74037023
A284: =VLOOKUP(B284,Grupos!$A$2:$B$619,2,FALSE) -> BREAKERS | B284: ITM120NG | C284: INTERRUPTOR TERMOMAGNETICO 1P 20 AMP NEGRO | D284: 7380 | E284: 5145.9468 | G284: =E284+F284 -> 5145.9468 | H284: =E284*D284 -> 37977088 | I284: =F284*D284 -> 0 | J284: =G284*D284 -> 37977088 | K284: =J284/$J$332 -> 0.1250001 | M284: 0 | N284: =G284+L284+M284 -> 5145.9468 | O284: =N284*D284 -> 37977088 | P284: =T284/D284 -> 6949.4309 | Q284: 21250 | R284: =Q284-P284 -> 14300.569 | S284: =R284/Q284 -> 0.67296796 | T284: 51286800 | U284: =O284/T284 -> 0.74048464
A285: =VLOOKUP(B285,Grupos!$A$2:$B$619,2,FALSE) -> BREAKERS | B285: ITM130 | C285: INTERRUPTOR TERMOMAGNETICO 1P 30 AMP BLANCO | D285: 1416 | E285: 5145.9468 | G285: =E285+F285 -> 5145.9468 | H285: =E285*D285 -> 7286660.7 | I285: =F285*D285 -> 0 | J285: =G285*D285 -> 7286660.7 | K285: =J285/$J$332 -> 0.02398376 | M285: 0 | N285: =G285+L285+M285 -> 5145.9468 | O285: =N285*D285 -> 7286660.7 | P285: =T285/D285 -> 6947.4576 | Q285: 21250 | R285: =Q285-P285 -> 14302.542 | S285: =R285/Q285 -> 0.67306082 | T285: 9837600 | U285: =O285/T285 -> 0.74069496
A286: =VLOOKUP(B286,Grupos!$A$2:$B$619,2,FALSE) -> BREAKERS | B286: ITM130NG | C286: INTERRUPTOR TERMOMAGNETICO 1P 30 AMP NEGRO | D286: 1980 | E286: 5212.9902 | G286: =E286+F286 -> 5212.9902 | H286: =E286*D286 -> 10321721 | I286: =F286*D286 -> 0 | J286: =G286*D286 -> 10321721 | K286: =J286/$J$332 -> 0.033973541 | M286: 0 | N286: =G286+L286+M286 -> 5212.9902 | O286: =N286*D286 -> 10321721 | P286: =T286/D286 -> 6948.4848 | Q286: 21250 | R286: =Q286-P286 -> 14301.515 | S286: =R286/Q286 -> 0.67301248 | T286: 13758000 | U286: =O286/T286 -> 0.75023408
A287: =VLOOKUP(B287,Grupos!$A$2:$B$619,2,FALSE) -> BREAKERS | B287: ITM140 | C287: INTERRUPTOR TERMOMAGNETICO 1P 40 AMP BLANCO | D287: 1440 | E287: 5470.1009 | G287: =E287+F287 -> 5470.1009 | H287: =E287*D287 -> 7876945.4 | I287: =F287*D287 -> 0 | J287: =G287*D287 -> 7876945.4 | K287: =J287/$J$332 -> 0.025926659 | M287: 0 | N287: =G287+L287+M287 -> 5470.1009 | O287: =N287*D287 -> 7876945.4 | P287: =T287/D287 -> 6975.4167 | Q287: 21250 | R287: =Q287-P287 -> 14274.583 | S287: =R287/Q287 -> 0.6717451 | T287: 10044600 | U287: =O287/T287 -> 0.78419702
A288: =VLOOKUP(B288,Grupos!$A$2:$B$619,2,FALSE) -> BREAKERS | B288: ITM140NG | C288: INTERRUPTOR TERMOMAGNETICO 1P 40 AMP NEGRO | D288: 1128 | E288: 5541.3675 | G288: =E288+F288 -> 5541.3675 | H288: =E288*D288 -> 6250662.5 | I288: =F288*D288 -> 0 | J288: =G288*D288 -> 6250662.5 | K288: =J288/$J$332 -> 0.020573812 | M288: 0 | N288: =G288+L288+M288 -> 5541.3675 | O288: =N288*D288 -> 6250662.5 | P288: =T288/D288 -> 6934.5745 | Q288: 21250 | R288: =Q288-P288 -> 14315.426 | S288: =R288/Q288 -> 0.67366708 | T288: 7822200 | U288: =O288/T288 -> 0.79909265
A289: =VLOOKUP(B289,Grupos!$A$2:$B$619,2,FALSE) -> BREAKERS | B289: ITM150 | C289: INTERRUPTOR TERMOMAGNETICO 1P 50 AMP BLANCO | D289: 312 | E289: 6052.9657 | G289: =E289+F289 -> 6052.9657 | H289: =E289*D289 -> 1888525.3 | I289: =F289*D289 -> 0 | J289: =G289*D289 -> 1888525.3 | K289: =J289/$J$332 -> 0.0062160074 | M289: 0 | N289: =G289+L289+M289 -> 6052.9657 | O289: =N289*D289 -> 1888525.3 | P289: =T289/D289 -> 6990.3846 | Q289: 21250 | R289: =Q289-P289 -> 14259.615 | S289: =R289/Q289 -> 0.67104072 | T289: 2181000 | U289: =O289/T289 -> 0.86589881
A290: =VLOOKUP(B290,Grupos!$A$2:$B$619,2,FALSE) -> BREAKERS | B290: ITM150NG | C290: INTERRUPTOR TERMOMAGNETICO 1P 50 AMP NEGRO | D290: 252 | E290: 5541.3675 | G290: =E290+F290 -> 5541.3675 | H290: =E290*D290 -> 1396424.6 | I290: =F290*D290 -> 0 | J290: =G290*D290 -> 1396424.6 | K290: =J290/$J$332 -> 0.0045962772 | M290: 0 | N290: =G290+L290+M290 -> 5541.3675 | O290: =N290*D290 -> 1396424.6 | P290: =T290/D290 -> 6916.6667 | Q290: 21250 | R290: =Q290-P290 -> 14333.333 | S290: =R290/Q290 -> 0.6745098 | T290: 1743000 | U290: =O290/T290 -> 0.80116156
A291: =VLOOKUP(B291,Grupos!$A$2:$B$619,2,FALSE) -> BREAKERS | B291: ITM160 | C291: INTERRUPTOR TERMOMAGNETICO 1P 60 AMP BLANCO | D291: 96 | E291: 6066.47 | G291: =E291+F291 -> 6066.47 | H291: =E291*D291 -> 582381.12 | I291: =F291*D291 -> 0 | J291: =G291*D291 -> 582381.12 | K291: =J291/$J$332 -> 0.0019168848 | M291: 0 | N291: =G291+L291+M291 -> 6066.47 | O291: =N291*D291 -> 582381.12 | P291: =T291/D291 -> 7143.75 | Q291: 21250 | R291: =Q291-P291 -> 14106.25 | S291: =R291/Q291 -> 0.66382353 | T291: 685800 | U291: =O291/T291 -> 0.84919965
A292: =VLOOKUP(B292,Grupos!$A$2:$B$619,2,FALSE) -> BREAKERS | B292: ITM160NG | C292: INTERRUPTOR TERMOMAGNETICO 1P 60 AMP NEGRO | D292: 156 | E292: 6093.0433 | G292: =E292+F292 -> 6093.0433 | H292: =E292*D292 -> 950514.76 | I292: =F292*D292 -> 0 | J292: =G292*D292 -> 950514.76 | K292: =J292/$J$332 -> 0.0031285823 | M292: 0 | N292: =G292+L292+M292 -> 6093.0433 | O292: =N292*D292 -> 950514.76 | P292: =T292/D292 -> 6950 | Q292: 21250 | R292: =Q292-P292 -> 14300 | S292: =R292/Q292 -> 0.67294118 | T292: 1084200 | U292: =O292/T292 -> 0.87669688
... A330: =VLOOKUP(B330,Grupos!$A$2:$B$619,2,FALSE) -> BREAKERS | B330: ITM-R363 | C330: INTERRUPTOR TERMOMAGNÉTICO 3P 63 AMP TIPO RIEL | D330: 8 | E330: 16739.136 | G330: =E330+F330 -> 16739.136 | H330: =E330*D330 -> 133913.09 | I330: =F330*D330 -> 0 | J330: =G330*D330 -> 133913.09 | K330: =J330/$J$332 -> 0.0004407697 | M330: 0 | N330: =G330+L330+M330 -> 16739.136 | O330: =N330*D330 -> 133913.09 | P330: =T330/D330 -> 19500 | Q330: 20150 | R330: =Q330-P330 -> 650 | S330: =R330/Q330 -> 0.032258065 | T330: 156000 | U330: =O330/T330 -> 0.85841721
A331: =VLOOKUP(B331,Grupos!$A$2:$B$619,2,FALSE) -> BREAKERS | B331: ITM-R150 | C331: INTERRUPTOR TERMOMAGNÉTICO 1P 50 AMP TIPO RIEL | D331: 36 | E331: 5579.7119 | G331: =E331+F331 -> 5579.7119 | H331: =E331*D331 -> 200869.63 | J331: =G331*D331 -> 200869.63 | K331: =J331/$J$332 -> 0.00066115455 | N331: =G331+L331+M331 -> 5579.7119 | O331: =N331*D331 -> 200869.63 | T331: 238800 | U331: =O331/T331 -> 0.8411626
A332: TOTAL BREAKERS | D332: =SUM(D281:D331) -> 47066 | H332: =SUM(H281:H331) -> 3.0381645e+08 | I332: =SUM(I281:I331) -> 0 | J332: =SUM(J281:J331) -> 3.0381645e+08 | K332: =J332/$J$332 -> 1 | O332: =SUM(O281:O331) -> 3.0381645e+08 | T332: =SUM(T281:T331) -> 4.0809076e+08 | U332: =O332/T332 -> 0.74448255 | V332: =T332/$T$346 -> 0.078680553
A333: =VLOOKUP(B333,Grupos!$A$2:$B$619,2,FALSE) -> VARILLAS | B333: VCU C-120 | C333: VARILLA COBRE 5/8 X 120 | D333: 218 | E333: 95000 | F333: 111.24 | G333: =E333+F333 -> 95111.24 | H333: =E333*D333 -> 20710000 | I333: =F333*D333 -> 24250.32 | J333: =G333*D333 -> 20734250 | K333: =J333/$J$345 -> 0.051560883 | M333: 488.87545 | N333: =G333+L333+M333 -> 95600.115 | O333: =N333*D333 -> 20840825 | P333: =T333/D333 -> 104094.95 | Q333: 0 | T333: 22692700 | U333: =O333/T333 -> 0.91839337
A334: =VLOOKUP(B334,Grupos!$A$2:$B$619,2,FALSE) -> VARILLAS | B334: VCU C-150 | C334: VARILLA COBRE 5/8 X 150 | D334: 225 | E334: 118600 | F334: 159.59 | G334: =E334+F334 -> 118759.59 | H334: =E334*D334 -> 26685000 | I334: =F334*D334 -> 35907.75 | J334: =G334*D334 -> 26720908 | K334: =J334/$J$345 -> 0.066448199 | M334: 701.36312 | N334: =G334+L334+M334 -> 119460.95 | O334: =N334*D334 -> 26878714 | P334: =T334/D334 -> 128978.44 | Q334: 0 | T334: 29020150 | U334: =O334/T334 -> 0.92620867
A335: =VLOOKUP(B335,Grupos!$A$2:$B$619,2,FALSE) -> VARILLAS | B335: VCU C-180 | C335: VARILLA COBRE 5/8 X 180 | D335: 236 | E335: 141854.27 | F335: 161.64 | G335: =E335+F335 -> 142015.91 | H335: =E335*D335 -> 33477607 | I335: =F335*D335 -> 38147.04 | J335: =G335*D335 -> 33515754 | K335: =J335/$J$345 -> 0.083345278 | M335: 710.37242 | N335: =G335+L335+M335 -> 142726.28 | O335: =N335*D335 -> 33683402 | P335: =T335/D335 -> 154385.17 | Q335: 0 | T335: 36434900 | U335: =O335/T335 -> 0.9244818
A336: =VLOOKUP(B336,Grupos!$A$2:$B$619,2,FALSE) -> VARILLAS | B336: VCU C-240 | C336: VARILLA COBRE 5/8 X 240 | D336: 1004 | E336: 189454.07 | F336: 98.86 | G336: =E336+F336 -> 189552.93 | H336: =E336*D336 -> 1.9021188e+08 | I336: =F336*D336 -> 99255.44 | J336: =G336*D336 -> 1.9031114e+08 | K336: =J336/$J$345 -> 0.47325609 | M336: 434.46806 | N336: =G336+L336+M336 -> 189987.39 | O336: =N336*D336 -> 1.9074734e+08 | P336: =T336/D336 -> 203147.41 | Q336: 0 | T336: 203960000 | U336: =O336/T336 -> 0.93521937
A337: =VLOOKUP(B337,Grupos!$A$2:$B$619,2,FALSE) -> VARILLAS | B337: VCU1/2-120 | C337: VARILLA COBRE 1/2 X 120 | D337: 479 | E337: 77904.762 | F337: 0 | G337: =E337+F337 -> 77904.762 | H337: =E337*D337 -> 37316381 | I337: =F337*D337 -> 0 | J337: =G337*D337 -> 37316381 | K337: =J337/$J$345 -> 0.092796485 | M337: 0 | N337: =G337+L337+M337 -> 77904.762 | O337: =N337*D337 -> 37316381 | P337: =T337/D337 -> 85486.117 | Q337: 0 | T337: 40947850 | U337: =O337/T337 -> 0.91131478
A338: =VLOOKUP(B338,Grupos!$A$2:$B$619,2,FALSE) -> VARILLAS | B338: VCU1/2-150 | C338: VARILLA COBRE 1/2 X 150 | D338: 260 | E338: 97900 | F338: 0 | G338: =E338+F338 -> 97900 | H338: =E338*D338 -> 25454000 | I338: =F338*D338 -> 0 | J338: =G338*D338 -> 25454000 | K338: =J338/$J$345 -> 0.063297717 | M338: 0 | N338: =G338+L338+M338 -> 97900 | O338: =N338*D338 -> 25454000 | P338: =T338/D338 -> 106793.6 | Q338: 0 | T338: 27766336 | U338: =O338/T338 -> 0.9167216
A339: =VLOOKUP(B339,Grupos!$A$2:$B$619,2,FALSE) -> VARILLAS | B339: VCU1/2-180 | C339: VARILLA COBRE 1/2 X 180 | D339: 173 | E339: 116800 | F339: 0 | G339: =E339+F339 -> 116800 | H339: =E339*D339 -> 20206400 | I339: =F339*D339 -> 0 | J339: =G339*D339 -> 20206400 | K339: =J339/$J$345 -> 0.050248251 | M339: 0 | N339: =G339+L339+M339 -> 116800 | O339: =N339*D339 -> 20206400 | P339: =T339/D339 -> 134899.51 | Q339: 0 | T339: 23337616 | U339: =O339/T339 -> 0.86582966
A340: =VLOOKUP(B340,Grupos!$A$2:$B$619,2,FALSE) -> VARILLAS | B340: VCU1/2-240 | C340: VARILLA COBRE 1/2 X 240 | D340: 240 | E340: 155900 | F340: 0 | G340: =E340+F340 -> 155900 | H340: =E340*D340 -> 37416000 | I340: =F340*D340 -> 0 | J340: =G340*D340 -> 37416000 | K340: =J340/$J$345 -> 0.093044212 | M340: 0 | N340: =G340+L340+M340 -> 155900 | O340: =N340*D340 -> 37416000 | P340: =T340/D340 -> 168550 | Q340: 0 | T340: 40452000 | U340: =O340/T340 -> 0.92494809
A341: =VLOOKUP(B341,Grupos!$A$2:$B$619,2,FALSE) -> VARILLAS | B341: VCU-E 120X1200 | C341: VARILLA ENCHAQUETADA 1/2 X 120 | D341: 130 | E341: 9215 | F341: 55.44 | G341: =E341+F341 -> 9270.44 | H341: =E341*D341 -> 1197950 | I341: =F341*D341 -> 7207.2 | J341: =G341*D341 -> 1205157.2 | K341: =J341/$J$345 -> 0.0029969238 | M341: 243.64666 | N341: =G341+L341+M341 -> 9514.0867 | O341: =N341*D341 -> 1236831.3 | P341: =T341/D341 -> 10819.231 | Q341: 0 | T341: 1406500 | U341: =O341/T341 -> 0.87936812
A342: =VLOOKUP(B342,Grupos!$A$2:$B$619,2,FALSE) -> VARILLAS | B342: VCU-E 120X1500 | C342: VARILLA ENCHAQUETADA 1/2 X 150 | D342: 450 | E342: 10379 | F342: 39.89 | G342: =E342+F342 -> 10418.89 | H342: =E342*D342 -> 4670550 | I342: =F342*D342 -> 17950.5 | J342: =G342*D342 -> 4688500.5 | K342: =J342/$J$345 -> 0.011659125 | M342: 175.30782 | N342: =G342+L342+M342 -> 10594.198 | O342: =N342*D342 -> 4767389 | P342: =T342/D342 -> 12160 | Q342: 0 | T342: 5472000 | U342: =O342/T342 -> 0.87123337
A343: =VLOOKUP(B343,Grupos!$A$2:$B$619,2,FALSE) -> VARILLAS | B343: VCU-E 120X1800 | C343: VARILLA ENCHAQUETADA 1/2 X 180 | D343: 120 | E343: 12125 | F343: 121.66 | G343: =E343+F343 -> 12246.66 | H343: =E343*D343 -> 1455000 | I343: =F343*D343 -> 14599.2 | J343: =G343*D343 -> 1469599.2 | K343: =J343/$J$345 -> 0.0036545248 | M343: 534.66907 | N343: =G343+L343+M343 -> 12781.329 | O343: =N343*D343 -> 1533759.5 | P343: =T343/D343 -> 13500 | Q343: 0 | T343: 1620000 | U343: =O343/T343 -> 0.94676512
A344: =VLOOKUP(B344,Grupos!$A$2:$B$619,2,FALSE) -> VARILLAS | B344: VCU-E 140X2400 | C344: VARILLA ENCHAQUETADA 5/8 X 240 | D344: 92 | E344: 33500 | F344: 123.04 | G344: =E344+F344 -> 33623.04 | H344: =E344*D344 -> 3082000 | I344: =F344*D344 -> 11319.68 | J344: =G344*D344 -> 3093319.7 | K344: =J344/$J$345 -> 0.0076923106 | M344: 540.73387 | N344: =G344+L344+M344 -> 34163.774 | O344: =N344*D344 -> 3143067.2 | P344: =T344/D344 -> 37300 | Q344: 0 | T344: 3431600 | U344: =O344/T344 -> 0.91591887
A345: TOTAL VARILLAS | D345: =SUM(D333:D344) -> 3627 | H345: =SUM(H333:H344) -> 4.0188277e+08 | I345: =SUM(I333:I344) -> 248637.13 | J345: =SUM(J333:J344) -> 4.0213141e+08 | K345: =J345/$J$345 -> 1 | O345: =SUM(O333:O344) -> 4.0322411e+08 | T345: =SUM(T333:T344) -> 4.3654165e+08 | U345: =O345/T345 -> 0.92367844 | V345: =T345/$T$346 -> 0.08416593
A346: TOTAL | D346: =SUM(D345,D332,D280,D277) -> 3035304.3 | H346: =SUM(H345,H332,H280,H277) -> 2.3435932e+09 | I346: =SUM(I345,I332,I280,I277) -> 1.1333136e+08 | J346: =SUM(J345,J332,J280,J277) -> 2.4569246e+09 | O346: =O345+O332+O280+O277 -> 3.5406061e+09 | T346: =T345+T332+T280+T277 -> 5.1866789e+09 | U346: =O346/T346 -> 0.68263453 | V346: =T346/$T$346 -> 1
A347: DESCUENTOS | O347: -7049530 | T347: -1.1222357e+08
A348: TOTAL SIN DESCUENTOS | D348: =D346+D347 -> 3035304.3 | H348: =H346+H347 -> 2.3435932e+09 | I348: =I346+I347 -> 1.1333136e+08 | J348: =J346+J347 -> 2.4569246e+09 | O348: =O346+O347 -> 3.5335565e+09 | T348: =T346+T347 -> 5.0744553e+09 | U348: =O348/T348 -> 0.69634204

Sheet Mar
A2: DETALLE DE VENTAS 2026
E3: COSTO SIT UNITARIO | H3: COSTO SIT CANTIDAD
A4: GRUPO | B4: REF. | C4: DESCRIPCION | D4: CANT | E4: CUMAT | F4: CUMO | G4: CUNago | H4: CTMAT | I4: CTMO | J4: CTSIT | K4: %PART | L4: CIFU | M4: MOU | N4: CTU | O4: CT | P4: PUV | Q4: PRECIOTOT | R4: %CTO | S4: %Part. | T4: MO Nago | U4: Dif | W4: MP Nago | X4: Dif
A5: =VLOOKUP(B5,Grupos!$A$2:$B$619,2,FALSE) -> ACCESORIOS | B5: 997 | C5: MAYOR VALOR COBRADO | D5: -3 | E5: 0 | F5: 0 | G5: =E5+F5 -> 0 | H5: =E5*D5 -> 0 | I5: =F5*D5 -> 0 | J5: =G5*D5 -> 0 | K5: =J5/$J$303 -> 0 | L5: =$K$373*K5/D5 -> 0 | M5: =F5*$M$372 -> 0 | N5: =G5+L5+M5 -> 0 | O5: =N5*D5 -> 0 | P5: =Q5/D5 -> 4288368.3 | Q5: -12865105 | R5: =O5/Q5 -> 0 | W5: =IFERROR(VLOOKUP(B5,[1]Todos!$A$2:$B$3021,2,FALSE),0) -> 0 | X5: =W5-E5 -> 0
A6: =VLOOKUP(B6,Grupos!$A$2:$B$619,2,FALSE) -> ACCESORIOS | B6: BN-18 | C6: BANDEJA PARA INTERIOR *I-18P,I-218,I-318 | D6: 1 | E6: 1902.46 | F6: 121.38 | G6: =E6+F6 -> 2023.84 | H6: =E6*D6 -> 1902.46 | I6: =F6*D6 -> 121.38 | J6: =G6*D6 -> 2023.84 | K6: =J6/$J$303 -> 1.2912583e-06 | L6: =$K$373*K6/D6 -> 577.5979 | M6: =F6*$M$372 -> 796.54573 | N6: =G6+L6+M6 -> 3397.9836 | O6: =N6*D6 -> 3397.9836 | P6: =Q6/D6 -> 10374 | Q6: 10374 | R6: =O6/Q6 -> 0.32754807 | T6: =IFERROR(VLOOKUP(B6,[1]Todos!$A$2:$C$3021,3,FALSE),0) -> 0 | U6: =T6-F6 -> -121.38 | W6: =IFERROR(VLOOKUP(B6,[1]Todos!$A$2:$B$3021,2,FALSE),0) -> 0 | X6: =W6-E6 -> -1902.46
A7: =VLOOKUP(B7,Grupos!$A$2:$B$619,2,FALSE) -> ACCESORIOS | B7: BN-24 | C7: BANDEJA PARA INTERIOR *I-224,I-324* | D7: 1 | E7: 2116.58 | F7: 79.18 | G7: =E7+F7 -> 2195.76 | H7: =E7*D7 -> 2116.58 | I7: =F7*D7 -> 79.18 | J7: =G7*D7 -> 2195.76 | K7: =J7/$J$303 -> 1.4009473e-06 | L7: =$K$373*K7/D7 -> 626.66336 | M7: =F7*$M$372 -> 519.61189 | N7: =G7+L7+M7 -> 3342.0352 | O7: =N7*D7 -> 3342.0352 | P7: =Q7/D7 -> 26700 | Q7: 26700 | R7: =O7/Q7 -> 0.12516986 | T7: =IFERROR(VLOOKUP(B7,[1]Todos!$A$2:$C$3021,3,FALSE),0) -> 0 | U7: =T7-F7 -> -79.18 | W7: =IFERROR(VLOOKUP(B7,[1]Todos!$A$2:$B$3021,2,FALSE),0) -> 0 | X7: =W7-E7 -> -2116.58
A8: =VLOOKUP(B8,Grupos!$A$2:$B$619,2,FALSE) -> ACCESORIOS | B8: BN-36 | C8: BANDEJA PARA INTERIOR *I-236,I-336* | D8: 1 | E8: 2926.65 | F8: 152.8 | G8: =E8+F8 -> 3079.45 | H8: =E8*D8 -> 2926.65 | I8: =F8*D8 -> 152.8 | J8: =G8*D8 -> 3079.45 | K8: =J8/$J$303 -> 1.9647627e-06 | L8: =$K$373*K8/D8 -> 878.86585 | M8: =F8*$M$372 -> 1002.7368 | N8: =G8+L8+M8 -> 4961.0526 | O8: =N8*D8 -> 4961.0526 | P8: =Q8/D8 -> 20580 | Q8: 20580 | R8: =O8/Q8 -> 0.24106184 | T8: =IFERROR(VLOOKUP(B8,[1]Todos!$A$2:$C$3021,3,FALSE),0) -> 0 | U8: =T8-F8 -> -152.8 | W8: =IFERROR(VLOOKUP(B8,[1]Todos!$A$2:$B$3021,2,FALSE),0) -> 0 | X8: =W8-E8 -> -2926.65
A9: =VLOOKUP(B9,Grupos!$A$2:$B$619,2,FALSE) -> ACCESORIOS | B9: BNTOTA | C9: BANDEJA PARA TOTALIZADOR | D9: 1 | E9: 1927.16 | F9: 63.69 | G9: =E9+F9 -> 1990.85 | H9: =E9*D9 -> 1927.16 | I9: =F9*D9 -> 63.69 | J9: =G9*D9 -> 1990.85 | K9: =J9/$J$303 -> 1.2702099e-06 | L9: =$K$373*K9/D9 -> 568.18265 | M9: =F9*$M$372 -> 417.96011 | N9: =G9+L9+M9 -> 2976.9928 | O9: =N9*D9 -> 2976.9928 | P9: =Q9/D9 -> 17218.5 | Q9: 17218.5 | R9: =O9/Q9 -> 0.17289501 | T9: =IFERROR(VLOOKUP(B9,[1]Todos!$A$2:$C$3021,3,FALSE),0) -> 67 | U9: =T9-F9 -> 3.31 | W9: =IFERROR(VLOOKUP(B9,[1]Todos!$A$2:$B$3021,2,FALSE),0) -> 1927.16 | X9: =W9-E9 -> 0
A10: =VLOOKUP(B10,Grupos!$A$2:$B$619,2,FALSE) -> ACCESORIOS | B10: CIERRE | C10: CIERRE DE TRINQUETE | D10: 15 | E10: 68.15 | F10: 12.36 | G10: =E10+F10 -> 80.51 | H10: =E10*D10 -> 1022.25 | I10: =F10*D10 -> 185.4 | J10: =G10*D10 -> 1207.65 | K10: =J10/$J$303 -> 7.7050955e-07 | L10: =$K$373*K10/D10 -> 22.977314 | M10: =F10*$M$372 -> 81.111429 | N10: =G10+L10+M10 -> 184.59874 | O10: =N10*D10 -> 2768.9811 | P10: =Q10/D10 -> 2887.5 | Q10: 43312.5 | R10: =O10/Q10 -> 0.063930301 | T10: =IFERROR(VLOOKUP(B10,[1]Todos!$A$2:$C$3021,3,FALSE),0) -> 12.51 | U10: =T10-F10 -> 0.15 | W10: =IFERROR(VLOOKUP(B10,[1]Todos!$A$2:$B$3021,2,FALSE),0) -> 68.15 | X10: =W10-E10 -> 0
A11: =VLOOKUP(B11,Grupos!$A$2:$B$619,2,FALSE) -> ACCESORIOS | B11: GRAPAM12-D | C11: GRAPA METALICA 1/2" DOBLE | D11: 8400 | E11: 55.77 | F11: 28.94 | G11: =E11+F11 -> 84.71 | H11: =E11*D11 -> 468468 | I11: =F11*D11 -> 243096 | J11: =G11*D11 -> 711564 | K11: =J11/$J$303 -> 0.00045399483 | L11: =$K$373*K11/D11 -> 24.175981 | M11: =F11*$M$372 -> 189.91624 | N11: =G11+L11+M11 -> 298.80222 | O11: =N11*D11 -> 2509938.7 | P11: =Q11/D11 -> 125.48571 | Q11: 1054080 | R11: =O11/Q11 -> 2.3811653 | T11: =IFERROR(VLOOKUP(B11,[1]Todos!$A$2:$C$3021,3,FALSE),0) -> 29.35 | U11: =T11-F11 -> 0.41 | W11: =IFERROR(VLOOKUP(B11,[1]Todos!$A$2:$B$3021,2,FALSE),0) -> 55.77 | X11: =W11-E11 -> 0
A12: =VLOOKUP(B12,Grupos!$A$2:$B$619,2,FALSE) -> ACCESORIOS | B12: GRAPAM12-S | C12: GRAPA METALICA 1/2" SENCILLA | D12: 8400 | E12: 40.38 | F12: 44.51 | G12: =E12+F12 -> 84.89 | H12: =E12*D12 -> 339192 | I12: =F12*D12 -> 373884 | J12: =G12*D12 -> 713076 | K12: =J12/$J$303 -> 0.00045495952 | L12: =$K$373*K12/D12 -> 24.227353 | M12: =F12*$M$372 -> 292.09302 | N12: =G12+L12+M12 -> 401.21037 | O12: =N12*D12 -> 3370167.1 | P12: =Q12/D12 -> 106.78572 | Q12: 897000.03 | R12: =O12/Q12 -> 3.7571539 | T12: =IFERROR(VLOOKUP(B12,[1]Todos!$A$2:$C$3021,3,FALSE),0) -> 44.51 | U12: =T12-F12 -> 0 | W12: =IFERROR(VLOOKUP(B12,[1]Todos!$A$2:$B$3021,2,FALSE),0) -> 40.38 | X12: =W12-E12 -> 0
A13: =VLOOKUP(B13,Grupos!$A$2:$B$619,2,FALSE) -> ACCESORIOS | B13: NEUTRO18 | C13: NEUTRO DE 18 CIRCUITOS | D13: 1 | E13: 3042.06 | F13: 0 | G13: =E13+F13 -> 3042.06 | H13: =E13*D13 -> 3042.06 | I13: =F13*D13 -> 0 | J13: =G13*D13 -> 3042.06 | K13: =J13/$J$303 -> 1.9409069e-06 | L13: =$K$373*K13/D13 -> 868.19485 | M13: =F13*$M$372 -> 0 | N13: =G13+L13+M13 -> 3910.2549 | O13: =N13*D13 -> 3910.2549 | P13: =Q13/D13 -> 32812.5 | Q13: 32812.5 | R13: =O13/Q13 -> 0.11916967 | T13: =IFERROR(VLOOKUP(B13,[1]Todos!$A$2:$C$3021,3,FALSE),0) -> 0 | U13: =T13-F13 -> 0 | W13: =IFERROR(VLOOKUP(B13,[1]Todos!$A$2:$B$3021,2,FALSE),0) -> 3042.06 | X13: =W13-E13 -> 0
A14: =VLOOKUP(B14,Grupos!$A$2:$B$619,2,FALSE) -> ACCESORIOS | B14: NEUTRO18RALET | C14: NEUTRO 18 CIRCUITOS RALET | D14: 412 | E14: 4402 | F14: 0 | G14: =E14+F14 -> 4402 | H14: =E14*D14 -> 1813624 | I14: =F14*D14 -> 0 | J14: =G14*D14 -> 1813624 | K14: =J14/$J$303 -> 0.0011571354 | L14: =$K$373*K14/D14 -> 1256.3177 | M14: =F14*$M$372 -> 0 | N14: =G14+L14+M14 -> 5658.3177 | O14: =N14*D14 -> 2331226.9 | P14: =Q14/D14 -> 30000 | Q14: 12360000 | R14: =O14/Q14 -> 0.18861059 | T14: =IFERROR(VLOOKUP(B14,[1]Todos!$A$2:$C$3021,3,FALSE),0) -> 0 | U14: =T14-F14 -> 0 | W14: =IFERROR(VLOOKUP(B14,[1]Todos!$A$2:$B$3021,2,FALSE),0) -> 4402 | X14: =W14-E14 -> 0
A15: =VLOOKUP(B15,Grupos!$A$2:$B$619,2,FALSE) -> ACCESORIOS | B15: NEUTRO36R | C15: NEUTRO DE 36 CIRCUITOS REFORZADO | D15: 1 | E15: 13631.16 | F15: 0 | G15: =E15+F15 -> 13631.16 | H15: =E15*D15 -> 13631.16 | I15: =F15*D15 -> 0 | J15: =G15*D15 -> 13631.16 | K15: =J15/$J$303 -> 8.6970057e-06 | L15: =$K$373*K15/D15 -> 3890.2924 | M15: =F15*$M$372 -> 0 | N15: =G15+L15+M15 -> 17521.452 | O15: =N15*D15 -> 17521.452 | P15: =Q15/D15 -> 39280 | Q15: 39280 | R15: =O15/Q15 -> 0.44606549 | T15: =IFERROR(VLOOKUP(B15,[1]Todos!$A$2:$C$3021,3,FALSE),0) -> 0 | U15: =T15-F15 -> 0 | W15: =IFERROR(VLOOKUP(B15,[1]Todos!$A$2:$B$3021,2,FALSE),0) -> 13631.16 | X15: =W15-E15 -> 0
A16: =VLOOKUP(B16,Grupos!$A$2:$B$619,2,FALSE) -> ACCESORIOS | B16: NEUTRO6 | C16: NEUTRO DE 6 CIRCUITOS | D16: 49 | E16: 1229.39 | F16: 0 | G16: =E16+F16 -> 1229.39 | H16: =E16*D16 -> 60240.11 | I16: =F16*D16 -> 0 | J16: =G16*D16 -> 60240.11 | K16: =J16/$J$303 -> 3.8434629e-05 | L16: =$K$373*K16/D16 -> 350.86424 | M16: =F16*$M$372 -> 0 | N16: =G16+L16+M16 -> 1580.2542 | O16: =N16*D16 -> 77432.458 | P16: =Q16/D16 -> 6159.9996 | Q16: 301839.98 | R16: =O16/Q16 -> 0.2565348 | T16: =IFERROR(VLOOKUP(B16,[1]Todos!$A$2:$C$3021,3,FALSE),0) -> 0 | U16: =T16-F16 -> 0 | W16: =IFERROR(VLOOKUP(B16,[1]Todos!$A$2:$B$3021,2,FALSE),0) -> 1229.39 | X16: =W16-E16 -> 0
A17: =VLOOKUP(B17,Grupos!$A$2:$B$619,2,FALSE) -> ACCESORIOS | B17: NEUTRO8 | C17: NEUTRO DE 8 CIRCUITOS | D17: 13 | E17: 1583.66 | F17: 0 | G17: =E17+F17 -> 1583.66 | H17: =E17*D17 -> 20587.58 | I17: =F17*D17 -> 0 | J17: =G17*D17 -> 20587.58 | K17: =J17/$J$303 -> 1.3135368e-05 | L17: =$K$373*K17/D17 -> 451.97184 | M17: =F17*$M$372 -> 0 | N17: =G17+L17+M17 -> 2035.6318 | O17: =N17*D17 -> 26463.214 | P17: =Q17/D17 -> 9240 | Q17: 120120 | R17: =O17/Q17 -> 0.22030648 | T17: =IFERROR(VLOOKUP(B17,[1]Todos!$A$2:$C$3021,3,FALSE),0) -> 0 | U17: =T17-F17 -> 0 | W17: =IFERROR(VLOOKUP(B17,[1]Todos!$A$2:$B$3021,2,FALSE),0) -> 1583.66 | X17: =W17-E17 -> 0
... A42: =VLOOKUP(B42,Grupos!$A$2:$B$619,2,FALSE) -> ACCESORIOS | B42: TIERRA8ALET | C42: TIERRA 8 CIRCUITOS ALET | D42: 35 | E42: 1201 | F42: 0 | G42: =E42+F42 -> 1201 | H42: =E42*D42 -> 42035 | I42: =F42*D42 -> 0 | J42: =G42*D42 -> 42035 | K42: =J42/$J$303 -> 2.6819334e-05 | L42: =$K$373*K42/D42 -> 342.76182 | M42: =F42*$M$372 -> 0 | N42: =G42+L42+M42 -> 1543.7618 | O42: =N42*D42 -> 54031.664 | P42: =Q42/D42 -> 8799.9994 | Q42: 307999.98 | R42: =O42/Q42 -> 0.17542749 | T42: =IFERROR(VLOOKUP(B42,[1]Todos!$A$2:$C$3021,3,FALSE),0) -> 0 | U42: =T42-F42 -> 0 | W42: =IFERROR(VLOOKUP(B42,[1]Todos!$A$2:$B$3021,2,FALSE),0) -> 1201 | X42: =W42-E42 -> 0
A43: Total ACCESORIOS | D43: =SUBTOTAL(9,D5:D42) -> 18136 | H43: =SUBTOTAL(9,H5:H42) -> 3814624.3 | I43: =SUBTOTAL(9,I5:I42) -> 631004.79 | J43: =SUBTOTAL(9,J5:J42) -> 4445629.1 | O43: =SUBTOTAL(9,O5:O42) -> 9855312.7 | Q43: =SUBTOTAL(9,Q5:Q42) -> 8490650.5 | R43: =O43/Q43 -> 1.1607253 | S43: =Q43/$Q$303 -> 0.0021210773 | T43: =IFERROR(VLOOKUP(B43,[1]Todos!$A$2:$C$3021,3,FALSE),0) -> 0 | U43: =T43-F43 -> 0 | W43: =IFERROR(VLOOKUP(B43,[1]Todos!$A$2:$B$3021,2,FALSE),0) -> 0 | X43: =W43-E43 -> 0
A44: =VLOOKUP(B44,Grupos!$A$2:$B$619,2,FALSE) -> ADAPTADORES | B44: ACAMPANA12 | C44: ADAPTADOR CAMPANA 1/2" | D44: 6400 | E44: 15.04 | F44: 4.49 | G44: =E44+F44 -> 19.53 | H44: =E44*D44 -> 96256 | I44: =F44*D44 -> 28736 | J44: =G44*D44 -> 124992 | K44: =J44/$J$303 -> 7.9747882e-05 | L44: =$K$373*K44/D44 -> 5.5738038 | M44: =F44*$M$372 -> 29.465236 | N44: =G44+L44+M44 -> 54.56904 | O44: =N44*D44 -> 349241.85 | P44: =Q44/D44 -> 91.875002 | Q44: 588000.01 | R44: =O44/Q44 -> 0.59394872 | T44: =IFERROR(VLOOKUP(B44,[1]Todos!$A$2:$C$3021,3,FALSE),0) -> 4.85 | U44: =T44-F44 -> 0.36 | W44: =IFERROR(VLOOKUP(B44,[1]Todos!$A$2:$B$3021,2,FALSE),0) -> 15.04 | X44: =W44-E44 -> 0
A45: =VLOOKUP(B45,Grupos!$A$2:$B$619,2,FALSE) -> ADAPTADORES | B45: ACAMPANA34 | C45: ADAPTADOR CAMPANA 3/4" | D45: 1000 | E45: 20.18 | F45: 4.9 | G45: =E45+F45 -> 25.08 | H45: =E45*D45 -> 20180 | I45: =F45*D45 -> 4900 | J45: =G45*D45 -> 25080 | K45: =J45/$J$303 -> 1.6001639e-05 | L45: =$K$373*K45/D45 -> 7.1577572 | M45: =F45*$M$372 -> 32.155825 | N45: =G45+L45+M45 -> 64.393583 | O45: =N45*D45 -> 64393.583 | P45: =Q45/D45 -> 105.00001 | Q45: 105000.01 | R45: =O45/Q45 -> 0.61327216 | T45: =IFERROR(VLOOKUP(B45,[1]Todos!$A$2:$C$3021,3,FALSE),0) -> 4.9 | U45: =T45-F45 -> 0 | W45: =IFERROR(VLOOKUP(B45,[1]Todos!$A$2:$B$3021,2,FALSE),0) -> 20.18 | X45: =W45-E45 -> 0
A46: =VLOOKUP(B46,Grupos!$A$2:$B$619,2,FALSE) -> ADAPTADORES | B46: ADAPTER12 | C46: ADAPTADOR TERMINAL 1/2" | D46: 145200 | E46: 26.11 | F46: 10.44 | G46: =E46+F46 -> 36.55 | H46: =E46*D46 -> 3791172 | I46: =F46*D46 -> 1515888 | J46: =G46*D46 -> 5307060 | K46: =J46/$J$303 -> 0.0033860311 | L46: =$K$373*K46/D46 -> 10.431261 | M46: =F46*$M$372 -> 68.511596 | N46: =G46+L46+M46 -> 115.49286 | O46: =N46*D46 -> 16769563 | P46: =Q46/D46 -> 106.23968 | Q46: 15426001 | R46: =O46/Q46 -> 1.0870972 | T46: =IFERROR(VLOOKUP(B46,[1]Todos!$A$2:$C$3021,3,FALSE),0) -> 10.32 | U46: =T46-F46 -> -0.12 | W46: =IFERROR(VLOOKUP(B46,[1]Todos!$A$2:$B$3021,2,FALSE),0) -> 26.12 | X46: =W46-E46 -> 0.01
A47: =VLOOKUP(B47,Grupos!$A$2:$B$619,2,FALSE) -> ADAPTADORES | B47: ADAPTER12-AI | C47: ADAPTADOR TERMINAL 1/2" ALTO IMPACTO | D47: 31200 | E47: 55.65 | F47: 10.51 | G47: =E47+F47 -> 66.16 | H47: =E47*D47 -> 1736280 | I47: =F47*D47 -> 327912 | J47: =G47*D47 -> 2064192 | K47: =J47/$J$303 -> 0.0013170038 | L47: =$K$373*K47/D47 -> 18.881867 | M47: =F47*$M$372 -> 68.970964 | N47: =G47+L47+M47 -> 154.01283 | O47: =N47*D47 -> 4805200.3 | P47: =Q47/D47 -> 164.38845 | Q47: 5128919.8 | R47: =O47/Q47 -> 0.9368835 | T47: =IFERROR(VLOOKUP(B47,[1]Todos!$A$2:$C$3021,3,FALSE),0) -> 10.6 | U47: =T47-F47 -> 0.09 | W47: =IFERROR(VLOOKUP(B47,[1]Todos!$A$2:$B$3021,2,FALSE),0) -> 55.65 | X47: =W47-E47 -> 0
A48: =VLOOKUP(B48,Grupos!$A$2:$B$619,2,FALSE) -> ADAPTADORES | B48: ADAPTER12-PP-SE | C48: ADAPTADOR TERMINAL 1/2" EN POLIPROPILENO SIN ENSAMBLE | D48: 738900 | E48: 27.67 | F48: 5.04 | G48: =E48+F48 -> 32.71 | H48: =E48*D48 -> 20445363 | I48: =F48*D48 -> 3724056 | J48: =G48*D48 -> 24169419 | K48: =J48/$J$303 -> 0.015420667 | L48: =$K$373*K48/D48 -> 9.3353365 | M48: =F48*$M$372 -> 33.074563 | N48: =G48+L48+M48 -> 75.1199 | O48: =N48*D48 -> 55506094 | P48: =Q48/D48 -> 104.57613 | Q48: 77271301 | R48: =O48/Q48 -> 0.71832741 | T48: =IFERROR(VLOOKUP(B48,[1]Todos!$A$2:$C$3021,3,FALSE),0) -> 5.37 | U48: =T48-F48 -> 0.33 | W48: =IFERROR(VLOOKUP(B48,[1]Todos!$A$2:$B$3021,2,FALSE),0) -> 27.67 | X48: =W48-E48 -> 0
A49: =VLOOKUP(B49,Grupos!$A$2:$B$619,2,FALSE) -> ADAPTADORES | B49: ADAPTER34 | C49: ADAPTADOR TERMINAL 3/4" | D49: 190400 | E49: 41.81 | F49: 10.85 | G49: =E49+F49 -> 52.66 | H49: =E49*D49 -> 7960624 | I49: =F49*D49 -> 2065840 | J49: =G49*D49 -> 10026464 | K49: =J49/$J$303 -> 0.0063971235 | L49: =$K$373*K49/D49 -> 15.029007 | M49: =F49*$M$372 -> 71.202185 | N49: =G49+L49+M49 -> 138.89119 | O49: =N49*D49 -> 26444883 | P49: =Q49/D49 -> 139.9832 | Q49: 26652801 | R49: =O49/Q49 -> 0.99219903 | T49: =IFERROR(VLOOKUP(B49,[1]Todos!$A$2:$C$3021,3,FALSE),0) -> 11.11 | U49: =T49-F49 -> 0.26 | W49: =IFERROR(VLOOKUP(B49,[1]Todos!$A$2:$B$3021,2,FALSE),0) -> 41.81 | X49: =W49-E49 -> 0
A50: =VLOOKUP(B50,Grupos!$A$2:$B$619,2,FALSE) -> ADAPTADORES | B50: ADAPTER34-AI | C50: ADAPTADOR TERMINAL 3/4'' ALTO IMPACTO | D50: 1600 | E50: 73.07 | F50: 2.75 | G50: =E50+F50 -> 75.82 | H50: =E50*D50 -> 116912 | I50: =F50*D50 -> 4400 | J50: =G50*D50 -> 121312 | K50: =J50/$J$303 -> 7.7399954e-05 | L50: =$K$373*K50/D50 -> 21.638802 | M50: =F50*$M$372 -> 18.046637 | N50: =G50+L50+M50 -> 115.50544 | O50: =N50*D50 -> 184808.7 | P50: =Q50/D50 -> 211 | Q50: 337600 | R50: =O50/Q50 -> 0.54741914 | T50: =IFERROR(VLOOKUP(B50,[1]Todos!$A$2:$C$3021,3,FALSE),0) -> 2.75 | U50: =T50-F50 -> 0 | W50: =IFERROR(VLOOKUP(B50,[1]Todos!$A$2:$B$3021,2,FALSE),0) -> 73.07 | X50: =W50-E50 -> 0
A51: Total ADAPTADORES | D51: =SUBTOTAL(9,D44:D50) -> 1114700 | H51: =SUBTOTAL(9,H44:H50) -> 34166787 | I51: =SUBTOTAL(9,I44:I50) -> 7671732 | J51: =SUBTOTAL(9,J44:J50) -> 41838519 | O51: =SUBTOTAL(9,O44:O50) -> 1.0412418e+08 | Q51: =SUBTOTAL(9,Q44:Q50) -> 1.2550962e+08 | R51: =O51/Q51 -> 0.82961116 | S51: =Q51/$Q$303 -> 0.031353972 | T51: =IFERROR(VLOOKUP(B51,[1]Todos!$A$2:$C$3021,3,FALSE),0) -> 0 | U51: =T51-F51 -> 0 | W51: =IFERROR(VLOOKUP(B51,[1]Todos!$A$2:$B$3021,2,FALSE),0) -> 0 | X51: =W51-E51 -> 0
A52: =VLOOKUP(B52,Grupos!$A$2:$B$619,2,FALSE) -> CAJAS ARRANCADORAS | B52: CA-30 | C52: CAJA ARRANCADOR Y CONTROL INDUSTRIAL 30X20X16 | D52: 19 | E52: 30398.83 | F52: 4300.86 | G52: =E52+F52 -> 34699.69 | H52: =E52*D52 -> 577577.77 | I52: =F52*D52 -> 81716.34 | J52: =G52*D52 -> 659294.11 | K52: =J52/$J$303 -> 0.00042064539 | L52: =$K$373*K52/D52 -> 9903.1881 | M52: =F52*$M$372 -> 28224.021 | N52: =G52+L52+M52 -> 72826.899 | O52: =N52*D52 -> 1383711.1 | P52: =Q52/D52 -> 106235.68 | Q52: 2018477.9 | R52: =O52/Q52 -> 0.68552204 | T52: =IFERROR(VLOOKUP(B52,[1]Todos!$A$2:$C$3021,3,FALSE),0) -> 4472.47 | U52: =T52-F52 -> 171.61 | W52: =IFERROR(VLOOKUP(B52,[1]Todos!$A$2:$B$3021,2,FALSE),0) -> 30398.83 | X52: =W52-E52 -> 0
A53: =VLOOKUP(B53,Grupos!$A$2:$B$619,2,FALSE) -> CAJAS ARRANCADORAS | B53: CA-40 | C53: CAJA ARRANCADOR Y CONTROL INDUSTRIAL 40X30X20 | D53: 10 | E53: 40781.56 | F53: 5815.83 | G53: =E53+F53 -> 46597.39 | H53: =E53*D53 -> 407815.6 | I53: =F53*D53 -> 58158.3 | J53: =G53*D53 -> 465973.9 | K53: =J53/$J$303 -> 0.00029730248 | L53: =$K$373*K53/D53 -> 13298.756 | M53: =F53*$M$372 -> 38165.881 | N53: =G53+L53+M53 -> 98062.027 | O53: =N53*D53 -> 980620.27 | P53: =Q53/D53 -> 160165 | Q53: 1601650 | R53: =O53/Q53 -> 0.61225629 | T53: =IFERROR(VLOOKUP(B53,[1]Todos!$A$2:$C$3021,3,FALSE),0) -> 5353.18 | U53: =T53-F53 -> -462.65 | W53: =IFERROR(VLOOKUP(B53,[1]Todos!$A$2:$B$3021,2,FALSE),0) -> 40781.56 | X53: =W53-E53 -> 0
A54: =VLOOKUP(B54,Grupos!$A$2:$B$619,2,FALSE) -> CAJAS ARRANCADORAS | B54: CA-60 | C54: CAJA ARRANCADOR Y CONTROL INDUSTRIAL 60X40X25 | D54: 1 | E54: 62538.51 | F54: 4746.81 | G54: =E54+F54 -> 67285.32 | H54: =E54*D54 -> 62538.51 | I54: =F54*D54 -> 4746.81 | J54: =G54*D54 -> 67285.32 | K54: =J54/$J$303 -> 4.2929641e-05 | L54: =$K$373*K54/D54 -> 19203.03 | M54: =F54*$M$372 -> 31150.529 | N54: =G54+L54+M54 -> 117638.88 | O54: =N54*D54 -> 117638.88 | P54: =Q54/D54 -> 279539.99 | Q54: 279539.99 | R54: =O54/Q54 -> 0.42083023 | T54: =IFERROR(VLOOKUP(B54,[1]Todos!$A$2:$C$3021,3,FALSE),0) -> 5265.73 | U54: =T54-F54 -> 518.92 | W54: =IFERROR(VLOOKUP(B54,[1]Todos!$A$2:$B$3021,2,FALSE),0) -> 62538.51 | X54: =W54-E54 -> 0
A55: =VLOOKUP(B55,Grupos!$A$2:$B$619,2,FALSE) -> CAJAS ARRANCADORAS | B55: CA-70 | C55: CAJA ARRANCADOR Y CONTROL INDUSTRIAL 70X50X25 | D55: 5 | E55: 78390.9 | F55: 7027.37 | G55: =E55+F55 -> 85418.27 | H55: =E55*D55 -> 391954.5 | I55: =F55*D55 -> 35136.85 | J55: =G55*D55 -> 427091.35 | K55: =J55/$J$303 -> 0.00027249448 | L55: =$K$373*K55/D55 -> 24378.12 | M55: =F55*$M$372 -> 46116.507 | N55: =G55+L55+M55 -> 155912.9 | O55: =N55*D55 -> 779564.48 | P55: =Q55/D55 -> 311689.6 | Q55: 1558448 | R55: =O55/Q55 -> 0.50021847 | T55: =IFERROR(VLOOKUP(B55,[1]Todos!$A$2:$C$3021,3,FALSE),0) -> 7236.18 | U55: =T55-F55 -> 208.81 | W55: =IFERROR(VLOOKUP(B55,[1]Todos!$A$2:$B$3021,2,FALSE),0) -> 78390.9 | X55: =W55-E55 -> 0
A56: =VLOOKUP(B56,Grupos!$A$2:$B$619,2,FALSE) -> CAJAS ARRANCADORAS | B56: CA-80 | C56: CAJA ARRANCADOR Y CONTROL INDUSTRIAL 80X50X25 | D56: 2 | E56: 84343.91 | F56: 6368.9 | G56: =E56+F56 -> 90712.81 | H56: =E56*D56 -> 168687.82 | I56: =F56*D56 -> 12737.8 | J56: =G56*D56 -> 181425.62 | K56: =J56/$J$303 -> 0.00011575388 | L56: =$K$373*K56/D56 -> 25889.166 | M56: =F56*$M$372 -> 41795.354 | N56: =G56+L56+M56 -> 158397.33 | O56: =N56*D56 -> 316794.66 | P56: =Q56/D56 -> 373318 | Q56: 746636 | R56: =O56/Q56 -> 0.42429599 | T56: =IFERROR(VLOOKUP(B56,[1]Todos!$A$2:$C$3021,3,FALSE),0) -> 8005.49 | U56: =T56-F56 -> 1636.59 | W56: =IFERROR(VLOOKUP(B56,[1]Todos!$A$2:$B$3021,2,FALSE),0) -> 84343.91 | X56: =W56-E56 -> 0
A57: =VLOOKUP(B57,Grupos!$A$2:$B$619,2,FALSE) -> CAJAS ARRANCADORAS | B57: CA-90 | C57: CAJA ARRANCADOR Y CONTROL INDUSTRIAL 90X50X25 | D57: 8 | E57: 94916.92 | F57: 4655.04 | G57: =E57+F57 -> 99571.96 | H57: =E57*D57 -> 759335.36 | I57: =F57*D57 -> 37240.32 | J57: =G57*D57 -> 796575.68 | K57: =J57/$J$303 -> 0.00050823431 | L57: =$K$373*K57/D57 -> 28417.541 | M57: =F57*$M$372 -> 30548.297 | N57: =G57+L57+M57 -> 158537.8 | O57: =N57*D57 -> 1268302.4 | P57: =Q57/D57 -> 364486.57 | Q57: 2915892.6 | R57: =O57/Q57 -> 0.43496197 | T57: =IFERROR(VLOOKUP(B57,[1]Todos!$A$2:$C$3021,3,FALSE),0) -> 5465.68 | U57: =T57-F57 -> 810.64 | W57: =IFERROR(VLOOKUP(B57,[1]Todos!$A$2:$B$3021,2,FALSE),0) -> 94916.92 | X57: =W57-E57 -> 0
